Workbook

Sheet Start Here
A1: FreshTurn Operations
A2: Everything for running the business in one file. Works in Excel and Google Sheets.
A4: HOW THE FILE WORKS
A5: Dark blue headers | B5: You type in these columns.
A6: Grey headers / grey cells | B6: Worked out automatically. Don't type in them.
A7: Dropdowns | B7: Most columns have a dropdown list (IDs, Y/N, statuses). Use them so the totals work.
A8: Example rows | B8: Rows marked 'EXAMPLE' show how to fill things in. Delete or overwrite them when you start for real.
A9: Door / key safe codes | B9: Never put codes in this file. Keep them in a password manager (e.g. Bitwarden, free) and share only with the cleaner who needs them.
A11: EVERY CLEAN
A12: 1. Cleans Log | B12: Add a row: date, property, cleaner, status. Charges and cleaner pay are calculated for you.
A13: 2. Stock | B13: Cleaner texts you the counts (or fills in the Stock form). Update 'Count now'. Anything at or below the reorder level turns red.
A14: 3. Damage | B14: Anything broken or missing? Add it to Damage the same day and send the host photos. Platforms only allow claims for 14 days.
A16: EVERY WEEK (Friday)
A17: 4. Cleaner Pay | B17: Add a row for each cleaner for the week that just ended. It totals their jobs. Pay them, then fill in 'Paid date'.
A18: 5. Shopping | B18: Check Stock for red items. Buy them (one shop for all properties), log each purchase in Purchases, keep the receipt photo.
A19: 6. Dashboard | B19: Check the alerts box. Everything in it should be zero or dealt with.
A21: EVERY MONTH (1st)
A22: 7. Invoices | B22: Add a row per host for last month. Use Invoice Builder to see the itemised list, copy it into your invoicing app (or PDF) and send.
A23: 8. Expenses | B23: Log running costs (insurance, phone, software, mileage). These reduce your tax bill.
A24: 9. Dashboard | B24: Pick last month: check profit, how much you keep per clean and your effective hourly rate.
A26: NEW PROPERTY
A27: Steps | B27: Add the host to Hosts, the property to Properties (price fills in from Settings, or type an agreed price), then add its stock items to Stock using the template rows.
A29: TABS
A30: Dashboard | B30: Monthly numbers, tax year totals, VAT threshold tracker and alerts.
A31: Cleans Log | B31: One row per clean. The heart of the system.
A32: Properties / Hosts / Cleaners | B32: Who and where.
A33: Stock / Supplies | B33: What each property should have, what it has now, and what everything costs.
A34: Purchases | B34: Everything you buy for a property. Marks what to recharge to the host (+10%) and checks approval and receipts.
A35: Damage | B35: Guest damage with claim deadlines.
A36: Invoices / Invoice Builder | B36: Monthly invoices per host and whether they're paid.
A37: Cleaner Pay | B37: Weekly pay per cleaner.
A38: Expenses | B38: Your running costs for tax.
A39: Price Calculator | B39: Work out a price for a new property from the hours it takes.
A40: Settings | B40: Prices, cleaner pay, markup, approval limits and other rules. Change them here and everything updates.

Sheet Dashboard
A1: Dashboard
A2: Pick a month and a tax year. UK tax years run 6 April to 5 April.
B4: Month | C4: 46296
B5: Tax year | C5: 2026/27
B7: THIS MONTH | E7: NEEDS ATTENTION NOW
B8: Completed cleans | C8: =COUNTIFS('Cleans Log'!$Q$5:$Q$1004,$C$4,'Cleans Log'!$D$5:$D$1004,"Completed") -> 3 | E8: Stock items to reorder | F8: =COUNTIF(Stock!$H$5:$H$504,"REORDER") -> 4
B9: Deep cleans | C9: =COUNTIFS('Cleans Log'!$Q$5:$Q$1004,$C$4,'Cleans Log'!$D$5:$D$1004,"Deep clean") -> 0 | E9: Stock not counted yet | F9: =COUNTIF(Stock!$H$5:$H$504,"Count it") -> 0
B10: Cleaning income | C10: =SUMIFS('Cleans Log'!$N$5:$N$1004,'Cleans Log'!$Q$5:$Q$1004,$C$4) -> 225 | E10: Damage: tell host / claim soon / missed | F10: =COUNTIF(Damage!$N$5:$N$304,"TELL HOST")+COUNTIF(Damage!$N$5:$N$304,"Claim soon")+COUNTIF(Damage!$N$5:$N$304,"Deadline passed") -> 0
B11: Items recharged to hosts | C11: =SUMIFS(Purchases!$N$5:$N$1004,Purchases!$P$5:$P$1004,$C$4) -> 7.04 | E11: Purchases needing approval or receipt | F11: =COUNTIFS(Purchases!$O$5:$O$1004,"<>OK",Purchases!$A$5:$A$1004,"<>") -> 0
B12: Total to invoice | C12: =C10+C11 -> 232.04 | E12: Cleaners to pay | F12: =COUNTIF('Cleaner Pay'!$J$5:$J$504,"PAY NOW") -> 0
B13: Cleaner pay | C13: =SUMIFS('Cleans Log'!$O$5:$O$1004,'Cleans Log'!$Q$5:$Q$1004,$C$4) -> 147.5 | E13: Overdue invoices | F13: =COUNTIF(Invoices!$L$7:$L$306,"OVERDUE") -> 0
B14: Purchases (cost) | C14: =SUMIFS(Purchases!$F$5:$F$1004,Purchases!$P$5:$P$1004,$C$4) -> 6.4 | E14: Money owed to you | F14: =Invoices!$B$4 -> 232.04
B15: Running costs | C15: =SUMIFS(Expenses!$G$5:$G$504,Expenses!$I$5:$I$504,$C$4) -> 13.4 | E15: Cleans with no photos sent | F15: =COUNTIFS('Cleans Log'!$D$5:$D$1004,"Completed",'Cleans Log'!$J$5:$J$1004,"<>Y") -> 0
B16: PROFIT | C16: =C12-C13-C14-C15 -> 64.74
B17: You keep per clean (after cleaner pay) | C17: =IFERROR((C10-C13)/(C8+C9),0) -> 25.833333 | E17: TAX YEAR (for Self Assessment)
B18: Hours cleaned | C18: =SUMIFS('Cleans Log'!$L$5:$L$1004,'Cleans Log'!$Q$5:$Q$1004,$C$4) -> 7.5833333 | E18: Income | F18: =SUMIFS('Cleans Log'!$N$5:$N$1004,'Cleans Log'!$T$5:$T$1004,$C$5)+SUMIFS(Purchases!$N$5:$N$1004,Purchases!$R$5:$R$1004,$C$5) -> 232.04
B19: Income per cleaning hour | C19: =IFERROR(C10/C18,0) -> 29.67033 | E19: Cleaner pay | F19: =SUMIFS('Cleans Log'!$O$5:$O$1004,'Cleans Log'!$T$5:$T$1004,$C$5) -> 147.5
E20: Purchases | F20: =SUMIFS(Purchases!$F$5:$F$1004,Purchases!$R$5:$R$1004,$C$5) -> 6.4
E21: Running costs (incl. mileage) | F21: =SUMIFS(Expenses!$G$5:$G$504,Expenses!$H$5:$H$504,$C$5) -> 13.4
B22: BY PROPERTY (this month) | C22: You keep (£) | E22: Profit | F22: =F18-F19-F20-F21 -> 64.74
B23: =IF(Properties!$A$5="","",Properties!$A$5&" "&Properties!$B$5) -> P001 First client (EXAMPLE) | C23: =IF(Properties!$A$5="","",SUMIFS('Cleans Log'!$P$5:$P$1004,'Cleans Log'!$B$5:$B$1004,Properties!$A$5,'Cleans Log'!$Q$5:$Q$1004,$C$4)) -> 77.5 | E23: Put aside for tax | F23: =MAX(0,F22)*Settings!$B$14 -> 16.185
B24: =IF(Properties!$A$6="","",Properties!$A$6&" "&Properties!$B$6) | C24: =IF(Properties!$A$6="","",SUMIFS('Cleans Log'!$P$5:$P$1004,'Cleans Log'!$B$5:$B$1004,Properties!$A$6,'Cleans Log'!$Q$5:$Q$1004,$C$4))
B25: =IF(Properties!$A$7="","",Properties!$A$7&" "&Properties!$B$7) | C25: =IF(Properties!$A$7="","",SUMIFS('Cleans Log'!$P$5:$P$1004,'Cleans Log'!$B$5:$B$1004,Properties!$A$7,'Cleans Log'!$Q$5:$Q$1004,$C$4)) | E25: VAT THRESHOLD (rolling 12 months)
B26: =IF(Properties!$A$8="","",Properties!$A$8&" "&Properties!$B$8) | C26: =IF(Properties!$A$8="","",SUMIFS('Cleans Log'!$P$5:$P$1004,'Cleans Log'!$B$5:$B$1004,Properties!$A$8,'Cleans Log'!$Q$5:$Q$1004,$C$4)) | E26: Income in the last 12 months | F26: =SUMIFS('Cleans Log'!$N$5:$N$1004,'Cleans Log'!$A$5:$A$1004,">"&EDATE(TODAY(),-12))+SUMIFS(Purchases!$N$5:$N$1004,Purchases!$A$5:$A$1004,">"&EDATE(TODAY(),-12)) -> 232.04
B27: =IF(Properties!$A$9="","",Properties!$A$9&" "&Properties!$B$9) | C27: =IF(Properties!$A$9="","",SUMIFS('Cleans Log'!$P$5:$P$1004,'Cleans Log'!$B$5:$B$1004,Properties!$A$9,'Cleans Log'!$Q$5:$Q$1004,$C$4)) | E27: % of VAT threshold | F27: =IFERROR(F26/Settings!$B$15,0) -> 0.0025782222
B28: =IF(Properties!$A$10="","",Properties!$A$10&" "&Properties!$B$10) | C28: =IF(Properties!$A$10="","",SUMIFS('Cleans Log'!$P$5:$P$1004,'Cleans Log'!$B$5:$B$1004,Properties!$A$10,'Cleans Log'!$Q$5:$Q$1004,$C$4)) | E28: What to do | F28: =IF(F27>=1,"Register for VAT now (within 30 days)",IF(F27>=0.8,"Getting close: talk to an accountant","Fine")) -> Fine
B29: =IF(Properties!$A$11="","",Properties!$A$11&" "&Properties!$B$11) | C29: =IF(Properties!$A$11="","",SUMIFS('Cleans Log'!$P$5:$P$1004,'Cleans Log'!$B$5:$B$1004,Properties!$A$11,'Cleans Log'!$Q$5:$Q$1004,$C$4))
B30: =IF(Properties!$A$12="","",Properties!$A$12&" "&Properties!$B$12) | C30: =IF(Properties!$A$12="","",SUMIFS('Cleans Log'!$P$5:$P$1004,'Cleans Log'!$B$5:$B$1004,Properties!$A$12,'Cleans Log'!$Q$5:$Q$1004,$C$4))
B31: =IF(Properties!$A$13="","",Properties!$A$13&" "&Properties!$B$13) | C31: =IF(Properties!$A$13="","",SUMIFS('Cleans Log'!$P$5:$P$1004,'Cleans Log'!$B$5:$B$1004,Properties!$A$13,'Cleans Log'!$Q$5:$Q$1004,$C$4))
B32: =IF(Properties!$A$14="","",Properties!$A$14&" "&Properties!$B$14) | C32: =IF(Properties!$A$14="","",SUMIFS('Cleans Log'!$P$5:$P$1004,'Cleans Log'!$B$5:$B$1004,Properties!$A$14,'Cleans Log'!$Q$5:$Q$1004,$C$4))
B33: =IF(Properties!$A$15="","",Properties!$A$15&" "&Properties!$B$15) | C33: =IF(Properties!$A$15="","",SUMIFS('Cleans Log'!$P$5:$P$1004,'Cleans Log'!$B$5:$B$1004,Properties!$A$15,'Cleans Log'!$Q$5:$Q$1004,$C$4))
B34: =IF(Properties!$A$16="","",Properties!$A$16&" "&Properties!$B$16) | C34: =IF(Properties!$A$16="","",SUMIFS('Cleans Log'!$P$5:$P$1004,'Cleans Log'!$B$5:$B$1004,Properties!$A$16,'Cleans Log'!$Q$5:$Q$1004,$C$4))
B35: =IF(Properties!$A$17="","",Properties!$A$17&" "&Properties!$B$17) | C35: =IF(Properties!$A$17="","",SUMIFS('Cleans Log'!$P$5:$P$1004,'Cleans Log'!$B$5:$B$1004,Properties!$A$17,'Cleans Log'!$Q$5:$Q$1004,$C$4))
B36: =IF(Properties!$A$18="","",Properties!$A$18&" "&Properties!$B$18) | C36: =IF(Properties!$A$18="","",SUMIFS('Cleans Log'!$P$5:$P$1004,'Cleans Log'!$B$5:$B$1004,Properties!$A$18,'Cleans Log'!$Q$5:$Q$1004,$C$4))
B37: =IF(Properties!$A$19="","",Properties!$A$19&" "&Properties!$B$19) | C37: =IF(Properties!$A$19="","",SUMIFS('Cleans Log'!$P$5:$P$1004,'Cleans Log'!$B$5:$B$1004,Properties!$A$19,'Cleans Log'!$Q$5:$Q$1004,$C$4))

Sheet Cleans Log
A1: Cleans Log
A2: One row per visit. Status: Completed, Deep clean, Late cancel (host charged 50%), Cancelled (no charge), Re-clean (free fix).
A4: Date | B4: Prop ID | C4: Cleaner ID | D4: Status | E4: Start | F4: Finish | G4: Rush (Y/N) | H4: Hot tub (Y/N) | I4: Other extra (£) | J4: Photos sent (Y/N) | K4: Issues / notes | L4: Hours | M4: Host ID | N4: Charge to host (£) | O4: Cleaner pay (£) | P4: You keep (£) | Q4: Month | R4: Work week ends (Fri) | S4: Invoice line # | T4: Tax year
A5: 46298 | B5: P001 | C5: C001 | D5: Completed | E5: 0.46875 | F5: 0.57638889 | G5: N | H5: N | J5: Y | K5: EXAMPLE | L5: =IF(OR($E5="",$F5=""),"",MOD($F5-$E5,1)*24) -> 2.5833333 | M5: =IF($B5="","",IFERROR(INDEX(Properties!$D$5:$D$104,MATCH($B5,Properties!$A$5:$A$104,0)),"?")) -> H001 | N5: =IF($B5="","",IFERROR(IF($D5="Completed",INDEX(Properties!$I$5:$I$104,MATCH($B5,Properties!$A$5:$A$104,0))*(1+IF($G5="Y",Settings!$B$8,0))+IF($H5="Y",Settings!$B$7,0)+N($I5),IF($D5="Deep clean",INDEX(Settings!$E$22:$E$26,MATCH(MIN(INDEX(Properties!$E$5:$E$104,MATCH($B5,Properties!$A$5:$A$104,0)),4),Settings!$A$22:$A$26,0))+N($I5),IF($D5="Late cancel",INDEX(Properties!$I$5:$I$104,MATCH($B5,Properties!$A$5:$A$104,0))*Settings!$B$10,0))),0)) -> 60 | O5: =IF($B5="","",IFERROR(IF($D5="Completed",INDEX(Properties!$L$5:$L$104,MATCH($B5,Properties!$A$5:$A$104,0))+IF($G5="Y",INDEX(Properties!$I$5:$I$104,MATCH($B5,Properties!$A$5:$A$104,0))*Settings!$B$8*Settings!$B$9,0)+IF($H5="Y",Settings!$B$7*Settings!$B$9,0)+N($I5)*Settings!$B$9,IF($D5="Deep clean",INDEX(Settings!$E$22:$E$26,MATCH(MIN(INDEX(Properties!$E$5:$E$104,MATCH($B5,Properties!$A$5:$A$104,0)),4),Settings!$A$22:$A$26,0))*Settings!$B$19+N($I5)*Settings!$B$9,IF($D5="Late cancel",INDEX(Properties!$L$5:$L$104,MATCH($B5,Properties!$A$5:$A$104,0))*Settings!$B$11,0))),0)) -> 40 | P5: =IF($B5="","",$N5-$O5) -> 20 | Q5: =IF($A5="","",DATE(YEAR($A5),MONTH($A5),1)) -> 46296 | R5: =IF($A5="","",$A5+MOD(6-WEEKDAY($A5),7)) -> 46304 | S5: =IF($B5="","",IF(AND($M5='Invoice Builder'!$C$5,$Q5='Invoice Builder'!$C$6,N($N5)>0),COUNTIFS($M$5:$M5,'Invoice Builder'!$C$5,$Q$5:$Q5,'Invoice Builder'!$C$6,$N$5:$N5,">0"),"")) -> 1 | T5: =IF($A5="","",IF($A5>=DATE(YEAR($A5),4,6),YEAR($A5)&"/"&RIGHT(YEAR($A5)+1,2),YEAR($A5)-1&"/"&RIGHT(YEAR($A5),2))) -> 2026/27
A6: 46305 | B6: P001 | C6: C001 | D6: Completed | E6: 0.46180556 | F6: 0.56597222 | G6: N | H6: N | J6: Y | K6: EXAMPLE: bulb replaced | L6: =IF(OR($E6="",$F6=""),"",MOD($F6-$E6,1)*24) -> 2.5 | M6: =IF($B6="","",IFERROR(INDEX(Properties!$D$5:$D$104,MATCH($B6,Properties!$A$5:$A$104,0)),"?")) -> H001 | N6: =IF($B6="","",IFERROR(IF($D6="Completed",INDEX(Properties!$I$5:$I$104,MATCH($B6,Properties!$A$5:$A$104,0))*(1+IF($G6="Y",Settings!$B$8,0))+IF($H6="Y",Settings!$B$7,0)+N($I6),IF($D6="Deep clean",INDEX(Settings!$E$22:$E$26,MATCH(MIN(INDEX(Properties!$E$5:$E$104,MATCH($B6,Properties!$A$5:$A$104,0)),4),Settings!$A$22:$A$26,0))+N($I6),IF($D6="Late cancel",INDEX(Properties!$I$5:$I$104,MATCH($B6,Properties!$A$5:$A$104,0))*Settings!$B$10,0))),0)) -> 60 | O6: =IF($B6="","",IFERROR(IF($D6="Completed",INDEX(Properties!$L$5:$L$104,MATCH($B6,Properties!$A$5:$A$104,0))+IF($G6="Y",INDEX(Properties!$I$5:$I$104,MATCH($B6,Properties!$A$5:$A$104,0))*Settings!$B$8*Settings!$B$9,0)+IF($H6="Y",Settings!$B$7*Settings!$B$9,0)+N($I6)*Settings!$B$9,IF($D6="Deep clean",INDEX(Settings!$E$22:$E$26,MATCH(MIN(INDEX(Properties!$E$5:$E$104,MATCH($B6,Properties!$A$5:$A$104,0)),4),Settings!$A$22:$A$26,0))*Settings!$B$19+N($I6)*Settings!$B$9,IF($D6="Late cancel",INDEX(Properties!$L$5:$L$104,MATCH($B6,Properties!$A$5:$A$104,0))*Settings!$B$11,0))),0)) -> 40 | P6: =IF($B6="","",$N6-$O6) -> 20 | Q6: =IF($A6="","",DATE(YEAR($A6),MONTH($A6),1)) -> 46296 | R6: =IF($A6="","",$A6+MOD(6-WEEKDAY($A6),7)) -> 46311 | S6: =IF($B6="","",IF(AND($M6='Invoice Builder'!$C$5,$Q6='Invoice Builder'!$C$6,N($N6)>0),COUNTIFS($M$5:$M6,'Invoice Builder'!$C$5,$Q$5:$Q6,'Invoice Builder'!$C$6,$N$5:$N6,">0"),"")) -> 2 | T6: =IF($A6="","",IF($A6>=DATE(YEAR($A6),4,6),YEAR($A6)&"/"&RIGHT(YEAR($A6)+1,2),YEAR($A6)-1&"/"&RIGHT(YEAR($A6),2))) -> 2026/27
A7: 46312 | B7: P001 | C7: C002 | D7: Completed | E7: 0.52083333 | F7: 0.625 | G7: Y | H7: N | J7: Y | K7: EXAMPLE: booked same morning | L7: =IF(OR($E7="",$F7=""),"",MOD($F7-$E7,1)*24) -> 2.5 | M7: =IF($B7="","",IFERROR(INDEX(Properties!$D$5:$D$104,MATCH($B7,Properties!$A$5:$A$104,0)),"?")) -> H001 | N7: =IF($B7="","",IFERROR(IF($D7="Completed",INDEX(Properties!$I$5:$I$104,MATCH($B7,Properties!$A$5:$A$104,0))*(1+IF($G7="Y",Settings!$B$8,0))+IF($H7="Y",Settings!$B$7,0)+N($I7),IF($D7="Deep clean",INDEX(Settings!$E$22:$E$26,MATCH(MIN(INDEX(Properties!$E$5:$E$104,MATCH($B7,Properties!$A$5:$A$104,0)),4),Settings!$A$22:$A$26,0))+N($I7),IF($D7="Late cancel",INDEX(Properties!$I$5:$I$104,MATCH($B7,Properties!$A$5:$A$104,0))*Settings!$B$10,0))),0)) -> 75 | O7: =IF($B7="","",IFERROR(IF($D7="Completed",INDEX(Properties!$L$5:$L$104,MATCH($B7,Properties!$A$5:$A$104,0))+IF($G7="Y",INDEX(Properties!$I$5:$I$104,MATCH($B7,Properties!$A$5:$A$104,0))*Settings!$B$8*Settings!$B$9,0)+IF($H7="Y",Settings!$B$7*Settings!$B$9,0)+N($I7)*Settings!$B$9,IF($D7="Deep clean",INDEX(Settings!$E$22:$E$26,MATCH(MIN(INDEX(Properties!$E$5:$E$104,MATCH($B7,Properties!$A$5:$A$104,0)),4),Settings!$A$22:$A$26,0))*Settings!$B$19+N($I7)*Settings!$B$9,IF($D7="Late cancel",INDEX(Properties!$L$5:$L$104,MATCH($B7,Properties!$A$5:$A$104,0))*Settings!$B$11,0))),0)) -> 47.5 | P7: =IF($B7="","",$N7-$O7) -> 27.5 | Q7: =IF($A7="","",DATE(YEAR($A7),MONTH($A7),1)) -> 46296 | R7: =IF($A7="","",$A7+MOD(6-WEEKDAY($A7),7)) -> 46318 | S7: =IF($B7="","",IF(AND($M7='Invoice Builder'!$C$5,$Q7='Invoice Builder'!$C$6,N($N7)>0),COUNTIFS($M$5:$M7,'Invoice Builder'!$C$5,$Q$5:$Q7,'Invoice Builder'!$C$6,$N$5:$N7,">0"),"")) -> 3 | T7: =IF($A7="","",IF($A7>=DATE(YEAR($A7),4,6),YEAR($A7)&"/"&RIGHT(YEAR($A7)+1,2),YEAR($A7)-1&"/"&RIGHT(YEAR($A7),2))) -> 2026/27
A8: 46319 | B8: P001 | C8: C001 | D8: Late cancel | G8: N | H8: N | K8: EXAMPLE: guest extended, host told us at 9am | L8: =IF(OR($E8="",$F8=""),"",MOD($F8-$E8,1)*24) | M8: =IF($B8="","",IFERROR(INDEX(Properties!$D$5:$D$104,MATCH($B8,Properties!$A$5:$A$104,0)),"?")) -> H001 | N8: =IF($B8="","",IFERROR(IF($D8="Completed",INDEX(Properties!$I$5:$I$104,MATCH($B8,Properties!$A$5:$A$104,0))*(1+IF($G8="Y",Settings!$B$8,0))+IF($H8="Y",Settings!$B$7,0)+N($I8),IF($D8="Deep clean",INDEX(Settings!$E$22:$E$26,MATCH(MIN(INDEX(Properties!$E$5:$E$104,MATCH($B8,Properties!$A$5:$A$104,0)),4),Settings!$A$22:$A$26,0))+N($I8),IF($D8="Late cancel",INDEX(Properties!$I$5:$I$104,MATCH($B8,Properties!$A$5:$A$104,0))*Settings!$B$10,0))),0)) -> 30 | O8: =IF($B8="","",IFERROR(IF($D8="Completed",INDEX(Properties!$L$5:$L$104,MATCH($B8,Properties!$A$5:$A$104,0))+IF($G8="Y",INDEX(Properties!$I$5:$I$104,MATCH($B8,Properties!$A$5:$A$104,0))*Settings!$B$8*Settings!$B$9,0)+IF($H8="Y",Settings!$B$7*Settings!$B$9,0)+N($I8)*Settings!$B$9,IF($D8="Deep clean",INDEX(Settings!$E$22:$E$26,MATCH(MIN(INDEX(Properties!$E$5:$E$104,MATCH($B8,Properties!$A$5:$A$104,0)),4),Settings!$A$22:$A$26,0))*Settings!$B$19+N($I8)*Settings!$B$9,IF($D8="Late cancel",INDEX(Properties!$L$5:$L$104,MATCH($B8,Properties!$A$5:$A$104,0))*Settings!$B$11,0))),0)) -> 20 | P8: =IF($B8="","",$N8-$O8) -> 10 | Q8: =IF($A8="","",DATE(YEAR($A8),MONTH($A8),1)) -> 46296 | R8: =IF($A8="","",$A8+MOD(6-WEEKDAY($A8),7)) -> 46325 | S8: =IF($B8="","",IF(AND($M8='Invoice Builder'!$C$5,$Q8='Invoice Builder'!$C$6,N($N8)>0),COUNTIFS($M$5:$M8,'Invoice Builder'!$C$5,$Q$5:$Q8,'Invoice Builder'!$C$6,$N$5:$N8,">0"),"")) -> 4 | T8: =IF($A8="","",IF($A8>=DATE(YEAR($A8),4,6),YEAR($A8)&"/"&RIGHT(YEAR($A8)+1,2),YEAR($A8)-1&"/"&RIGHT(YEAR($A8),2))) -> 2026/27
L9: =IF(OR($E9="",$F9=""),"",MOD($F9-$E9,1)*24) | M9: =IF($B9="","",IFERROR(INDEX(Properties!$D$5:$D$104,MATCH($B9,Properties!$A$5:$A$104,0)),"?")) | N9: =IF($B9="","",IFERROR(IF($D9="Completed",INDEX(Properties!$I$5:$I$104,MATCH($B9,Properties!$A$5:$A$104,0))*(1+IF($G9="Y",Settings!$B$8,0))+IF($H9="Y",Settings!$B$7,0)+N($I9),IF($D9="Deep clean",INDEX(Settings!$E$22:$E$26,MATCH(MIN(INDEX(Properties!$E$5:$E$104,MATCH($B9,Properties!$A$5:$A$104,0)),4),Settings!$A$22:$A$26,0))+N($I9),IF($D9="Late cancel",INDEX(Properties!$I$5:$I$104,MATCH($B9,Properties!$A$5:$A$104,0))*Settings!$B$10,0))),0)) | O9: =IF($B9="","",IFERROR(IF($D9="Completed",INDEX(Properties!$L$5:$L$104,MATCH($B9,Properties!$A$5:$A$104,0))+IF($G9="Y",INDEX(Properties!$I$5:$I$104,MATCH($B9,Properties!$A$5:$A$104,0))*Settings!$B$8*Settings!$B$9,0)+IF($H9="Y",Settings!$B$7*Settings!$B$9,0)+N($I9)*Settings!$B$9,IF($D9="Deep clean",INDEX(Settings!$E$22:$E$26,MATCH(MIN(INDEX(Properties!$E$5:$E$104,MATCH($B9,Properties!$A$5:$A$104,0)),4),Settings!$A$22:$A$26,0))*Settings!$B$19+N($I9)*Settings!$B$9,IF($D9="Late cancel",INDEX(Properties!$L$5:$L$104,MATCH($B9,Properties!$A$5:$A$104,0))*Settings!$B$11,0))),0)) | P9: =IF($B9="","",$N9-$O9) | Q9: =IF($A9="","",DATE(YEAR($A9),MONTH($A9),1)) | R9: =IF($A9="","",$A9+MOD(6-WEEKDAY($A9),7)) | S9: =IF($B9="","",IF(AND($M9='Invoice Builder'!$C$5,$Q9='Invoice Builder'!$C$6,N($N9)>0),COUNTIFS($M$5:$M9,'Invoice Builder'!$C$5,$Q$5:$Q9,'Invoice Builder'!$C$6,$N$5:$N9,">0"),"")) | T9: =IF($A9="","",IF($A9>=DATE(YEAR($A9),4,6),YEAR($A9)&"/"&RIGHT(YEAR($A9)+1,2),YEAR($A9)-1&"/"&RIGHT(YEAR($A9),2)))
L10: =IF(OR($E10="",$F10=""),"",MOD($F10-$E10,1)*24) | M10: =IF($B10="","",IFERROR(INDEX(Properties!$D$5:$D$104,MATCH($B10,Properties!$A$5:$A$104,0)),"?")) | N10: =IF($B10="","",IFERROR(IF($D10="Completed",INDEX(Properties!$I$5:$I$104,MATCH($B10,Properties!$A$5:$A$104,0))*(1+IF($G10="Y",Settings!$B$8,0))+IF($H10="Y",Settings!$B$7,0)+N($I10),IF($D10="Deep clean",INDEX(Settings!$E$22:$E$26,MATCH(MIN(INDEX(Properties!$E$5:$E$104,MATCH($B10,Properties!$A$5:$A$104,0)),4),Settings!$A$22:$A$26,0))+N($I10),IF($D10="Late cancel",INDEX(Properties!$I$5:$I$104,MATCH($B10,Properties!$A$5:$A$104,0))*Settings!$B$10,0))),0)) | O10: =IF($B10="","",IFERROR(IF($D10="Completed",INDEX(Properties!$L$5:$L$104,MATCH($B10,Properties!$A$5:$A$104,0))+IF($G10="Y",INDEX(Properties!$I$5:$I$104,MATCH($B10,Properties!$A$5:$A$104,0))*Settings!$B$8*Settings!$B$9,0)+IF($H10="Y",Settings!$B$7*Settings!$B$9,0)+N($I10)*Settings!$B$9,IF($D10="Deep clean",INDEX(Settings!$E$22:$E$26,MATCH(MIN(INDEX(Properties!$E$5:$E$104,MATCH($B10,Properties!$A$5:$A$104,0)),4),Settings!$A$22:$A$26,0))*Settings!$B$19+N($I10)*Settings!$B$9,IF($D10="Late cancel",INDEX(Properties!$L$5:$L$104,MATCH($B10,Properties!$A$5:$A$104,0))*Settings!$B$11,0))),0)) | P10: =IF($B10="","",$N10-$O10) | Q10: =IF($A10="","",DATE(YEAR($A10),MONTH($A10),1)) | R10: =IF($A10="","",$A10+MOD(6-WEEKDAY($A10),7)) | S10: =IF($B10="","",IF(AND($M10='Invoice Builder'!$C$5,$Q10='Invoice Builder'!$C$6,N($N10)>0),COUNTIFS($M$5:$M10,'Invoice Builder'!$C$5,$Q$5:$Q10,'Invoice Builder'!$C$6,$N$5:$N10,">0"),"")) | T10: =IF($A10="","",IF($A10>=DATE(YEAR($A10),4,6),YEAR($A10)&"/"&RIGHT(YEAR($A10)+1,2),YEAR($A10)-1&"/"&RIGHT(YEAR($A10),2)))
L11: =IF(OR($E11="",$F11=""),"",MOD($F11-$E11,1)*24) | M11: =IF($B11="","",IFERROR(INDEX(Properties!$D$5:$D$104,MATCH($B11,Properties!$A$5:$A$104,0)),"?")) | N11: =IF($B11="","",IFERROR(IF($D11="Completed",INDEX(Properties!$I$5:$I$104,MATCH($B11,Properties!$A$5:$A$104,0))*(1+IF($G11="Y",Settings!$B$8,0))+IF($H11="Y",Settings!$B$7,0)+N($I11),IF($D11="Deep clean",INDEX(Settings!$E$22:$E$26,MATCH(MIN(INDEX(Properties!$E$5:$E$104,MATCH($B11,Properties!$A$5:$A$104,0)),4),Settings!$A$22:$A$26,0))+N($I11),IF($D11="Late cancel",INDEX(Properties!$I$5:$I$104,MATCH($B11,Properties!$A$5:$A$104,0))*Settings!$B$10,0))),0)) | O11: =IF($B11="","",IFERROR(IF($D11="Completed",INDEX(Properties!$L$5:$L$104,MATCH($B11,Properties!$A$5:$A$104,0))+IF($G11="Y",INDEX(Properties!$I$5:$I$104,MATCH($B11,Properties!$A$5:$A$104,0))*Settings!$B$8*Settings!$B$9,0)+IF($H11="Y",Settings!$B$7*Settings!$B$9,0)+N($I11)*Settings!$B$9,IF($D11="Deep clean",INDEX(Settings!$E$22:$E$26,MATCH(MIN(INDEX(Properties!$E$5:$E$104,MATCH($B11,Properties!$A$5:$A$104,0)),4),Settings!$A$22:$A$26,0))*Settings!$B$19+N($I11)*Settings!$B$9,IF($D11="Late cancel",INDEX(Properties!$L$5:$L$104,MATCH($B11,Properties!$A$5:$A$104,0))*Settings!$B$11,0))),0)) | P11: =IF($B11="","",$N11-$O11) | Q11: =IF($A11="","",DATE(YEAR($A11),MONTH($A11),1)) | R11: =IF($A11="","",$A11+MOD(6-WEEKDAY($A11),7)) | S11: =IF($B11="","",IF(AND($M11='Invoice Builder'!$C$5,$Q11='Invoice Builder'!$C$6,N($N11)>0),COUNTIFS($M$5:$M11,'Invoice Builder'!$C$5,$Q$5:$Q11,'Invoice Builder'!$C$6,$N$5:$N11,">0"),"")) | T11: =IF($A11="","",IF($A11>=DATE(YEAR($A11),4,6),YEAR($A11)&"/"&RIGHT(YEAR($A11)+1,2),YEAR($A11)-1&"/"&RIGHT(YEAR($A11),2)))
L12: =IF(OR($E12="",$F12=""),"",MOD($F12-$E12,1)*24) | M12: =IF($B12="","",IFERROR(INDEX(Properties!$D$5:$D$104,MATCH($B12,Properties!$A$5:$A$104,0)),"?")) | N12: =IF($B12="","",IFERROR(IF($D12="Completed",INDEX(Properties!$I$5:$I$104,MATCH($B12,Properties!$A$5:$A$104,0))*(1+IF($G12="Y",Settings!$B$8,0))+IF($H12="Y",Settings!$B$7,0)+N($I12),IF($D12="Deep clean",INDEX(Settings!$E$22:$E$26,MATCH(MIN(INDEX(Properties!$E$5:$E$104,MATCH($B12,Properties!$A$5:$A$104,0)),4),Settings!$A$22:$A$26,0))+N($I12),IF($D12="Late cancel",INDEX(Properties!$I$5:$I$104,MATCH($B12,Properties!$A$5:$A$104,0))*Settings!$B$10,0))),0)) | O12: =IF($B12="","",IFERROR(IF($D12="Completed",INDEX(Properties!$L$5:$L$104,MATCH($B12,Properties!$A$5:$A$104,0))+IF($G12="Y",INDEX(Properties!$I$5:$I$104,MATCH($B12,Properties!$A$5:$A$104,0))*Settings!$B$8*Settings!$B$9,0)+IF($H12="Y",Settings!$B$7*Settings!$B$9,0)+N($I12)*Settings!$B$9,IF($D12="Deep clean",INDEX(Settings!$E$22:$E$26,MATCH(MIN(INDEX(Properties!$E$5:$E$104,MATCH($B12,Properties!$A$5:$A$104,0)),4),Settings!$A$22:$A$26,0))*Settings!$B$19+N($I12)*Settings!$B$9,IF($D12="Late cancel",INDEX(Properties!$L$5:$L$104,MATCH($B12,Properties!$A$5:$A$104,0))*Settings!$B$11,0))),0)) | P12: =IF($B12="","",$N12-$O12) | Q12: =IF($A12="","",DATE(YEAR($A12),MONTH($A12),1)) | R12: =IF($A12="","",$A12+MOD(6-WEEKDAY($A12),7)) | S12: =IF($B12="","",IF(AND($M12='Invoice Builder'!$C$5,$Q12='Invoice Builder'!$C$6,N($N12)>0),COUNTIFS($M$5:$M12,'Invoice Builder'!$C$5,$Q$5:$Q12,'Invoice Builder'!$C$6,$N$5:$N12,">0"),"")) | T12: =IF($A12="","",IF($A12>=DATE(YEAR($A12),4,6),YEAR($A12)&"/"&RIGHT(YEAR($A12)+1,2),YEAR($A12)-1&"/"&RIGHT(YEAR($A12),2)))
L13: =IF(OR($E13="",$F13=""),"",MOD($F13-$E13,1)*24) | M13: =IF($B13="","",IFERROR(INDEX(Properties!$D$5:$D$104,MATCH($B13,Properties!$A$5:$A$104,0)),"?")) | N13: =IF($B13="","",IFERROR(IF($D13="Completed",INDEX(Properties!$I$5:$I$104,MATCH($B13,Properties!$A$5:$A$104,0))*(1+IF($G13="Y",Settings!$B$8,0))+IF($H13="Y",Settings!$B$7,0)+N($I13),IF($D13="Deep clean",INDEX(Settings!$E$22:$E$26,MATCH(MIN(INDEX(Properties!$E$5:$E$104,MATCH($B13,Properties!$A$5:$A$104,0)),4),Settings!$A$22:$A$26,0))+N($I13),IF($D13="Late cancel",INDEX(Properties!$I$5:$I$104,MATCH($B13,Properties!$A$5:$A$104,0))*Settings!$B$10,0))),0)) | O13: =IF($B13="","",IFERROR(IF($D13="Completed",INDEX(Properties!$L$5:$L$104,MATCH($B13,Properties!$A$5:$A$104,0))+IF($G13="Y",INDEX(Properties!$I$5:$I$104,MATCH($B13,Properties!$A$5:$A$104,0))*Settings!$B$8*Settings!$B$9,0)+IF($H13="Y",Settings!$B$7*Settings!$B$9,0)+N($I13)*Settings!$B$9,IF($D13="Deep clean",INDEX(Settings!$E$22:$E$26,MATCH(MIN(INDEX(Properties!$E$5:$E$104,MATCH($B13,Properties!$A$5:$A$104,0)),4),Settings!$A$22:$A$26,0))*Settings!$B$19+N($I13)*Settings!$B$9,IF($D13="Late cancel",INDEX(Properties!$L$5:$L$104,MATCH($B13,Properties!$A$5:$A$104,0))*Settings!$B$11,0))),0)) | P13: =IF($B13="","",$N13-$O13) | Q13: =IF($A13="","",DATE(YEAR($A13),MONTH($A13),1)) | R13: =IF($A13="","",$A13+MOD(6-WEEKDAY($A13),7)) | S13: =IF($B13="","",IF(AND($M13='Invoice Builder'!$C$5,$Q13='Invoice Builder'!$C$6,N($N13)>0),COUNTIFS($M$5:$M13,'Invoice Builder'!$C$5,$Q$5:$Q13,'Invoice Builder'!$C$6,$N$5:$N13,">0"),"")) | T13: =IF($A13="","",IF($A13>=DATE(YEAR($A13),4,6),YEAR($A13)&"/"&RIGHT(YEAR($A13)+1,2),YEAR($A13)-1&"/"&RIGHT(YEAR($A13),2)))
L14: =IF(OR($E14="",$F14=""),"",MOD($F14-$E14,1)*24) | M14: =IF($B14="","",IFERROR(INDEX(Properties!$D$5:$D$104,MATCH($B14,Properties!$A$5:$A$104,0)),"?")) | N14: =IF($B14="","",IFERROR(IF($D14="Completed",INDEX(Properties!$I$5:$I$104,MATCH($B14,Properties!$A$5:$A$104,0))*(1+IF($G14="Y",Settings!$B$8,0))+IF($H14="Y",Settings!$B$7,0)+N($I14),IF($D14="Deep clean",INDEX(Settings!$E$22:$E$26,MATCH(MIN(INDEX(Properties!$E$5:$E$104,MATCH($B14,Properties!$A$5:$A$104,0)),4),Settings!$A$22:$A$26,0))+N($I14),IF($D14="Late cancel",INDEX(Properties!$I$5:$I$104,MATCH($B14,Properties!$A$5:$A$104,0))*Settings!$B$10,0))),0)) | O14: =IF($B14="","",IFERROR(IF($D14="Completed",INDEX(Properties!$L$5:$L$104,MATCH($B14,Properties!$A$5:$A$104,0))+IF($G14="Y",INDEX(Properties!$I$5:$I$104,MATCH($B14,Properties!$A$5:$A$104,0))*Settings!$B$8*Settings!$B$9,0)+IF($H14="Y",Settings!$B$7*Settings!$B$9,0)+N($I14)*Settings!$B$9,IF($D14="Deep clean",INDEX(Settings!$E$22:$E$26,MATCH(MIN(INDEX(Properties!$E$5:$E$104,MATCH($B14,Properties!$A$5:$A$104,0)),4),Settings!$A$22:$A$26,0))*Settings!$B$19+N($I14)*Settings!$B$9,IF($D14="Late cancel",INDEX(Properties!$L$5:$L$104,MATCH($B14,Properties!$A$5:$A$104,0))*Settings!$B$11,0))),0)) | P14: =IF($B14="","",$N14-$O14) | Q14: =IF($A14="","",DATE(YEAR($A14),MONTH($A14),1)) | R14: =IF($A14="","",$A14+MOD(6-WEEKDAY($A14),7)) | S14: =IF($B14="","",IF(AND($M14='Invoice Builder'!$C$5,$Q14='Invoice Builder'!$C$6,N($N14)>0),COUNTIFS($M$5:$M14,'Invoice Builder'!$C$5,$Q$5:$Q14,'Invoice Builder'!$C$6,$N$5:$N14,">0"),"")) | T14: =IF($A14="","",IF($A14>=DATE(YEAR($A14),4,6),YEAR($A14)&"/"&RIGHT(YEAR($A14)+1,2),YEAR($A14)-1&"/"&RIGHT(YEAR($A14),2)))
L15: =IF(OR($E15="",$F15=""),"",MOD($F15-$E15,1)*24) | M15: =IF($B15="","",IFERROR(INDEX(Properties!$D$5:$D$104,MATCH($B15,Properties!$A$5:$A$104,0)),"?")) | N15: =IF($B15="","",IFERROR(IF($D15="Completed",INDEX(Properties!$I$5:$I$104,MATCH($B15,Properties!$A$5:$A$104,0))*(1+IF($G15="Y",Settings!$B$8,0))+IF($H15="Y",Settings!$B$7,0)+N($I15),IF($D15="Deep clean",INDEX(Settings!$E$22:$E$26,MATCH(MIN(INDEX(Properties!$E$5:$E$104,MATCH($B15,Properties!$A$5:$A$104,0)),4),Settings!$A$22:$A$26,0))+N($I15),IF($D15="Late cancel",INDEX(Properties!$I$5:$I$104,MATCH($B15,Properties!$A$5:$A$104,0))*Settings!$B$10,0))),0)) | O15: =IF($B15="","",IFERROR(IF($D15="Completed",INDEX(Properties!$L$5:$L$104,MATCH($B15,Properties!$A$5:$A$104,0))+IF($G15="Y",INDEX(Properties!$I$5:$I$104,MATCH($B15,Properties!$A$5:$A$104,0))*Settings!$B$8*Settings!$B$9,0)+IF($H15="Y",Settings!$B$7*Settings!$B$9,0)+N($I15)*Settings!$B$9,IF($D15="Deep clean",INDEX(Settings!$E$22:$E$26,MATCH(MIN(INDEX(Properties!$E$5:$E$104,MATCH($B15,Properties!$A$5:$A$104,0)),4),Settings!$A$22:$A$26,0))*Settings!$B$19+N($I15)*Settings!$B$9,IF($D15="Late cancel",INDEX(Properties!$L$5:$L$104,MATCH($B15,Properties!$A$5:$A$104,0))*Settings!$B$11,0))),0)) | P15: =IF($B15="","",$N15-$O15) | Q15: =IF($A15="","",DATE(YEAR($A15),MONTH($A15),1)) | R15: =IF($A15="","",$A15+MOD(6-WEEKDAY($A15),7)) | S15: =IF($B15="","",IF(AND($M15='Invoice Builder'!$C$5,$Q15='Invoice Builder'!$C$6,N($N15)>0),COUNTIFS($M$5:$M15,'Invoice Builder'!$C$5,$Q$5:$Q15,'Invoice Builder'!$C$6,$N$5:$N15,">0"),"")) | T15: =IF($A15="","",IF($A15>=DATE(YEAR($A15),4,6),YEAR($A15)&"/"&RIGHT(YEAR($A15)+1,2),YEAR($A15)-1&"/"&RIGHT(YEAR($A15),2)))
L16: =IF(OR($E16="",$F16=""),"",MOD($F16-$E16,1)*24) | M16: =IF($B16="","",IFERROR(INDEX(Properties!$D$5:$D$104,MATCH($B16,Properties!$A$5:$A$104,0)),"?")) | N16: =IF($B16="","",IFERROR(IF($D16="Completed",INDEX(Properties!$I$5:$I$104,MATCH($B16,Properties!$A$5:$A$104,0))*(1+IF($G16="Y",Settings!$B$8,0))+IF($H16="Y",Settings!$B$7,0)+N($I16),IF($D16="Deep clean",INDEX(Settings!$E$22:$E$26,MATCH(MIN(INDEX(Properties!$E$5:$E$104,MATCH($B16,Properties!$A$5:$A$104,0)),4),Settings!$A$22:$A$26,0))+N($I16),IF($D16="Late cancel",INDEX(Properties!$I$5:$I$104,MATCH($B16,Properties!$A$5:$A$104,0))*Settings!$B$10,0))),0)) | O16: =IF($B16="","",IFERROR(IF($D16="Completed",INDEX(Properties!$L$5:$L$104,MATCH($B16,Properties!$A$5:$A$104,0))+IF($G16="Y",INDEX(Properties!$I$5:$I$104,MATCH($B16,Properties!$A$5:$A$104,0))*Settings!$B$8*Settings!$B$9,0)+IF($H16="Y",Settings!$B$7*Settings!$B$9,0)+N($I16)*Settings!$B$9,IF($D16="Deep clean",INDEX(Settings!$E$22:$E$26,MATCH(MIN(INDEX(Properties!$E$5:$E$104,MATCH($B16,Properties!$A$5:$A$104,0)),4),Settings!$A$22:$A$26,0))*Settings!$B$19+N($I16)*Settings!$B$9,IF($D16="Late cancel",INDEX(Properties!$L$5:$L$104,MATCH($B16,Properties!$A$5:$A$104,0))*Settings!$B$11,0))),0)) | P16: =IF($B16="","",$N16-$O16) | Q16: =IF($A16="","",DATE(YEAR($A16),MONTH($A16),1)) | R16: =IF($A16="","",$A16+MOD(6-WEEKDAY($A16),7)) | S16: =IF($B16="","",IF(AND($M16='Invoice Builder'!$C$5,$Q16='Invoice Builder'!$C$6,N($N16)>0),COUNTIFS($M$5:$M16,'Invoice Builder'!$C$5,$Q$5:$Q16,'Invoice Builder'!$C$6,$N$5:$N16,">0"),"")) | T16: =IF($A16="","",IF($A16>=DATE(YEAR($A16),4,6),YEAR($A16)&"/"&RIGHT(YEAR($A16)+1,2),YEAR($A16)-1&"/"&RIGHT(YEAR($A16),2)))
L17: =IF(OR($E17="",$F17=""),"",MOD($F17-$E17,1)*24) | M17: =IF($B17="","",IFERROR(INDEX(Properties!$D$5:$D$104,MATCH($B17,Properties!$A$5:$A$104,0)),"?")) | N17: =IF($B17="","",IFERROR(IF($D17="Completed",INDEX(Properties!$I$5:$I$104,MATCH($B17,Properties!$A$5:$A$104,0))*(1+IF($G17="Y",Settings!$B$8,0))+IF($H17="Y",Settings!$B$7,0)+N($I17),IF($D17="Deep clean",INDEX(Settings!$E$22:$E$26,MATCH(MIN(INDEX(Properties!$E$5:$E$104,MATCH($B17,Properties!$A$5:$A$104,0)),4),Settings!$A$22:$A$26,0))+N($I17),IF($D17="Late cancel",INDEX(Properties!$I$5:$I$104,MATCH($B17,Properties!$A$5:$A$104,0))*Settings!$B$10,0))),0)) | O17: =IF($B17="","",IFERROR(IF($D17="Completed",INDEX(Properties!$L$5:$L$104,MATCH($B17,Properties!$A$5:$A$104,0))+IF($G17="Y",INDEX(Properties!$I$5:$I$104,MATCH($B17,Properties!$A$5:$A$104,0))*Settings!$B$8*Settings!$B$9,0)+IF($H17="Y",Settings!$B$7*Settings!$B$9,0)+N($I17)*Settings!$B$9,IF($D17="Deep clean",INDEX(Settings!$E$22:$E$26,MATCH(MIN(INDEX(Properties!$E$5:$E$104,MATCH($B17,Properties!$A$5:$A$104,0)),4),Settings!$A$22:$A$26,0))*Settings!$B$19+N($I17)*Settings!$B$9,IF($D17="Late cancel",INDEX(Properties!$L$5:$L$104,MATCH($B17,Properties!$A$5:$A$104,0))*Settings!$B$11,0))),0)) | P17: =IF($B17="","",$N17-$O17) | Q17: =IF($A17="","",DATE(YEAR($A17),MONTH($A17),1)) | R17: =IF($A17="","",$A17+MOD(6-WEEKDAY($A17),7)) | S17: =IF($B17="","",IF(AND($M17='Invoice Builder'!$C$5,$Q17='Invoice Builder'!$C$6,N($N17)>0),COUNTIFS($M$5:$M17,'Invoice Builder'!$C$5,$Q$5:$Q17,'Invoice Builder'!$C$6,$N$5:$N17,">0"),"")) | T17: =IF($A17="","",IF($A17>=DATE(YEAR($A17),4,6),YEAR($A17)&"/"&RIGHT(YEAR($A17)+1,2),YEAR($A17)-1&"/"&RIGHT(YEAR($A17),2)))
L18: =IF(OR($E18="",$F18=""),"",MOD($F18-$E18,1)*24) | M18: =IF($B18="","",IFERROR(INDEX(Properties!$D$5:$D$104,MATCH($B18,Properties!$A$5:$A$104,0)),"?")) | N18: =IF($B18="","",IFERROR(IF($D18="Completed",INDEX(Properties!$I$5:$I$104,MATCH($B18,Properties!$A$5:$A$104,0))*(1+IF($G18="Y",Settings!$B$8,0))+IF($H18="Y",Settings!$B$7,0)+N($I18),IF($D18="Deep clean",INDEX(Settings!$E$22:$E$26,MATCH(MIN(INDEX(Properties!$E$5:$E$104,MATCH($B18,Properties!$A$5:$A$104,0)),4),Settings!$A$22:$A$26,0))+N($I18),IF($D18="Late cancel",INDEX(Properties!$I$5:$I$104,MATCH($B18,Properties!$A$5:$A$104,0))*Settings!$B$10,0))),0)) | O18: =IF($B18="","",IFERROR(IF($D18="Completed",INDEX(Properties!$L$5:$L$104,MATCH($B18,Properties!$A$5:$A$104,0))+IF($G18="Y",INDEX(Properties!$I$5:$I$104,MATCH($B18,Properties!$A$5:$A$104,0))*Settings!$B$8*Settings!$B$9,0)+IF($H18="Y",Settings!$B$7*Settings!$B$9,0)+N($I18)*Settings!$B$9,IF($D18="Deep clean",INDEX(Settings!$E$22:$E$26,MATCH(MIN(INDEX(Properties!$E$5:$E$104,MATCH($B18,Properties!$A$5:$A$104,0)),4),Settings!$A$22:$A$26,0))*Settings!$B$19+N($I18)*Settings!$B$9,IF($D18="Late cancel",INDEX(Properties!$L$5:$L$104,MATCH($B18,Properties!$A$5:$A$104,0))*Settings!$B$11,0))),0)) | P18: =IF($B18="","",$N18-$O18) | Q18: =IF($A18="","",DATE(YEAR($A18),MONTH($A18),1)) | R18: =IF($A18="","",$A18+MOD(6-WEEKDAY($A18),7)) | S18: =IF($B18="","",IF(AND($M18='Invoice Builder'!$C$5,$Q18='Invoice Builder'!$C$6,N($N18)>0),COUNTIFS($M$5:$M18,'Invoice Builder'!$C$5,$Q$5:$Q18,'Invoice Builder'!$C$6,$N$5:$N18,">0"),"")) | T18: =IF($A18="","",IF($A18>=DATE(YEAR($A18),4,6),YEAR($A18)&"/"&RIGHT(YEAR($A18)+1,2),YEAR($A18)-1&"/"&RIGHT(YEAR($A18),2)))
L19: =IF(OR($E19="",$F19=""),"",MOD($F19-$E19,1)*24) | M19: =IF($B19="","",IFERROR(INDEX(Properties!$D$5:$D$104,MATCH($B19,Properties!$A$5:$A$104,0)),"?")) | N19: =IF($B19="","",IFERROR(IF($D19="Completed",INDEX(Properties!$I$5:$I$104,MATCH($B19,Properties!$A$5:$A$104,0))*(1+IF($G19="Y",Settings!$B$8,0))+IF($H19="Y",Settings!$B$7,0)+N($I19),IF($D19="Deep clean",INDEX(Settings!$E$22:$E$26,MATCH(MIN(INDEX(Properties!$E$5:$E$104,MATCH($B19,Properties!$A$5:$A$104,0)),4),Settings!$A$22:$A$26,0))+N($I19),IF($D19="Late cancel",INDEX(Properties!$I$5:$I$104,MATCH($B19,Properties!$A$5:$A$104,0))*Settings!$B$10,0))),0)) | O19: =IF($B19="","",IFERROR(IF($D19="Completed",INDEX(Properties!$L$5:$L$104,MATCH($B19,Properties!$A$5:$A$104,0))+IF($G19="Y",INDEX(Properties!$I$5:$I$104,MATCH($B19,Properties!$A$5:$A$104,0))*Settings!$B$8*Settings!$B$9,0)+IF($H19="Y",Settings!$B$7*Settings!$B$9,0)+N($I19)*Settings!$B$9,IF($D19="Deep clean",INDEX(Settings!$E$22:$E$26,MATCH(MIN(INDEX(Properties!$E$5:$E$104,MATCH($B19,Properties!$A$5:$A$104,0)),4),Settings!$A$22:$A$26,0))*Settings!$B$19+N($I19)*Settings!$B$9,IF($D19="Late cancel",INDEX(Properties!$L$5:$L$104,MATCH($B19,Properties!$A$5:$A$104,0))*Settings!$B$11,0))),0)) | P19: =IF($B19="","",$N19-$O19) | Q19: =IF($A19="","",DATE(YEAR($A19),MONTH($A19),1)) | R19: =IF($A19="","",$A19+MOD(6-WEEKDAY($A19),7)) | S19: =IF($B19="","",IF(AND($M19='Invoice Builder'!$C$5,$Q19='Invoice Builder'!$C$6,N($N19)>0),COUNTIFS($M$5:$M19,'Invoice Builder'!$C$5,$Q$5:$Q19,'Invoice Builder'!$C$6,$N$5:$N19,">0"),"")) | T19: =IF($A19="","",IF($A19>=DATE(YEAR($A19),4,6),YEAR($A19)&"/"&RIGHT(YEAR($A19)+1,2),YEAR($A19)-1&"/"&RIGHT(YEAR($A19),2)))
L20: =IF(OR($E20="",$F20=""),"",MOD($F20-$E20,1)*24) | M20: =IF($B20="","",IFERROR(INDEX(Properties!$D$5:$D$104,MATCH($B20,Properties!$A$5:$A$104,0)),"?")) | N20: =IF($B20="","",IFERROR(IF($D20="Completed",INDEX(Properties!$I$5:$I$104,MATCH($B20,Properties!$A$5:$A$104,0))*(1+IF($G20="Y",Settings!$B$8,0))+IF($H20="Y",Settings!$B$7,0)+N($I20),IF($D20="Deep clean",INDEX(Settings!$E$22:$E$26,MATCH(MIN(INDEX(Properties!$E$5:$E$104,MATCH($B20,Properties!$A$5:$A$104,0)),4),Settings!$A$22:$A$26,0))+N($I20),IF($D20="Late cancel",INDEX(Properties!$I$5:$I$104,MATCH($B20,Properties!$A$5:$A$104,0))*Settings!$B$10,0))),0)) | O20: =IF($B20="","",IFERROR(IF($D20="Completed",INDEX(Properties!$L$5:$L$104,MATCH($B20,Properties!$A$5:$A$104,0))+IF($G20="Y",INDEX(Properties!$I$5:$I$104,MATCH($B20,Properties!$A$5:$A$104,0))*Settings!$B$8*Settings!$B$9,0)+IF($H20="Y",Settings!$B$7*Settings!$B$9,0)+N($I20)*Settings!$B$9,IF($D20="Deep clean",INDEX(Settings!$E$22:$E$26,MATCH(MIN(INDEX(Properties!$E$5:$E$104,MATCH($B20,Properties!$A$5:$A$104,0)),4),Settings!$A$22:$A$26,0))*Settings!$B$19+N($I20)*Settings!$B$9,IF($D20="Late cancel",INDEX(Properties!$L$5:$L$104,MATCH($B20,Properties!$A$5:$A$104,0))*Settings!$B$11,0))),0)) | P20: =IF($B20="","",$N20-$O20) | Q20: =IF($A20="","",DATE(YEAR($A20),MONTH($A20),1)) | R20: =IF($A20="","",$A20+MOD(6-WEEKDAY($A20),7)) | S20: =IF($B20="","",IF(AND($M20='Invoice Builder'!$C$5,$Q20='Invoice Builder'!$C$6,N($N20)>0),COUNTIFS($M$5:$M20,'Invoice Builder'!$C$5,$Q$5:$Q20,'Invoice Builder'!$C$6,$N$5:$N20,">0"),"")) | T20: =IF($A20="","",IF($A20>=DATE(YEAR($A20),4,6),YEAR($A20)&"/"&RIGHT(YEAR($A20)+1,2),YEAR($A20)-1&"/"&RIGHT(YEAR($A20),2)))
... L1004: =IF(OR($E1004="",$F1004=""),"",MOD($F1004-$E1004,1)*24) | M1004: =IF($B1004="","",IFERROR(INDEX(Properties!$D$5:$D$104,MATCH($B1004,Properties!$A$5:$A$104,0)),"?")) | N1004: =IF($B1004="","",IFERROR(IF($D1004="Completed",INDEX(Properties!$I$5:$I$104,MATCH($B1004,Properties!$A$5:$A$104,0))*(1+IF($G1004="Y",Settings!$B$8,0))+IF($H1004="Y",Settings!$B$7,0)+N($I1004),IF($D1004="Deep clean",INDEX(Settings!$E$22:$E$26,MATCH(MIN(INDEX(Properties!$E$5:$E$104,MATCH($B1004,Properties!$A$5:$A$104,0)),4),Settings!$A$22:$A$26,0))+N($I1004),IF($D1004="Late cancel",INDEX(Properties!$I$5:$I$104,MATCH($B1004,Properties!$A$5:$A$104,0))*Settings!$B$10,0))),0)) | O1004: =IF($B1004="","",IFERROR(IF($D1004="Completed",INDEX(Properties!$L$5:$L$104,MATCH($B1004,Properties!$A$5:$A$104,0))+IF($G1004="Y",INDEX(Properties!$I$5:$I$104,MATCH($B1004,Properties!$A$5:$A$104,0))*Settings!$B$8*Settings!$B$9,0)+IF($H1004="Y",Settings!$B$7*Settings!$B$9,0)+N($I1004)*Settings!$B$9,IF($D1004="Deep clean",INDEX(Settings!$E$22:$E$26,MATCH(MIN(INDEX(Properties!$E$5:$E$104,MATCH($B1004,Properties!$A$5:$A$104,0)),4),Settings!$A$22:$A$26,0))*Settings!$B$19+N($I1004)*Settings!$B$9,IF($D1004="Late cancel",INDEX(Properties!$L$5:$L$104,MATCH($B1004,Properties!$A$5:$A$104,0))*Settings!$B$11,0))),0)) | P1004: =IF($B1004="","",$N1004-$O1004) | Q1004: =IF($A1004="","",DATE(YEAR($A1004),MONTH($A1004),1)) | R1004: =IF($A1004="","",$A1004+MOD(6-WEEKDAY($A1004),7)) | S1004: =IF($B1004="","",IF(AND($M1004='Invoice Builder'!$C$5,$Q1004='Invoice Builder'!$C$6,N($N1004)>0),COUNTIFS($M$5:$M1004,'Invoice Builder'!$C$5,$Q$5:$Q1004,'Invoice Builder'!$C$6,$N$5:$N1004,">0"),"")) | T1004: =IF($A1004="","",IF($A1004>=DATE(YEAR($A1004),4,6),YEAR($A1004)&"/"&RIGHT(YEAR($A1004)+1,2),YEAR($A1004)-1&"/"&RIGHT(YEAR($A1004),2)))

Sheet Stock
A1: Stock per Property
A2: Full stock = what should be there after a clean. Update 'Count now' from the cleaner's counts. Red = buy before the next clean.
A4: Prop ID | B4: Item ID | C4: Item | D4: Full stock | E4: Reorder at or below | F4: Count now | G4: Last counted | H4: Status | I4: Need to buy | J4: Est. cost (£) | L4: Template for a new 2-bed: copy rows 5–21 and change the Prop ID. Scale full stock up or down for bigger or smaller places.
A5: P001 | B5: S01 | C5: =IF($B5="","",IFERROR(INDEX(Supplies!$B$5:$B$104,MATCH($B5,Supplies!$A$5:$A$104,0)),"?")) -> Toilet roll | D5: 8 | E5: 4 | F5: 5 | G5: 46319 | H5: =IF($A5="","",IF($F5="","Count it",IF($F5<=$E5,"REORDER","OK"))) -> OK | I5: =IF(OR($A5="",$F5=""),"",MAX(0,$D5-$F5)) -> 3 | J5: =IF(OR($A5="",$I5=""),"",$I5*IFERROR(INDEX(Supplies!$F$5:$F$104,MATCH($B5,Supplies!$A$5:$A$104,0)),0)) -> 1.575
A6: P001 | B6: S02 | C6: =IF($B6="","",IFERROR(INDEX(Supplies!$B$5:$B$104,MATCH($B6,Supplies!$A$5:$A$104,0)),"?")) -> Kitchen roll | D6: 3 | E6: 1 | F6: 2 | G6: 46319 | H6: =IF($A6="","",IF($F6="","Count it",IF($F6<=$E6,"REORDER","OK"))) -> OK | I6: =IF(OR($A6="",$F6=""),"",MAX(0,$D6-$F6)) -> 1 | J6: =IF(OR($A6="",$I6=""),"",$I6*IFERROR(INDEX(Supplies!$F$5:$F$104,MATCH($B6,Supplies!$A$5:$A$104,0)),0)) -> 1
A7: P001 | B7: S03 | C7: =IF($B7="","",IFERROR(INDEX(Supplies!$B$5:$B$104,MATCH($B7,Supplies!$A$5:$A$104,0)),"?")) -> Hand soap (500ml pump) | D7: 2 | E7: 1 | F7: 1 | G7: 46319 | H7: =IF($A7="","",IF($F7="","Count it",IF($F7<=$E7,"REORDER","OK"))) -> REORDER | I7: =IF(OR($A7="",$F7=""),"",MAX(0,$D7-$F7)) -> 1 | J7: =IF(OR($A7="",$I7=""),"",$I7*IFERROR(INDEX(Supplies!$F$5:$F$104,MATCH($B7,Supplies!$A$5:$A$104,0)),0)) -> 1.5
A8: P001 | B8: S04 | C8: =IF($B8="","",IFERROR(INDEX(Supplies!$B$5:$B$104,MATCH($B8,Supplies!$A$5:$A$104,0)),"?")) -> Mini shampoo | D8: 6 | E8: 2 | F8: 4 | G8: 46319 | H8: =IF($A8="","",IF($F8="","Count it",IF($F8<=$E8,"REORDER","OK"))) -> OK | I8: =IF(OR($A8="",$F8=""),"",MAX(0,$D8-$F8)) -> 2 | J8: =IF(OR($A8="",$I8=""),"",$I8*IFERROR(INDEX(Supplies!$F$5:$F$104,MATCH($B8,Supplies!$A$5:$A$104,0)),0)) -> 0.48
A9: P001 | B9: S05 | C9: =IF($B9="","",IFERROR(INDEX(Supplies!$B$5:$B$104,MATCH($B9,Supplies!$A$5:$A$104,0)),"?")) -> Mini conditioner | D9: 6 | E9: 2 | F9: 4 | G9: 46319 | H9: =IF($A9="","",IF($F9="","Count it",IF($F9<=$E9,"REORDER","OK"))) -> OK | I9: =IF(OR($A9="",$F9=""),"",MAX(0,$D9-$F9)) -> 2 | J9: =IF(OR($A9="",$I9=""),"",$I9*IFERROR(INDEX(Supplies!$F$5:$F$104,MATCH($B9,Supplies!$A$5:$A$104,0)),0)) -> 0.48
A10: P001 | B10: S06 | C10: =IF($B10="","",IFERROR(INDEX(Supplies!$B$5:$B$104,MATCH($B10,Supplies!$A$5:$A$104,0)),"?")) -> Mini shower gel | D10: 6 | E10: 2 | F10: 2 | G10: 46319 | H10: =IF($A10="","",IF($F10="","Count it",IF($F10<=$E10,"REORDER","OK"))) -> REORDER | I10: =IF(OR($A10="",$F10=""),"",MAX(0,$D10-$F10)) -> 4 | J10: =IF(OR($A10="",$I10=""),"",$I10*IFERROR(INDEX(Supplies!$F$5:$F$104,MATCH($B10,Supplies!$A$5:$A$104,0)),0)) -> 0.96
A11: P001 | B11: S07 | C11: =IF($B11="","",IFERROR(INDEX(Supplies!$B$5:$B$104,MATCH($B11,Supplies!$A$5:$A$104,0)),"?")) -> Dishwasher tablets | D11: 20 | E11: 8 | F11: 14 | G11: 46319 | H11: =IF($A11="","",IF($F11="","Count it",IF($F11<=$E11,"REORDER","OK"))) -> OK | I11: =IF(OR($A11="",$F11=""),"",MAX(0,$D11-$F11)) -> 6 | J11: =IF(OR($A11="",$I11=""),"",$I11*IFERROR(INDEX(Supplies!$F$5:$F$104,MATCH($B11,Supplies!$A$5:$A$104,0)),0)) -> 0.9
A12: P001 | B12: S08 | C12: =IF($B12="","",IFERROR(INDEX(Supplies!$B$5:$B$104,MATCH($B12,Supplies!$A$5:$A$104,0)),"?")) -> Washing-up liquid | D12: 2 | E12: 1 | F12: 2 | G12: 46319 | H12: =IF($A12="","",IF($F12="","Count it",IF($F12<=$E12,"REORDER","OK"))) -> OK | I12: =IF(OR($A12="",$F12=""),"",MAX(0,$D12-$F12)) -> 0 | J12: =IF(OR($A12="",$I12=""),"",$I12*IFERROR(INDEX(Supplies!$F$5:$F$104,MATCH($B12,Supplies!$A$5:$A$104,0)),0)) -> 0
A13: P001 | B13: S09 | C13: =IF($B13="","",IFERROR(INDEX(Supplies!$B$5:$B$104,MATCH($B13,Supplies!$A$5:$A$104,0)),"?")) -> Sponge scourers | D13: 3 | E13: 1 | F13: 2 | G13: 46319 | H13: =IF($A13="","",IF($F13="","Count it",IF($F13<=$E13,"REORDER","OK"))) -> OK | I13: =IF(OR($A13="",$F13=""),"",MAX(0,$D13-$F13)) -> 1 | J13: =IF(OR($A13="",$I13=""),"",$I13*IFERROR(INDEX(Supplies!$F$5:$F$104,MATCH($B13,Supplies!$A$5:$A$104,0)),0)) -> 0.3
A14: P001 | B14: S10 | C14: =IF($B14="","",IFERROR(INDEX(Supplies!$B$5:$B$104,MATCH($B14,Supplies!$A$5:$A$104,0)),"?")) -> Bin bags (kitchen) | D14: 20 | E14: 8 | F14: 7 | G14: 46319 | H14: =IF($A14="","",IF($F14="","Count it",IF($F14<=$E14,"REORDER","OK"))) -> REORDER | I14: =IF(OR($A14="",$F14=""),"",MAX(0,$D14-$F14)) -> 13 | J14: =IF(OR($A14="",$I14=""),"",$I14*IFERROR(INDEX(Supplies!$F$5:$F$104,MATCH($B14,Supplies!$A$5:$A$104,0)),0)) -> 1.04
A15: P001 | B15: S11 | C15: =IF($B15="","",IFERROR(INDEX(Supplies!$B$5:$B$104,MATCH($B15,Supplies!$A$5:$A$104,0)),"?")) -> Tea bags | D15: 40 | E15: 15 | F15: 22 | G15: 46319 | H15: =IF($A15="","",IF($F15="","Count it",IF($F15<=$E15,"REORDER","OK"))) -> OK | I15: =IF(OR($A15="",$F15=""),"",MAX(0,$D15-$F15)) -> 18 | J15: =IF(OR($A15="",$I15=""),"",$I15*IFERROR(INDEX(Supplies!$F$5:$F$104,MATCH($B15,Supplies!$A$5:$A$104,0)),0)) -> 0.45
A16: P001 | B16: S12 | C16: =IF($B16="","",IFERROR(INDEX(Supplies!$B$5:$B$104,MATCH($B16,Supplies!$A$5:$A$104,0)),"?")) -> Coffee sachets / pods | D16: 20 | E16: 8 | F16: 9 | G16: 46319 | H16: =IF($A16="","",IF($F16="","Count it",IF($F16<=$E16,"REORDER","OK"))) -> OK | I16: =IF(OR($A16="",$F16=""),"",MAX(0,$D16-$F16)) -> 11 | J16: =IF(OR($A16="",$I16=""),"",$I16*IFERROR(INDEX(Supplies!$F$5:$F$104,MATCH($B16,Supplies!$A$5:$A$104,0)),0)) -> 1.65
... A21: P001 | B21: S24 | C21: =IF($B21="","",IFERROR(INDEX(Supplies!$B$5:$B$104,MATCH($B21,Supplies!$A$5:$A$104,0)),"?")) -> AA batteries | D21: 4 | E21: 2 | F21: 4 | G21: 46319 | H21: =IF($A21="","",IF($F21="","Count it",IF($F21<=$E21,"REORDER","OK"))) -> OK | I21: =IF(OR($A21="",$F21=""),"",MAX(0,$D21-$F21)) -> 0 | J21: =IF(OR($A21="",$I21=""),"",$I21*IFERROR(INDEX(Supplies!$F$5:$F$104,MATCH($B21,Supplies!$A$5:$A$104,0)),0)) -> 0
C22: =IF($B22="","",IFERROR(INDEX(Supplies!$B$5:$B$104,MATCH($B22,Supplies!$A$5:$A$104,0)),"?")) | H22: =IF($A22="","",IF($F22="","Count it",IF($F22<=$E22,"REORDER","OK"))) | I22: =IF(OR($A22="",$F22=""),"",MAX(0,$D22-$F22)) | J22: =IF(OR($A22="",$I22=""),"",$I22*IFERROR(INDEX(Supplies!$F$5:$F$104,MATCH($B22,Supplies!$A$5:$A$104,0)),0))
C23: =IF($B23="","",IFERROR(INDEX(Supplies!$B$5:$B$104,MATCH($B23,Supplies!$A$5:$A$104,0)),"?")) | H23: =IF($A23="","",IF($F23="","Count it",IF($F23<=$E23,"REORDER","OK"))) | I23: =IF(OR($A23="",$F23=""),"",MAX(0,$D23-$F23)) | J23: =IF(OR($A23="",$I23=""),"",$I23*IFERROR(INDEX(Supplies!$F$5:$F$104,MATCH($B23,Supplies!$A$5:$A$104,0)),0))
C24: =IF($B24="","",IFERROR(INDEX(Supplies!$B$5:$B$104,MATCH($B24,Supplies!$A$5:$A$104,0)),"?")) | H24: =IF($A24="","",IF($F24="","Count it",IF($F24<=$E24,"REORDER","OK"))) | I24: =IF(OR($A24="",$F24=""),"",MAX(0,$D24-$F24)) | J24: =IF(OR($A24="",$I24=""),"",$I24*IFERROR(INDEX(Supplies!$F$5:$F$104,MATCH($B24,Supplies!$A$5:$A$104,0)),0))
C25: =IF($B25="","",IFERROR(INDEX(Supplies!$B$5:$B$104,MATCH($B25,Supplies!$A$5:$A$104,0)),"?")) | H25: =IF($A25="","",IF($F25="","Count it",IF($F25<=$E25,"REORDER","OK"))) | I25: =IF(OR($A25="",$F25=""),"",MAX(0,$D25-$F25)) | J25: =IF(OR($A25="",$I25=""),"",$I25*IFERROR(INDEX(Supplies!$F$5:$F$104,MATCH($B25,Supplies!$A$5:$A$104,0)),0))
C26: =IF($B26="","",IFERROR(INDEX(Supplies!$B$5:$B$104,MATCH($B26,Supplies!$A$5:$A$104,0)),"?")) | H26: =IF($A26="","",IF($F26="","Count it",IF($F26<=$E26,"REORDER","OK"))) | I26: =IF(OR($A26="",$F26=""),"",MAX(0,$D26-$F26)) | J26: =IF(OR($A26="",$I26=""),"",$I26*IFERROR(INDEX(Supplies!$F$5:$F$104,MATCH($B26,Supplies!$A$5:$A$104,0)),0))
C27: =IF($B27="","",IFERROR(INDEX(Supplies!$B$5:$B$104,MATCH($B27,Supplies!$A$5:$A$104,0)),"?")) | H27: =IF($A27="","",IF($F27="","Count it",IF($F27<=$E27,"REORDER","OK"))) | I27: =IF(OR($A27="",$F27=""),"",MAX(0,$D27-$F27)) | J27: =IF(OR($A27="",$I27=""),"",$I27*IFERROR(INDEX(Supplies!$F$5:$F$104,MATCH($B27,Supplies!$A$5:$A$104,0)),0))
C28: =IF($B28="","",IFERROR(INDEX(Supplies!$B$5:$B$104,MATCH($B28,Supplies!$A$5:$A$104,0)),"?")) | H28: =IF($A28="","",IF($F28="","Count it",IF($F28<=$E28,"REORDER","OK"))) | I28: =IF(OR($A28="",$F28=""),"",MAX(0,$D28-$F28)) | J28: =IF(OR($A28="",$I28=""),"",$I28*IFERROR(INDEX(Supplies!$F$5:$F$104,MATCH($B28,Supplies!$A$5:$A$104,0)),0))
C29: =IF($B29="","",IFERROR(INDEX(Supplies!$B$5:$B$104,MATCH($B29,Supplies!$A$5:$A$104,0)),"?")) | H29: =IF($A29="","",IF($F29="","Count it",IF($F29<=$E29,"REORDER","OK"))) | I29: =IF(OR($A29="",$F29=""),"",MAX(0,$D29-$F29)) | J29: =IF(OR($A29="",$I29=""),"",$I29*IFERROR(INDEX(Supplies!$F$5:$F$104,MATCH($B29,Supplies!$A$5:$A$104,0)),0))
C30: =IF($B30="","",IFERROR(INDEX(Supplies!$B$5:$B$104,MATCH($B30,Supplies!$A$5:$A$104,0)),"?")) | H30: =IF($A30="","",IF($F30="","Count it",IF($F30<=$E30,"REORDER","OK"))) | I30: =IF(OR($A30="",$F30=""),"",MAX(0,$D30-$F30)) | J30: =IF(OR($A30="",$I30=""),"",$I30*IFERROR(INDEX(Supplies!$F$5:$F$104,MATCH($B30,Supplies!$A$5:$A$104,0)),0))
C31: =IF($B31="","",IFERROR(INDEX(Supplies!$B$5:$B$104,MATCH($B31,Supplies!$A$5:$A$104,0)),"?")) | H31: =IF($A31="","",IF($F31="","Count it",IF($F31<=$E31,"REORDER","OK"))) | I31: =IF(OR($A31="",$F31=""),"",MAX(0,$D31-$F31)) | J31: =IF(OR($A31="",$I31=""),"",$I31*IFERROR(INDEX(Supplies!$F$5:$F$104,MATCH($B31,Supplies!$A$5:$A$104,0)),0))
C32: =IF($B32="","",IFERROR(INDEX(Supplies!$B$5:$B$104,MATCH($B32,Supplies!$A$5:$A$104,0)),"?")) | H32: =IF($A32="","",IF($F32="","Count it",IF($F32<=$E32,"REORDER","OK"))) | I32: =IF(OR($A32="",$F32=""),"",MAX(0,$D32-$F32)) | J32: =IF(OR($A32="",$I32=""),"",$I32*IFERROR(INDEX(Supplies!$F$5:$F$104,MATCH($B32,Supplies!$A$5:$A$104,0)),0))
C33: =IF($B33="","",IFERROR(INDEX(Supplies!$B$5:$B$104,MATCH($B33,Supplies!$A$5:$A$104,0)),"?")) | H33: =IF($A33="","",IF($F33="","Count it",IF($F33<=$E33,"REORDER","OK"))) | I33: =IF(OR($A33="",$F33=""),"",MAX(0,$D33-$F33)) | J33: =IF(OR($A33="",$I33=""),"",$I33*IFERROR(INDEX(Supplies!$F$5:$F$104,MATCH($B33,Supplies!$A$5:$A$104,0)),0))
... C504: =IF($B504="","",IFERROR(INDEX(Supplies!$B$5:$B$104,MATCH($B504,Supplies!$A$5:$A$104,0)),"?")) | H504: =IF($A504="","",IF($F504="","Count it",IF($F504<=$E504,"REORDER","OK"))) | I504: =IF(OR($A504="",$F504=""),"",MAX(0,$D504-$F504)) | J504: =IF(OR($A504="",$I504=""),"",$I504*IFERROR(INDEX(Supplies!$F$5:$F$104,MATCH($B504,Supplies!$A$5:$A$104,0)),0))

Sheet Purchases
A1: Purchases & Replacements
A2: Everything you buy for a property. Charge host = Y adds it to their invoice at cost + markup. Keep every receipt (photo is fine).
A4: Date | B4: Prop ID | C4: Item ID (optional) | D4: What | E4: Qty | F4: Total cost (£, from receipt) | G4: Type | H4: Charge host? (Y/N) | I4: Host approved? (Y/N) | J4: Receipt saved? (Y/N) | K4: Notes | L4: Host ID | M4: Cost each (£) | N4: Charge to host (£) | O4: Check | P4: Month | Q4: Invoice line # | R4: Tax year
A5: 46304 | B5: P001 | C5: S22 | D5: LED bulb E27 | E5: 1 | F5: 1.5 | G5: Replacement | H5: Y | J5: Y | K5: EXAMPLE: bedside lamp | L5: =IF($B5="","",IFERROR(INDEX(Properties!$D$5:$D$104,MATCH($B5,Properties!$A$5:$A$104,0)),"-")) -> H001 | M5: =IF(OR($A5="",N($E5)=0),"",$F5/$E5) -> 1.5 | N5: =IF($A5="","",IF($H5="Y",$F5*(1+Settings!$B$3),0)) -> 1.65 | O5: =IF($A5="","",IF(AND($H5="Y",$G5<>"Restock",N($M5)>Settings!$B$4,$I5<>"Y"),"Get host OK",IF(AND($H5="Y",$F5>Settings!$B$5,$I5<>"Y"),"Host should pay upfront",IF($J5<>"Y","Save receipt","OK")))) -> OK | P5: =IF($A5="","",DATE(YEAR($A5),MONTH($A5),1)) -> 46296 | Q5: =IF($A5="","",IF(AND($L5='Invoice Builder'!$C$5,$P5='Invoice Builder'!$C$6,N($N5)>0),COUNTIFS($L$5:$L5,'Invoice Builder'!$C$5,$P$5:$P5,'Invoice Builder'!$C$6,$N$5:$N5,">0"),"")) -> 1 | R5: =IF($A5="","",IF($A5>=DATE(YEAR($A5),4,6),YEAR($A5)&"/"&RIGHT(YEAR($A5)+1,2),YEAR($A5)-1&"/"&RIGHT(YEAR($A5),2))) -> 2026/27
A6: 46320 | B6: P001 | C6: S14 | D6: UHT milk portions | E6: 12 | F6: 0.9 | G6: Restock | H6: Y | J6: Y | K6: EXAMPLE | L6: =IF($B6="","",IFERROR(INDEX(Properties!$D$5:$D$104,MATCH($B6,Properties!$A$5:$A$104,0)),"-")) -> H001 | M6: =IF(OR($A6="",N($E6)=0),"",$F6/$E6) -> 0.075 | N6: =IF($A6="","",IF($H6="Y",$F6*(1+Settings!$B$3),0)) -> 0.99 | O6: =IF($A6="","",IF(AND($H6="Y",$G6<>"Restock",N($M6)>Settings!$B$4,$I6<>"Y"),"Get host OK",IF(AND($H6="Y",$F6>Settings!$B$5,$I6<>"Y"),"Host should pay upfront",IF($J6<>"Y","Save receipt","OK")))) -> OK | P6: =IF($A6="","",DATE(YEAR($A6),MONTH($A6),1)) -> 46296 | Q6: =IF($A6="","",IF(AND($L6='Invoice Builder'!$C$5,$P6='Invoice Builder'!$C$6,N($N6)>0),COUNTIFS($L$5:$L6,'Invoice Builder'!$C$5,$P$5:$P6,'Invoice Builder'!$C$6,$N$5:$N6,">0"),"")) -> 2 | R6: =IF($A6="","",IF($A6>=DATE(YEAR($A6),4,6),YEAR($A6)&"/"&RIGHT(YEAR($A6)+1,2),YEAR($A6)-1&"/"&RIGHT(YEAR($A6),2))) -> 2026/27
A7: 46320 | B7: P001 | C7: S25 | D7: Wine glasses (guest broke 2) | E7: 2 | F7: 4 | G7: Guest damage | H7: Y | I7: Y | J7: Y | K7: EXAMPLE: see Damage tab | L7: =IF($B7="","",IFERROR(INDEX(Properties!$D$5:$D$104,MATCH($B7,Properties!$A$5:$A$104,0)),"-")) -> H001 | M7: =IF(OR($A7="",N($E7)=0),"",$F7/$E7) -> 2 | N7: =IF($A7="","",IF($H7="Y",$F7*(1+Settings!$B$3),0)) -> 4.4 | O7: =IF($A7="","",IF(AND($H7="Y",$G7<>"Restock",N($M7)>Settings!$B$4,$I7<>"Y"),"Get host OK",IF(AND($H7="Y",$F7>Settings!$B$5,$I7<>"Y"),"Host should pay upfront",IF($J7<>"Y","Save receipt","OK")))) -> OK | P7: =IF($A7="","",DATE(YEAR($A7),MONTH($A7),1)) -> 46296 | Q7: =IF($A7="","",IF(AND($L7='Invoice Builder'!$C$5,$P7='Invoice Builder'!$C$6,N($N7)>0),COUNTIFS($L$5:$L7,'Invoice Builder'!$C$5,$P$5:$P7,'Invoice Builder'!$C$6,$N$5:$N7,">0"),"")) -> 3 | R7: =IF($A7="","",IF($A7>=DATE(YEAR($A7),4,6),YEAR($A7)&"/"&RIGHT(YEAR($A7)+1,2),YEAR($A7)-1&"/"&RIGHT(YEAR($A7),2))) -> 2026/27
L8: =IF($B8="","",IFERROR(INDEX(Properties!$D$5:$D$104,MATCH($B8,Properties!$A$5:$A$104,0)),"-")) | M8: =IF(OR($A8="",N($E8)=0),"",$F8/$E8) | N8: =IF($A8="","",IF($H8="Y",$F8*(1+Settings!$B$3),0)) | O8: =IF($A8="","",IF(AND($H8="Y",$G8<>"Restock",N($M8)>Settings!$B$4,$I8<>"Y"),"Get host OK",IF(AND($H8="Y",$F8>Settings!$B$5,$I8<>"Y"),"Host should pay upfront",IF($J8<>"Y","Save receipt","OK")))) | P8: =IF($A8="","",DATE(YEAR($A8),MONTH($A8),1)) | Q8: =IF($A8="","",IF(AND($L8='Invoice Builder'!$C$5,$P8='Invoice Builder'!$C$6,N($N8)>0),COUNTIFS($L$5:$L8,'Invoice Builder'!$C$5,$P$5:$P8,'Invoice Builder'!$C$6,$N$5:$N8,">0"),"")) | R8: =IF($A8="","",IF($A8>=DATE(YEAR($A8),4,6),YEAR($A8)&"/"&RIGHT(YEAR($A8)+1,2),YEAR($A8)-1&"/"&RIGHT(YEAR($A8),2)))
L9: =IF($B9="","",IFERROR(INDEX(Properties!$D$5:$D$104,MATCH($B9,Properties!$A$5:$A$104,0)),"-")) | M9: =IF(OR($A9="",N($E9)=0),"",$F9/$E9) | N9: =IF($A9="","",IF($H9="Y",$F9*(1+Settings!$B$3),0)) | O9: =IF($A9="","",IF(AND($H9="Y",$G9<>"Restock",N($M9)>Settings!$B$4,$I9<>"Y"),"Get host OK",IF(AND($H9="Y",$F9>Settings!$B$5,$I9<>"Y"),"Host should pay upfront",IF($J9<>"Y","Save receipt","OK")))) | P9: =IF($A9="","",DATE(YEAR($A9),MONTH($A9),1)) | Q9: =IF($A9="","",IF(AND($L9='Invoice Builder'!$C$5,$P9='Invoice Builder'!$C$6,N($N9)>0),COUNTIFS($L$5:$L9,'Invoice Builder'!$C$5,$P$5:$P9,'Invoice Builder'!$C$6,$N$5:$N9,">0"),"")) | R9: =IF($A9="","",IF($A9>=DATE(YEAR($A9),4,6),YEAR($A9)&"/"&RIGHT(YEAR($A9)+1,2),YEAR($A9)-1&"/"&RIGHT(YEAR($A9),2)))
L10: =IF($B10="","",IFERROR(INDEX(Properties!$D$5:$D$104,MATCH($B10,Properties!$A$5:$A$104,0)),"-")) | M10: =IF(OR($A10="",N($E10)=0),"",$F10/$E10) | N10: =IF($A10="","",IF($H10="Y",$F10*(1+Settings!$B$3),0)) | O10: =IF($A10="","",IF(AND($H10="Y",$G10<>"Restock",N($M10)>Settings!$B$4,$I10<>"Y"),"Get host OK",IF(AND($H10="Y",$F10>Settings!$B$5,$I10<>"Y"),"Host should pay upfront",IF($J10<>"Y","Save receipt","OK")))) | P10: =IF($A10="","",DATE(YEAR($A10),MONTH($A10),1)) | Q10: =IF($A10="","",IF(AND($L10='Invoice Builder'!$C$5,$P10='Invoice Builder'!$C$6,N($N10)>0),COUNTIFS($L$5:$L10,'Invoice Builder'!$C$5,$P$5:$P10,'Invoice Builder'!$C$6,$N$5:$N10,">0"),"")) | R10: =IF($A10="","",IF($A10>=DATE(YEAR($A10),4,6),YEAR($A10)&"/"&RIGHT(YEAR($A10)+1,2),YEAR($A10)-1&"/"&RIGHT(YEAR($A10),2)))
L11: =IF($B11="","",IFERROR(INDEX(Properties!$D$5:$D$104,MATCH($B11,Properties!$A$5:$A$104,0)),"-")) | M11: =IF(OR($A11="",N($E11)=0),"",$F11/$E11) | N11: =IF($A11="","",IF($H11="Y",$F11*(1+Settings!$B$3),0)) | O11: =IF($A11="","",IF(AND($H11="Y",$G11<>"Restock",N($M11)>Settings!$B$4,$I11<>"Y"),"Get host OK",IF(AND($H11="Y",$F11>Settings!$B$5,$I11<>"Y"),"Host should pay upfront",IF($J11<>"Y","Save receipt","OK")))) | P11: =IF($A11="","",DATE(YEAR($A11),MONTH($A11),1)) | Q11: =IF($A11="","",IF(AND($L11='Invoice Builder'!$C$5,$P11='Invoice Builder'!$C$6,N($N11)>0),COUNTIFS($L$5:$L11,'Invoice Builder'!$C$5,$P$5:$P11,'Invoice Builder'!$C$6,$N$5:$N11,">0"),"")) | R11: =IF($A11="","",IF($A11>=DATE(YEAR($A11),4,6),YEAR($A11)&"/"&RIGHT(YEAR($A11)+1,2),YEAR($A11)-1&"/"&RIGHT(YEAR($A11),2)))
L12: =IF($B12="","",IFERROR(INDEX(Properties!$D$5:$D$104,MATCH($B12,Properties!$A$5:$A$104,0)),"-")) | M12: =IF(OR($A12="",N($E12)=0),"",$F12/$E12) | N12: =IF($A12="","",IF($H12="Y",$F12*(1+Settings!$B$3),0)) | O12: =IF($A12="","",IF(AND($H12="Y",$G12<>"Restock",N($M12)>Settings!$B$4,$I12<>"Y"),"Get host OK",IF(AND($H12="Y",$F12>Settings!$B$5,$I12<>"Y"),"Host should pay upfront",IF($J12<>"Y","Save receipt","OK")))) | P12: =IF($A12="","",DATE(YEAR($A12),MONTH($A12),1)) | Q12: =IF($A12="","",IF(AND($L12='Invoice Builder'!$C$5,$P12='Invoice Builder'!$C$6,N($N12)>0),COUNTIFS($L$5:$L12,'Invoice Builder'!$C$5,$P$5:$P12,'Invoice Builder'!$C$6,$N$5:$N12,">0"),"")) | R12: =IF($A12="","",IF($A12>=DATE(YEAR($A12),4,6),YEAR($A12)&"/"&RIGHT(YEAR($A12)+1,2),YEAR($A12)-1&"/"&RIGHT(YEAR($A12),2)))
L13: =IF($B13="","",IFERROR(INDEX(Properties!$D$5:$D$104,MATCH($B13,Properties!$A$5:$A$104,0)),"-")) | M13: =IF(OR($A13="",N($E13)=0),"",$F13/$E13) | N13: =IF($A13="","",IF($H13="Y",$F13*(1+Settings!$B$3),0)) | O13: =IF($A13="","",IF(AND($H13="Y",$G13<>"Restock",N($M13)>Settings!$B$4,$I13<>"Y"),"Get host OK",IF(AND($H13="Y",$F13>Settings!$B$5,$I13<>"Y"),"Host should pay upfront",IF($J13<>"Y","Save receipt","OK")))) | P13: =IF($A13="","",DATE(YEAR($A13),MONTH($A13),1)) | Q13: =IF($A13="","",IF(AND($L13='Invoice Builder'!$C$5,$P13='Invoice Builder'!$C$6,N($N13)>0),COUNTIFS($L$5:$L13,'Invoice Builder'!$C$5,$P$5:$P13,'Invoice Builder'!$C$6,$N$5:$N13,">0"),"")) | R13: =IF($A13="","",IF($A13>=DATE(YEAR($A13),4,6),YEAR($A13)&"/"&RIGHT(YEAR($A13)+1,2),YEAR($A13)-1&"/"&RIGHT(YEAR($A13),2)))
L14: =IF($B14="","",IFERROR(INDEX(Properties!$D$5:$D$104,MATCH($B14,Properties!$A$5:$A$104,0)),"-")) | M14: =IF(OR($A14="",N($E14)=0),"",$F14/$E14) | N14: =IF($A14="","",IF($H14="Y",$F14*(1+Settings!$B$3),0)) | O14: =IF($A14="","",IF(AND($H14="Y",$G14<>"Restock",N($M14)>Settings!$B$4,$I14<>"Y"),"Get host OK",IF(AND($H14="Y",$F14>Settings!$B$5,$I14<>"Y"),"Host should pay upfront",IF($J14<>"Y","Save receipt","OK")))) | P14: =IF($A14="","",DATE(YEAR($A14),MONTH($A14),1)) | Q14: =IF($A14="","",IF(AND($L14='Invoice Builder'!$C$5,$P14='Invoice Builder'!$C$6,N($N14)>0),COUNTIFS($L$5:$L14,'Invoice Builder'!$C$5,$P$5:$P14,'Invoice Builder'!$C$6,$N$5:$N14,">0"),"")) | R14: =IF($A14="","",IF($A14>=DATE(YEAR($A14),4,6),YEAR($A14)&"/"&RIGHT(YEAR($A14)+1,2),YEAR($A14)-1&"/"&RIGHT(YEAR($A14),2)))
L15: =IF($B15="","",IFERROR(INDEX(Properties!$D$5:$D$104,MATCH($B15,Properties!$A$5:$A$104,0)),"-")) | M15: =IF(OR($A15="",N($E15)=0),"",$F15/$E15) | N15: =IF($A15="","",IF($H15="Y",$F15*(1+Settings!$B$3),0)) | O15: =IF($A15="","",IF(AND($H15="Y",$G15<>"Restock",N($M15)>Settings!$B$4,$I15<>"Y"),"Get host OK",IF(AND($H15="Y",$F15>Settings!$B$5,$I15<>"Y"),"Host should pay upfront",IF($J15<>"Y","Save receipt","OK")))) | P15: =IF($A15="","",DATE(YEAR($A15),MONTH($A15),1)) | Q15: =IF($A15="","",IF(AND($L15='Invoice Builder'!$C$5,$P15='Invoice Builder'!$C$6,N($N15)>0),COUNTIFS($L$5:$L15,'Invoice Builder'!$C$5,$P$5:$P15,'Invoice Builder'!$C$6,$N$5:$N15,">0"),"")) | R15: =IF($A15="","",IF($A15>=DATE(YEAR($A15),4,6),YEAR($A15)&"/"&RIGHT(YEAR($A15)+1,2),YEAR($A15)-1&"/"&RIGHT(YEAR($A15),2)))
L16: =IF($B16="","",IFERROR(INDEX(Properties!$D$5:$D$104,MATCH($B16,Properties!$A$5:$A$104,0)),"-")) | M16: =IF(OR($A16="",N($E16)=0),"",$F16/$E16) | N16: =IF($A16="","",IF($H16="Y",$F16*(1+Settings!$B$3),0)) | O16: =IF($A16="","",IF(AND($H16="Y",$G16<>"Restock",N($M16)>Settings!$B$4,$I16<>"Y"),"Get host OK",IF(AND($H16="Y",$F16>Settings!$B$5,$I16<>"Y"),"Host should pay upfront",IF($J16<>"Y","Save receipt","OK")))) | P16: =IF($A16="","",DATE(YEAR($A16),MONTH($A16),1)) | Q16: =IF($A16="","",IF(AND($L16='Invoice Builder'!$C$5,$P16='Invoice Builder'!$C$6,N($N16)>0),COUNTIFS($L$5:$L16,'Invoice Builder'!$C$5,$P$5:$P16,'Invoice Builder'!$C$6,$N$5:$N16,">0"),"")) | R16: =IF($A16="","",IF($A16>=DATE(YEAR($A16),4,6),YEAR($A16)&"/"&RIGHT(YEAR($A16)+1,2),YEAR($A16)-1&"/"&RIGHT(YEAR($A16),2)))
L17: =IF($B17="","",IFERROR(INDEX(Properties!$D$5:$D$104,MATCH($B17,Properties!$A$5:$A$104,0)),"-")) | M17: =IF(OR($A17="",N($E17)=0),"",$F17/$E17) | N17: =IF($A17="","",IF($H17="Y",$F17*(1+Settings!$B$3),0)) | O17: =IF($A17="","",IF(AND($H17="Y",$G17<>"Restock",N($M17)>Settings!$B$4,$I17<>"Y"),"Get host OK",IF(AND($H17="Y",$F17>Settings!$B$5,$I17<>"Y"),"Host should pay upfront",IF($J17<>"Y","Save receipt","OK")))) | P17: =IF($A17="","",DATE(YEAR($A17),MONTH($A17),1)) | Q17: =IF($A17="","",IF(AND($L17='Invoice Builder'!$C$5,$P17='Invoice Builder'!$C$6,N($N17)>0),COUNTIFS($L$5:$L17,'Invoice Builder'!$C$5,$P$5:$P17,'Invoice Builder'!$C$6,$N$5:$N17,">0"),"")) | R17: =IF($A17="","",IF($A17>=DATE(YEAR($A17),4,6),YEAR($A17)&"/"&RIGHT(YEAR($A17)+1,2),YEAR($A17)-1&"/"&RIGHT(YEAR($A17),2)))
L18: =IF($B18="","",IFERROR(INDEX(Properties!$D$5:$D$104,MATCH($B18,Properties!$A$5:$A$104,0)),"-")) | M18: =IF(OR($A18="",N($E18)=0),"",$F18/$E18) | N18: =IF($A18="","",IF($H18="Y",$F18*(1+Settings!$B$3),0)) | O18: =IF($A18="","",IF(AND($H18="Y",$G18<>"Restock",N($M18)>Settings!$B$4,$I18<>"Y"),"Get host OK",IF(AND($H18="Y",$F18>Settings!$B$5,$I18<>"Y"),"Host should pay upfront",IF($J18<>"Y","Save receipt","OK")))) | P18: =IF($A18="","",DATE(YEAR($A18),MONTH($A18),1)) | Q18: =IF($A18="","",IF(AND($L18='Invoice Builder'!$C$5,$P18='Invoice Builder'!$C$6,N($N18)>0),COUNTIFS($L$5:$L18,'Invoice Builder'!$C$5,$P$5:$P18,'Invoice Builder'!$C$6,$N$5:$N18,">0"),"")) | R18: =IF($A18="","",IF($A18>=DATE(YEAR($A18),4,6),YEAR($A18)&"/"&RIGHT(YEAR($A18)+1,2),YEAR($A18)-1&"/"&RIGHT(YEAR($A18),2)))
L19: =IF($B19="","",IFERROR(INDEX(Properties!$D$5:$D$104,MATCH($B19,Properties!$A$5:$A$104,0)),"-")) | M19: =IF(OR($A19="",N($E19)=0),"",$F19/$E19) | N19: =IF($A19="","",IF($H19="Y",$F19*(1+Settings!$B$3),0)) | O19: =IF($A19="","",IF(AND($H19="Y",$G19<>"Restock",N($M19)>Settings!$B$4,$I19<>"Y"),"Get host OK",IF(AND($H19="Y",$F19>Settings!$B$5,$I19<>"Y"),"Host should pay upfront",IF($J19<>"Y","Save receipt","OK")))) | P19: =IF($A19="","",DATE(YEAR($A19),MONTH($A19),1)) | Q19: =IF($A19="","",IF(AND($L19='Invoice Builder'!$C$5,$P19='Invoice Builder'!$C$6,N($N19)>0),COUNTIFS($L$5:$L19,'Invoice Builder'!$C$5,$P$5:$P19,'Invoice Builder'!$C$6,$N$5:$N19,">0"),"")) | R19: =IF($A19="","",IF($A19>=DATE(YEAR($A19),4,6),YEAR($A19)&"/"&RIGHT(YEAR($A19)+1,2),YEAR($A19)-1&"/"&RIGHT(YEAR($A19),2)))
... L1004: =IF($B1004="","",IFERROR(INDEX(Properties!$D$5:$D$104,MATCH($B1004,Properties!$A$5:$A$104,0)),"-")) | M1004: =IF(OR($A1004="",N($E1004)=0),"",$F1004/$E1004) | N1004: =IF($A1004="","",IF($H1004="Y",$F1004*(1+Settings!$B$3),0)) | O1004: =IF($A1004="","",IF(AND($H1004="Y",$G1004<>"Restock",N($M1004)>Settings!$B$4,$I1004<>"Y"),"Get host OK",IF(AND($H1004="Y",$F1004>Settings!$B$5,$I1004<>"Y"),"Host should pay upfront",IF($J1004<>"Y","Save receipt","OK")))) | P1004: =IF($A1004="","",DATE(YEAR($A1004),MONTH($A1004),1)) | Q1004: =IF($A1004="","",IF(AND($L1004='Invoice Builder'!$C$5,$P1004='Invoice Builder'!$C$6,N($N1004)>0),COUNTIFS($L$5:$L1004,'Invoice Builder'!$C$5,$P$5:$P1004,'Invoice Builder'!$C$6,$N$5:$N1004,">0"),"")) | R1004: =IF($A1004="","",IF($A1004>=DATE(YEAR($A1004),4,6),YEAR($A1004)&"/"&RIGHT(YEAR($A1004)+1,2),YEAR($A1004)-1&"/"&RIGHT(YEAR($A1004),2)))

Sheet Damage
A1: Damage & Missing Items
A2: Log it the same day, send the host photos. The host claims from the guest via the platform within 14 days of checkout.
A4: Date found | B4: Prop ID | C4: Platform | D4: Guest checkout date | E4: What's damaged / missing | F4: Photos (link / folder) | G4: Host told (date) | H4: Replacement cost (£) | I4: Host's claim | J4: Notes | K4: Host ID | L4: Claim deadline | M4: Days left | N4: Alert
A5: 46319 | B5: P001 | C5: Airbnb | D5: 46319 | E5: 2 wine glasses broken | F5: Turno job photos 24 Oct | G5: 46319 | H5: 4 | I5: Claimed | J5: EXAMPLE | K5: =IF($B5="","",IFERROR(INDEX(Properties!$D$5:$D$104,MATCH($B5,Properties!$A$5:$A$104,0)),"-")) -> H001 | L5: =IF($D5="","",$D5+Settings!$B$16) -> 46333 | M5: =IF(OR($L5="",$I5="Claimed",$I5="Paid",$I5="Refused",$I5="Not claiming"),"",$L5-TODAY()) | N5: =IF($A5="","",IF($G5="","TELL HOST",IF($M5="","",IF($M5<0,"Deadline passed",IF($M5<=3,"Claim soon","")))))
K6: =IF($B6="","",IFERROR(INDEX(Properties!$D$5:$D$104,MATCH($B6,Properties!$A$5:$A$104,0)),"-")) | L6: =IF($D6="","",$D6+Settings!$B$16) | M6: =IF(OR($L6="",$I6="Claimed",$I6="Paid",$I6="Refused",$I6="Not claiming"),"",$L6-TODAY()) | N6: =IF($A6="","",IF($G6="","TELL HOST",IF($M6="","",IF($M6<0,"Deadline passed",IF($M6<=3,"Claim soon","")))))
K7: =IF($B7="","",IFERROR(INDEX(Properties!$D$5:$D$104,MATCH($B7,Properties!$A$5:$A$104,0)),"-")) | L7: =IF($D7="","",$D7+Settings!$B$16) | M7: =IF(OR($L7="",$I7="Claimed",$I7="Paid",$I7="Refused",$I7="Not claiming"),"",$L7-TODAY()) | N7: =IF($A7="","",IF($G7="","TELL HOST",IF($M7="","",IF($M7<0,"Deadline passed",IF($M7<=3,"Claim soon","")))))
K8: =IF($B8="","",IFERROR(INDEX(Properties!$D$5:$D$104,MATCH($B8,Properties!$A$5:$A$104,0)),"-")) | L8: =IF($D8="","",$D8+Settings!$B$16) | M8: =IF(OR($L8="",$I8="Claimed",$I8="Paid",$I8="Refused",$I8="Not claiming"),"",$L8-TODAY()) | N8: =IF($A8="","",IF($G8="","TELL HOST",IF($M8="","",IF($M8<0,"Deadline passed",IF($M8<=3,"Claim soon","")))))
K9: =IF($B9="","",IFERROR(INDEX(Properties!$D$5:$D$104,MATCH($B9,Properties!$A$5:$A$104,0)),"-")) | L9: =IF($D9="","",$D9+Settings!$B$16) | M9: =IF(OR($L9="",$I9="Claimed",$I9="Paid",$I9="Refused",$I9="Not claiming"),"",$L9-TODAY()) | N9: =IF($A9="","",IF($G9="","TELL HOST",IF($M9="","",IF($M9<0,"Deadline passed",IF($M9<=3,"Claim soon","")))))
K10: =IF($B10="","",IFERROR(INDEX(Properties!$D$5:$D$104,MATCH($B10,Properties!$A$5:$A$104,0)),"-")) | L10: =IF($D10="","",$D10+Settings!$B$16) | M10: =IF(OR($L10="",$I10="Claimed",$I10="Paid",$I10="Refused",$I10="Not claiming"),"",$L10-TODAY()) | N10: =IF($A10="","",IF($G10="","TELL HOST",IF($M10="","",IF($M10<0,"Deadline passed",IF($M10<=3,"Claim soon","")))))
K11: =IF($B11="","",IFERROR(INDEX(Properties!$D$5:$D$104,MATCH($B11,Properties!$A$5:$A$104,0)),"-")) | L11: =IF($D11="","",$D11+Settings!$B$16) | M11: =IF(OR($L11="",$I11="Claimed",$I11="Paid",$I11="Refused",$I11="Not claiming"),"",$L11-TODAY()) | N11: =IF($A11="","",IF($G11="","TELL HOST",IF($M11="","",IF($M11<0,"Deadline passed",IF($M11<=3,"Claim soon","")))))
K12: =IF($B12="","",IFERROR(INDEX(Properties!$D$5:$D$104,MATCH($B12,Properties!$A$5:$A$104,0)),"-")) | L12: =IF($D12="","",$D12+Settings!$B$16) | M12: =IF(OR($L12="",$I12="Claimed",$I12="Paid",$I12="Refused",$I12="Not claiming"),"",$L12-TODAY()) | N12: =IF($A12="","",IF($G12="","TELL HOST",IF($M12="","",IF($M12<0,"Deadline passed",IF($M12<=3,"Claim soon","")))))
K13: =IF($B13="","",IFERROR(INDEX(Properties!$D$5:$D$104,MATCH($B13,Properties!$A$5:$A$104,0)),"-")) | L13: =IF($D13="","",$D13+Settings!$B$16) | M13: =IF(OR($L13="",$I13="Claimed",$I13="Paid",$I13="Refused",$I13="Not claiming"),"",$L13-TODAY()) | N13: =IF($A13="","",IF($G13="","TELL HOST",IF($M13="","",IF($M13<0,"Deadline passed",IF($M13<=3,"Claim soon","")))))
K14: =IF($B14="","",IFERROR(INDEX(Properties!$D$5:$D$104,MATCH($B14,Properties!$A$5:$A$104,0)),"-")) | L14: =IF($D14="","",$D14+Settings!$B$16) | M14: =IF(OR($L14="",$I14="Claimed",$I14="Paid",$I14="Refused",$I14="Not claiming"),"",$L14-TODAY()) | N14: =IF($A14="","",IF($G14="","TELL HOST",IF($M14="","",IF($M14<0,"Deadline passed",IF($M14<=3,"Claim soon","")))))
K15: =IF($B15="","",IFERROR(INDEX(Properties!$D$5:$D$104,MATCH($B15,Properties!$A$5:$A$104,0)),"-")) | L15: =IF($D15="","",$D15+Settings!$B$16) | M15: =IF(OR($L15="",$I15="Claimed",$I15="Paid",$I15="Refused",$I15="Not claiming"),"",$L15-TODAY()) | N15: =IF($A15="","",IF($G15="","TELL HOST",IF($M15="","",IF($M15<0,"Deadline passed",IF($M15<=3,"Claim soon","")))))
K16: =IF($B16="","",IFERROR(INDEX(Properties!$D$5:$D$104,MATCH($B16,Properties!$A$5:$A$104,0)),"-")) | L16: =IF($D16="","",$D16+Settings!$B$16) | M16: =IF(OR($L16="",$I16="Claimed",$I16="Paid",$I16="Refused",$I16="Not claiming"),"",$L16-TODAY()) | N16: =IF($A16="","",IF($G16="","TELL HOST",IF($M16="","",IF($M16<0,"Deadline passed",IF($M16<=3,"Claim soon","")))))
K17: =IF($B17="","",IFERROR(INDEX(Properties!$D$5:$D$104,MATCH($B17,Properties!$A$5:$A$104,0)),"-")) | L17: =IF($D17="","",$D17+Settings!$B$16) | M17: =IF(OR($L17="",$I17="Claimed",$I17="Paid",$I17="Refused",$I17="Not claiming"),"",$L17-TODAY()) | N17: =IF($A17="","",IF($G17="","TELL HOST",IF($M17="","",IF($M17<0,"Deadline passed",IF($M17<=3,"Claim soon","")))))
... K304: =IF($B304="","",IFERROR(INDEX(Properties!$D$5:$D$104,MATCH($B304,Properties!$A$5:$A$104,0)),"-")) | L304: =IF($D304="","",$D304+Settings!$B$16) | M304: =IF(OR($L304="",$I304="Claimed",$I304="Paid",$I304="Refused",$I304="Not claiming"),"",$L304-TODAY()) | N304: =IF($A304="","",IF($G304="","TELL HOST",IF($M304="","",IF($M304<0,"Deadline passed",IF($M304<=3,"Claim soon","")))))

Sheet Invoices
A1: Invoices
A2: One row per host per month. Month = the 1st of the month you're billing for. Totals come from Cleans Log and Purchases.
A4: Owed to you now: | B4: =SUMIFS($J$7:$J$306,$L$7:$L$306,"Due")+SUMIFS($J$7:$J$306,$L$7:$L$306,"OVERDUE") -> 232.04
A6: Invoice no. | B6: Host ID | C6: Month (1st) | D6: Sent (date) | E6: Paid (date) | F6: Notes | G6: Cleans | H6: Cleaning (£) | I6: Recharged items (£) | J6: Total (£) | K6: Due | L6: Status
A7: FT-0001 | B7: H001 | C7: 46296 | D7: 46327 | F7: EXAMPLE | G7: =IF($B7="","",COUNTIFS('Cleans Log'!$M$5:$M$1004,$B7,'Cleans Log'!$Q$5:$Q$1004,$C7,'Cleans Log'!$N$5:$N$1004,">0")) -> 4 | H7: =IF($B7="","",SUMIFS('Cleans Log'!$N$5:$N$1004,'Cleans Log'!$M$5:$M$1004,$B7,'Cleans Log'!$Q$5:$Q$1004,$C7)) -> 225 | I7: =IF($B7="","",SUMIFS(Purchases!$N$5:$N$1004,Purchases!$L$5:$L$1004,$B7,Purchases!$P$5:$P$1004,$C7)) -> 7.04 | J7: =IF($B7="","",$H7+$I7) -> 232.04 | K7: =IF(OR($B7="",$D7=""),"",$D7+Settings!$B$12) -> 46334 | L7: =IF($B7="","",IF($E7<>"","Paid",IF($D7="","Not sent",IF(TODAY()>$K7,"OVERDUE","Due")))) -> Due
G8: =IF($B8="","",COUNTIFS('Cleans Log'!$M$5:$M$1004,$B8,'Cleans Log'!$Q$5:$Q$1004,$C8,'Cleans Log'!$N$5:$N$1004,">0")) | H8: =IF($B8="","",SUMIFS('Cleans Log'!$N$5:$N$1004,'Cleans Log'!$M$5:$M$1004,$B8,'Cleans Log'!$Q$5:$Q$1004,$C8)) | I8: =IF($B8="","",SUMIFS(Purchases!$N$5:$N$1004,Purchases!$L$5:$L$1004,$B8,Purchases!$P$5:$P$1004,$C8)) | J8: =IF($B8="","",$H8+$I8) | K8: =IF(OR($B8="",$D8=""),"",$D8+Settings!$B$12) | L8: =IF($B8="","",IF($E8<>"","Paid",IF($D8="","Not sent",IF(TODAY()>$K8,"OVERDUE","Due"))))
G9: =IF($B9="","",COUNTIFS('Cleans Log'!$M$5:$M$1004,$B9,'Cleans Log'!$Q$5:$Q$1004,$C9,'Cleans Log'!$N$5:$N$1004,">0")) | H9: =IF($B9="","",SUMIFS('Cleans Log'!$N$5:$N$1004,'Cleans Log'!$M$5:$M$1004,$B9,'Cleans Log'!$Q$5:$Q$1004,$C9)) | I9: =IF($B9="","",SUMIFS(Purchases!$N$5:$N$1004,Purchases!$L$5:$L$1004,$B9,Purchases!$P$5:$P$1004,$C9)) | J9: =IF($B9="","",$H9+$I9) | K9: =IF(OR($B9="",$D9=""),"",$D9+Settings!$B$12) | L9: =IF($B9="","",IF($E9<>"","Paid",IF($D9="","Not sent",IF(TODAY()>$K9,"OVERDUE","Due"))))
G10: =IF($B10="","",COUNTIFS('Cleans Log'!$M$5:$M$1004,$B10,'Cleans Log'!$Q$5:$Q$1004,$C10,'Cleans Log'!$N$5:$N$1004,">0")) | H10: =IF($B10="","",SUMIFS('Cleans Log'!$N$5:$N$1004,'Cleans Log'!$M$5:$M$1004,$B10,'Cleans Log'!$Q$5:$Q$1004,$C10)) | I10: =IF($B10="","",SUMIFS(Purchases!$N$5:$N$1004,Purchases!$L$5:$L$1004,$B10,Purchases!$P$5:$P$1004,$C10)) | J10: =IF($B10="","",$H10+$I10) | K10: =IF(OR($B10="",$D10=""),"",$D10+Settings!$B$12) | L10: =IF($B10="","",IF($E10<>"","Paid",IF($D10="","Not sent",IF(TODAY()>$K10,"OVERDUE","Due"))))
G11: =IF($B11="","",COUNTIFS('Cleans Log'!$M$5:$M$1004,$B11,'Cleans Log'!$Q$5:$Q$1004,$C11,'Cleans Log'!$N$5:$N$1004,">0")) | H11: =IF($B11="","",SUMIFS('Cleans Log'!$N$5:$N$1004,'Cleans Log'!$M$5:$M$1004,$B11,'Cleans Log'!$Q$5:$Q$1004,$C11)) | I11: =IF($B11="","",SUMIFS(Purchases!$N$5:$N$1004,Purchases!$L$5:$L$1004,$B11,Purchases!$P$5:$P$1004,$C11)) | J11: =IF($B11="","",$H11+$I11) | K11: =IF(OR($B11="",$D11=""),"",$D11+Settings!$B$12) | L11: =IF($B11="","",IF($E11<>"","Paid",IF($D11="","Not sent",IF(TODAY()>$K11,"OVERDUE","Due"))))
G12: =IF($B12="","",COUNTIFS('Cleans Log'!$M$5:$M$1004,$B12,'Cleans Log'!$Q$5:$Q$1004,$C12,'Cleans Log'!$N$5:$N$1004,">0")) | H12: =IF($B12="","",SUMIFS('Cleans Log'!$N$5:$N$1004,'Cleans Log'!$M$5:$M$1004,$B12,'Cleans Log'!$Q$5:$Q$1004,$C12)) | I12: =IF($B12="","",SUMIFS(Purchases!$N$5:$N$1004,Purchases!$L$5:$L$1004,$B12,Purchases!$P$5:$P$1004,$C12)) | J12: =IF($B12="","",$H12+$I12) | K12: =IF(OR($B12="",$D12=""),"",$D12+Settings!$B$12) | L12: =IF($B12="","",IF($E12<>"","Paid",IF($D12="","Not sent",IF(TODAY()>$K12,"OVERDUE","Due"))))
G13: =IF($B13="","",COUNTIFS('Cleans Log'!$M$5:$M$1004,$B13,'Cleans Log'!$Q$5:$Q$1004,$C13,'Cleans Log'!$N$5:$N$1004,">0")) | H13: =IF($B13="","",SUMIFS('Cleans Log'!$N$5:$N$1004,'Cleans Log'!$M$5:$M$1004,$B13,'Cleans Log'!$Q$5:$Q$1004,$C13)) | I13: =IF($B13="","",SUMIFS(Purchases!$N$5:$N$1004,Purchases!$L$5:$L$1004,$B13,Purchases!$P$5:$P$1004,$C13)) | J13: =IF($B13="","",$H13+$I13) | K13: =IF(OR($B13="",$D13=""),"",$D13+Settings!$B$12) | L13: =IF($B13="","",IF($E13<>"","Paid",IF($D13="","Not sent",IF(TODAY()>$K13,"OVERDUE","Due"))))
G14: =IF($B14="","",COUNTIFS('Cleans Log'!$M$5:$M$1004,$B14,'Cleans Log'!$Q$5:$Q$1004,$C14,'Cleans Log'!$N$5:$N$1004,">0")) | H14: =IF($B14="","",SUMIFS('Cleans Log'!$N$5:$N$1004,'Cleans Log'!$M$5:$M$1004,$B14,'Cleans Log'!$Q$5:$Q$1004,$C14)) | I14: =IF($B14="","",SUMIFS(Purchases!$N$5:$N$1004,Purchases!$L$5:$L$1004,$B14,Purchases!$P$5:$P$1004,$C14)) | J14: =IF($B14="","",$H14+$I14) | K14: =IF(OR($B14="",$D14=""),"",$D14+Settings!$B$12) | L14: =IF($B14="","",IF($E14<>"","Paid",IF($D14="","Not sent",IF(TODAY()>$K14,"OVERDUE","Due"))))
G15: =IF($B15="","",COUNTIFS('Cleans Log'!$M$5:$M$1004,$B15,'Cleans Log'!$Q$5:$Q$1004,$C15,'Cleans Log'!$N$5:$N$1004,">0")) | H15: =IF($B15="","",SUMIFS('Cleans Log'!$N$5:$N$1004,'Cleans Log'!$M$5:$M$1004,$B15,'Cleans Log'!$Q$5:$Q$1004,$C15)) | I15: =IF($B15="","",SUMIFS(Purchases!$N$5:$N$1004,Purchases!$L$5:$L$1004,$B15,Purchases!$P$5:$P$1004,$C15)) | J15: =IF($B15="","",$H15+$I15) | K15: =IF(OR($B15="",$D15=""),"",$D15+Settings!$B$12) | L15: =IF($B15="","",IF($E15<>"","Paid",IF($D15="","Not sent",IF(TODAY()>$K15,"OVERDUE","Due"))))
G16: =IF($B16="","",COUNTIFS('Cleans Log'!$M$5:$M$1004,$B16,'Cleans Log'!$Q$5:$Q$1004,$C16,'Cleans Log'!$N$5:$N$1004,">0")) | H16: =IF($B16="","",SUMIFS('Cleans Log'!$N$5:$N$1004,'Cleans Log'!$M$5:$M$1004,$B16,'Cleans Log'!$Q$5:$Q$1004,$C16)) | I16: =IF($B16="","",SUMIFS(Purchases!$N$5:$N$1004,Purchases!$L$5:$L$1004,$B16,Purchases!$P$5:$P$1004,$C16)) | J16: =IF($B16="","",$H16+$I16) | K16: =IF(OR($B16="",$D16=""),"",$D16+Settings!$B$12) | L16: =IF($B16="","",IF($E16<>"","Paid",IF($D16="","Not sent",IF(TODAY()>$K16,"OVERDUE","Due"))))
G17: =IF($B17="","",COUNTIFS('Cleans Log'!$M$5:$M$1004,$B17,'Cleans Log'!$Q$5:$Q$1004,$C17,'Cleans Log'!$N$5:$N$1004,">0")) | H17: =IF($B17="","",SUMIFS('Cleans Log'!$N$5:$N$1004,'Cleans Log'!$M$5:$M$1004,$B17,'Cleans Log'!$Q$5:$Q$1004,$C17)) | I17: =IF($B17="","",SUMIFS(Purchases!$N$5:$N$1004,Purchases!$L$5:$L$1004,$B17,Purchases!$P$5:$P$1004,$C17)) | J17: =IF($B17="","",$H17+$I17) | K17: =IF(OR($B17="",$D17=""),"",$D17+Settings!$B$12) | L17: =IF($B17="","",IF($E17<>"","Paid",IF($D17="","Not sent",IF(TODAY()>$K17,"OVERDUE","Due"))))
G18: =IF($B18="","",COUNTIFS('Cleans Log'!$M$5:$M$1004,$B18,'Cleans Log'!$Q$5:$Q$1004,$C18,'Cleans Log'!$N$5:$N$1004,">0")) | H18: =IF($B18="","",SUMIFS('Cleans Log'!$N$5:$N$1004,'Cleans Log'!$M$5:$M$1004,$B18,'Cleans Log'!$Q$5:$Q$1004,$C18)) | I18: =IF($B18="","",SUMIFS(Purchases!$N$5:$N$1004,Purchases!$L$5:$L$1004,$B18,Purchases!$P$5:$P$1004,$C18)) | J18: =IF($B18="","",$H18+$I18) | K18: =IF(OR($B18="",$D18=""),"",$D18+Settings!$B$12) | L18: =IF($B18="","",IF($E18<>"","Paid",IF($D18="","Not sent",IF(TODAY()>$K18,"OVERDUE","Due"))))
G19: =IF($B19="","",COUNTIFS('Cleans Log'!$M$5:$M$1004,$B19,'Cleans Log'!$Q$5:$Q$1004,$C19,'Cleans Log'!$N$5:$N$1004,">0")) | H19: =IF($B19="","",SUMIFS('Cleans Log'!$N$5:$N$1004,'Cleans Log'!$M$5:$M$1004,$B19,'Cleans Log'!$Q$5:$Q$1004,$C19)) | I19: =IF($B19="","",SUMIFS(Purchases!$N$5:$N$1004,Purchases!$L$5:$L$1004,$B19,Purchases!$P$5:$P$1004,$C19)) | J19: =IF($B19="","",$H19+$I19) | K19: =IF(OR($B19="",$D19=""),"",$D19+Settings!$B$12) | L19: =IF($B19="","",IF($E19<>"","Paid",IF($D19="","Not sent",IF(TODAY()>$K19,"OVERDUE","Due"))))
... G306: =IF($B306="","",COUNTIFS('Cleans Log'!$M$5:$M$1004,$B306,'Cleans Log'!$Q$5:$Q$1004,$C306,'Cleans Log'!$N$5:$N$1004,">0")) | H306: =IF($B306="","",SUMIFS('Cleans Log'!$N$5:$N$1004,'Cleans Log'!$M$5:$M$1004,$B306,'Cleans Log'!$Q$5:$Q$1004,$C306)) | I306: =IF($B306="","",SUMIFS(Purchases!$N$5:$N$1004,Purchases!$L$5:$L$1004,$B306,Purchases!$P$5:$P$1004,$C306)) | J306: =IF($B306="","",$H306+$I306) | K306: =IF(OR($B306="",$D306=""),"",$D306+Settings!$B$12) | L306: =IF($B306="","",IF($E306<>"","Paid",IF($D306="","Not sent",IF(TODAY()>$K306,"OVERDUE","Due"))))

Sheet Invoice Builder
A1: Invoice Builder
A2: Pick a host and month. The itemised lines appear below: copy them into your invoice (Zoho Invoice, Wave, or a Google Doc).
B5: Host ID | C5: H001
B6: Month (1st of month) | C6: 46296
B7: Host name | C7: =IFERROR(INDEX(Hosts!$B$5:$B$54,MATCH($C$5,Hosts!$A$5:$A$54,0)),"") -> First client
B8: Email | C8: =IFERROR(INDEX(Hosts!$D$5:$D$54,MATCH($C$5,Hosts!$A$5:$A$54,0)),"") -> 0
A10: # | B10: Date | C10: Property | D10: Cleaning | E10: Amount (£)
A11: 1 | B11: =IFERROR(INDEX('Cleans Log'!$A$5:$A$1004,MATCH($A11,'Cleans Log'!$S$5:$S$1004,0)),"") -> 46298 | C11: =IFERROR(INDEX(Properties!$B$5:$B$104,MATCH(INDEX('Cleans Log'!$B$5:$B$1004,MATCH($A11,'Cleans Log'!$S$5:$S$1004,0)),Properties!$A$5:$A$104,0)),"") -> First client (EXAMPLE) | D11: =IFERROR(IF(INDEX('Cleans Log'!$D$5:$D$1004,MATCH($A11,'Cleans Log'!$S$5:$S$1004,0))="Completed","Changeover clean",IF(INDEX('Cleans Log'!$D$5:$D$1004,MATCH($A11,'Cleans Log'!$S$5:$S$1004,0))="Late cancel","Late cancellation (50%)",INDEX('Cleans Log'!$D$5:$D$1004,MATCH($A11,'Cleans Log'!$S$5:$S$1004,0))))&IF(INDEX('Cleans Log'!$G$5:$G$1004,MATCH($A11,'Cleans Log'!$S$5:$S$1004,0))="Y"," + same-day rush","")&IF(INDEX('Cleans Log'!$H$5:$H$1004,MATCH($A11,'Cleans Log'!$S$5:$S$1004,0))="Y"," + hot tub check",""),"") -> Changeover clean | E11: =IFERROR(INDEX('Cleans Log'!$N$5:$N$1004,MATCH($A11,'Cleans Log'!$S$5:$S$1004,0)),"") -> 60
A12: 2 | B12: =IFERROR(INDEX('Cleans Log'!$A$5:$A$1004,MATCH($A12,'Cleans Log'!$S$5:$S$1004,0)),"") -> 46305 | C12: =IFERROR(INDEX(Properties!$B$5:$B$104,MATCH(INDEX('Cleans Log'!$B$5:$B$1004,MATCH($A12,'Cleans Log'!$S$5:$S$1004,0)),Properties!$A$5:$A$104,0)),"") -> First client (EXAMPLE) | D12: =IFERROR(IF(INDEX('Cleans Log'!$D$5:$D$1004,MATCH($A12,'Cleans Log'!$S$5:$S$1004,0))="Completed","Changeover clean",IF(INDEX('Cleans Log'!$D$5:$D$1004,MATCH($A12,'Cleans Log'!$S$5:$S$1004,0))="Late cancel","Late cancellation (50%)",INDEX('Cleans Log'!$D$5:$D$1004,MATCH($A12,'Cleans Log'!$S$5:$S$1004,0))))&IF(INDEX('Cleans Log'!$G$5:$G$1004,MATCH($A12,'Cleans Log'!$S$5:$S$1004,0))="Y"," + same-day rush","")&IF(INDEX('Cleans Log'!$H$5:$H$1004,MATCH($A12,'Cleans Log'!$S$5:$S$1004,0))="Y"," + hot tub check",""),"") -> Changeover clean | E12: =IFERROR(INDEX('Cleans Log'!$N$5:$N$1004,MATCH($A12,'Cleans Log'!$S$5:$S$1004,0)),"") -> 60
A13: 3 | B13: =IFERROR(INDEX('Cleans Log'!$A$5:$A$1004,MATCH($A13,'Cleans Log'!$S$5:$S$1004,0)),"") -> 46312 | C13: =IFERROR(INDEX(Properties!$B$5:$B$104,MATCH(INDEX('Cleans Log'!$B$5:$B$1004,MATCH($A13,'Cleans Log'!$S$5:$S$1004,0)),Properties!$A$5:$A$104,0)),"") -> First client (EXAMPLE) | D13: =IFERROR(IF(INDEX('Cleans Log'!$D$5:$D$1004,MATCH($A13,'Cleans Log'!$S$5:$S$1004,0))="Completed","Changeover clean",IF(INDEX('Cleans Log'!$D$5:$D$1004,MATCH($A13,'Cleans Log'!$S$5:$S$1004,0))="Late cancel","Late cancellation (50%)",INDEX('Cleans Log'!$D$5:$D$1004,MATCH($A13,'Cleans Log'!$S$5:$S$1004,0))))&IF(INDEX('Cleans Log'!$G$5:$G$1004,MATCH($A13,'Cleans Log'!$S$5:$S$1004,0))="Y"," + same-day rush","")&IF(INDEX('Cleans Log'!$H$5:$H$1004,MATCH($A13,'Cleans Log'!$S$5:$S$1004,0))="Y"," + hot tub check",""),"") -> Changeover clean + same-day rush | E13: =IFERROR(INDEX('Cleans Log'!$N$5:$N$1004,MATCH($A13,'Cleans Log'!$S$5:$S$1004,0)),"") -> 75
A14: 4 | B14: =IFERROR(INDEX('Cleans Log'!$A$5:$A$1004,MATCH($A14,'Cleans Log'!$S$5:$S$1004,0)),"") -> 46319 | C14: =IFERROR(INDEX(Properties!$B$5:$B$104,MATCH(INDEX('Cleans Log'!$B$5:$B$1004,MATCH($A14,'Cleans Log'!$S$5:$S$1004,0)),Properties!$A$5:$A$104,0)),"") -> First client (EXAMPLE) | D14: =IFERROR(IF(INDEX('Cleans Log'!$D$5:$D$1004,MATCH($A14,'Cleans Log'!$S$5:$S$1004,0))="Completed","Changeover clean",IF(INDEX('Cleans Log'!$D$5:$D$1004,MATCH($A14,'Cleans Log'!$S$5:$S$1004,0))="Late cancel","Late cancellation (50%)",INDEX('Cleans Log'!$D$5:$D$1004,MATCH($A14,'Cleans Log'!$S$5:$S$1004,0))))&IF(INDEX('Cleans Log'!$G$5:$G$1004,MATCH($A14,'Cleans Log'!$S$5:$S$1004,0))="Y"," + same-day rush","")&IF(INDEX('Cleans Log'!$H$5:$H$1004,MATCH($A14,'Cleans Log'!$S$5:$S$1004,0))="Y"," + hot tub check",""),"") -> Late cancellation (50%) | E14: =IFERROR(INDEX('Cleans Log'!$N$5:$N$1004,MATCH($A14,'Cleans Log'!$S$5:$S$1004,0)),"") -> 30
A15: 5 | B15: =IFERROR(INDEX('Cleans Log'!$A$5:$A$1004,MATCH($A15,'Cleans Log'!$S$5:$S$1004,0)),"") | C15: =IFERROR(INDEX(Properties!$B$5:$B$104,MATCH(INDEX('Cleans Log'!$B$5:$B$1004,MATCH($A15,'Cleans Log'!$S$5:$S$1004,0)),Properties!$A$5:$A$104,0)),"") | D15: =IFERROR(IF(INDEX('Cleans Log'!$D$5:$D$1004,MATCH($A15,'Cleans Log'!$S$5:$S$1004,0))="Completed","Changeover clean",IF(INDEX('Cleans Log'!$D$5:$D$1004,MATCH($A15,'Cleans Log'!$S$5:$S$1004,0))="Late cancel","Late cancellation (50%)",INDEX('Cleans Log'!$D$5:$D$1004,MATCH($A15,'Cleans Log'!$S$5:$S$1004,0))))&IF(INDEX('Cleans Log'!$G$5:$G$1004,MATCH($A15,'Cleans Log'!$S$5:$S$1004,0))="Y"," + same-day rush","")&IF(INDEX('Cleans Log'!$H$5:$H$1004,MATCH($A15,'Cleans Log'!$S$5:$S$1004,0))="Y"," + hot tub check",""),"") | E15: =IFERROR(INDEX('Cleans Log'!$N$5:$N$1004,MATCH($A15,'Cleans Log'!$S$5:$S$1004,0)),"")
A16: 6 | B16: =IFERROR(INDEX('Cleans Log'!$A$5:$A$1004,MATCH($A16,'Cleans Log'!$S$5:$S$1004,0)),"") | C16: =IFERROR(INDEX(Properties!$B$5:$B$104,MATCH(INDEX('Cleans Log'!$B$5:$B$1004,MATCH($A16,'Cleans Log'!$S$5:$S$1004,0)),Properties!$A$5:$A$104,0)),"") | D16: =IFERROR(IF(INDEX('Cleans Log'!$D$5:$D$1004,MATCH($A16,'Cleans Log'!$S$5:$S$1004,0))="Completed","Changeover clean",IF(INDEX('Cleans Log'!$D$5:$D$1004,MATCH($A16,'Cleans Log'!$S$5:$S$1004,0))="Late cancel","Late cancellation (50%)",INDEX('Cleans Log'!$D$5:$D$1004,MATCH($A16,'Cleans Log'!$S$5:$S$1004,0))))&IF(INDEX('Cleans Log'!$G$5:$G$1004,MATCH($A16,'Cleans Log'!$S$5:$S$1004,0))="Y"," + same-day rush","")&IF(INDEX('Cleans Log'!$H$5:$H$1004,MATCH($A16,'Cleans Log'!$S$5:$S$1004,0))="Y"," + hot tub check",""),"") | E16: =IFERROR(INDEX('Cleans Log'!$N$5:$N$1004,MATCH($A16,'Cleans Log'!$S$5:$S$1004,0)),"")
A17: 7 | B17: =IFERROR(INDEX('Cleans Log'!$A$5:$A$1004,MATCH($A17,'Cleans Log'!$S$5:$S$1004,0)),"") | C17: =IFERROR(INDEX(Properties!$B$5:$B$104,MATCH(INDEX('Cleans Log'!$B$5:$B$1004,MATCH($A17,'Cleans Log'!$S$5:$S$1004,0)),Properties!$A$5:$A$104,0)),"") | D17: =IFERROR(IF(INDEX('Cleans Log'!$D$5:$D$1004,MATCH($A17,'Cleans Log'!$S$5:$S$1004,0))="Completed","Changeover clean",IF(INDEX('Cleans Log'!$D$5:$D$1004,MATCH($A17,'Cleans Log'!$S$5:$S$1004,0))="Late cancel","Late cancellation (50%)",INDEX('Cleans Log'!$D$5:$D$1004,MATCH($A17,'Cleans Log'!$S$5:$S$1004,0))))&IF(INDEX('Cleans Log'!$G$5:$G$1004,MATCH($A17,'Cleans Log'!$S$5:$S$1004,0))="Y"," + same-day rush","")&IF(INDEX('Cleans Log'!$H$5:$H$1004,MATCH($A17,'Cleans Log'!$S$5:$S$1004,0))="Y"," + hot tub check",""),"") | E17: =IFERROR(INDEX('Cleans Log'!$N$5:$N$1004,MATCH($A17,'Cleans Log'!$S$5:$S$1004,0)),"")
A18: 8 | B18: =IFERROR(INDEX('Cleans Log'!$A$5:$A$1004,MATCH($A18,'Cleans Log'!$S$5:$S$1004,0)),"") | C18: =IFERROR(INDEX(Properties!$B$5:$B$104,MATCH(INDEX('Cleans Log'!$B$5:$B$1004,MATCH($A18,'Cleans Log'!$S$5:$S$1004,0)),Properties!$A$5:$A$104,0)),"") | D18: =IFERROR(IF(INDEX('Cleans Log'!$D$5:$D$1004,MATCH($A18,'Cleans Log'!$S$5:$S$1004,0))="Completed","Changeover clean",IF(INDEX('Cleans Log'!$D$5:$D$1004,MATCH($A18,'Cleans Log'!$S$5:$S$1004,0))="Late cancel","Late cancellation (50%)",INDEX('Cleans Log'!$D$5:$D$1004,MATCH($A18,'Cleans Log'!$S$5:$S$1004,0))))&IF(INDEX('Cleans Log'!$G$5:$G$1004,MATCH($A18,'Cleans Log'!$S$5:$S$1004,0))="Y"," + same-day rush","")&IF(INDEX('Cleans Log'!$H$5:$H$1004,MATCH($A18,'Cleans Log'!$S$5:$S$1004,0))="Y"," + hot tub check",""),"") | E18: =IFERROR(INDEX('Cleans Log'!$N$5:$N$1004,MATCH($A18,'Cleans Log'!$S$5:$S$1004,0)),"")
A19: 9 | B19: =IFERROR(INDEX('Cleans Log'!$A$5:$A$1004,MATCH($A19,'Cleans Log'!$S$5:$S$1004,0)),"") | C19: =IFERROR(INDEX(Properties!$B$5:$B$104,MATCH(INDEX('Cleans Log'!$B$5:$B$1004,MATCH($A19,'Cleans Log'!$S$5:$S$1004,0)),Properties!$A$5:$A$104,0)),"") | D19: =IFERROR(IF(INDEX('Cleans Log'!$D$5:$D$1004,MATCH($A19,'Cleans Log'!$S$5:$S$1004,0))="Completed","Changeover clean",IF(INDEX('Cleans Log'!$D$5:$D$1004,MATCH($A19,'Cleans Log'!$S$5:$S$1004,0))="Late cancel","Late cancellation (50%)",INDEX('Cleans Log'!$D$5:$D$1004,MATCH($A19,'Cleans Log'!$S$5:$S$1004,0))))&IF(INDEX('Cleans Log'!$G$5:$G$1004,MATCH($A19,'Cleans Log'!$S$5:$S$1004,0))="Y"," + same-day rush","")&IF(INDEX('Cleans Log'!$H$5:$H$1004,MATCH($A19,'Cleans Log'!$S$5:$S$1004,0))="Y"," + hot tub check",""),"") | E19: =IFERROR(INDEX('Cleans Log'!$N$5:$N$1004,MATCH($A19,'Cleans Log'!$S$5:$S$1004,0)),"")
A20: 10 | B20: =IFERROR(INDEX('Cleans Log'!$A$5:$A$1004,MATCH($A20,'Cleans Log'!$S$5:$S$1004,0)),"") | C20: =IFERROR(INDEX(Properties!$B$5:$B$104,MATCH(INDEX('Cleans Log'!$B$5:$B$1004,MATCH($A20,'Cleans Log'!$S$5:$S$1004,0)),Properties!$A$5:$A$104,0)),"") | D20: =IFERROR(IF(INDEX('Cleans Log'!$D$5:$D$1004,MATCH($A20,'Cleans Log'!$S$5:$S$1004,0))="Completed","Changeover clean",IF(INDEX('Cleans Log'!$D$5:$D$1004,MATCH($A20,'Cleans Log'!$S$5:$S$1004,0))="Late cancel","Late cancellation (50%)",INDEX('Cleans Log'!$D$5:$D$1004,MATCH($A20,'Cleans Log'!$S$5:$S$1004,0))))&IF(INDEX('Cleans Log'!$G$5:$G$1004,MATCH($A20,'Cleans Log'!$S$5:$S$1004,0))="Y"," + same-day rush","")&IF(INDEX('Cleans Log'!$H$5:$H$1004,MATCH($A20,'Cleans Log'!$S$5:$S$1004,0))="Y"," + hot tub check",""),"") | E20: =IFERROR(INDEX('Cleans Log'!$N$5:$N$1004,MATCH($A20,'Cleans Log'!$S$5:$S$1004,0)),"")
A21: 11 | B21: =IFERROR(INDEX('Cleans Log'!$A$5:$A$1004,MATCH($A21,'Cleans Log'!$S$5:$S$1004,0)),"") | C21: =IFERROR(INDEX(Properties!$B$5:$B$104,MATCH(INDEX('Cleans Log'!$B$5:$B$1004,MATCH($A21,'Cleans Log'!$S$5:$S$1004,0)),Properties!$A$5:$A$104,0)),"") | D21: =IFERROR(IF(INDEX('Cleans Log'!$D$5:$D$1004,MATCH($A21,'Cleans Log'!$S$5:$S$1004,0))="Completed","Changeover clean",IF(INDEX('Cleans Log'!$D$5:$D$1004,MATCH($A21,'Cleans Log'!$S$5:$S$1004,0))="Late cancel","Late cancellation (50%)",INDEX('Cleans Log'!$D$5:$D$1004,MATCH($A21,'Cleans Log'!$S$5:$S$1004,0))))&IF(INDEX('Cleans Log'!$G$5:$G$1004,MATCH($A21,'Cleans Log'!$S$5:$S$1004,0))="Y"," + same-day rush","")&IF(INDEX('Cleans Log'!$H$5:$H$1004,MATCH($A21,'Cleans Log'!$S$5:$S$1004,0))="Y"," + hot tub check",""),"") | E21: =IFERROR(INDEX('Cleans Log'!$N$5:$N$1004,MATCH($A21,'Cleans Log'!$S$5:$S$1004,0)),"")
A22: 12 | B22: =IFERROR(INDEX('Cleans Log'!$A$5:$A$1004,MATCH($A22,'Cleans Log'!$S$5:$S$1004,0)),"") | C22: =IFERROR(INDEX(Properties!$B$5:$B$104,MATCH(INDEX('Cleans Log'!$B$5:$B$1004,MATCH($A22,'Cleans Log'!$S$5:$S$1004,0)),Properties!$A$5:$A$104,0)),"") | D22: =IFERROR(IF(INDEX('Cleans Log'!$D$5:$D$1004,MATCH($A22,'Cleans Log'!$S$5:$S$1004,0))="Completed","Changeover clean",IF(INDEX('Cleans Log'!$D$5:$D$1004,MATCH($A22,'Cleans Log'!$S$5:$S$1004,0))="Late cancel","Late cancellation (50%)",INDEX('Cleans Log'!$D$5:$D$1004,MATCH($A22,'Cleans Log'!$S$5:$S$1004,0))))&IF(INDEX('Cleans Log'!$G$5:$G$1004,MATCH($A22,'Cleans Log'!$S$5:$S$1004,0))="Y"," + same-day rush","")&IF(INDEX('Cleans Log'!$H$5:$H$1004,MATCH($A22,'Cleans Log'!$S$5:$S$1004,0))="Y"," + hot tub check",""),"") | E22: =IFERROR(INDEX('Cleans Log'!$N$5:$N$1004,MATCH($A22,'Cleans Log'!$S$5:$S$1004,0)),"")
... A55: 45 | B55: =IFERROR(INDEX('Cleans Log'!$A$5:$A$1004,MATCH($A55,'Cleans Log'!$S$5:$S$1004,0)),"") | C55: =IFERROR(INDEX(Properties!$B$5:$B$104,MATCH(INDEX('Cleans Log'!$B$5:$B$1004,MATCH($A55,'Cleans Log'!$S$5:$S$1004,0)),Properties!$A$5:$A$104,0)),"") | D55: =IFERROR(IF(INDEX('Cleans Log'!$D$5:$D$1004,MATCH($A55,'Cleans Log'!$S$5:$S$1004,0))="Completed","Changeover clean",IF(INDEX('Cleans Log'!$D$5:$D$1004,MATCH($A55,'Cleans Log'!$S$5:$S$1004,0))="Late cancel","Late cancellation (50%)",INDEX('Cleans Log'!$D$5:$D$1004,MATCH($A55,'Cleans Log'!$S$5:$S$1004,0))))&IF(INDEX('Cleans Log'!$G$5:$G$1004,MATCH($A55,'Cleans Log'!$S$5:$S$1004,0))="Y"," + same-day rush","")&IF(INDEX('Cleans Log'!$H$5:$H$1004,MATCH($A55,'Cleans Log'!$S$5:$S$1004,0))="Y"," + hot tub check",""),"") | E55: =IFERROR(INDEX('Cleans Log'!$N$5:$N$1004,MATCH($A55,'Cleans Log'!$S$5:$S$1004,0)),"")
A57: # | B57: Date | C57: Property | D57: Supplies & replacements (cost + markup) | E57: Amount (£)
A58: 1 | B58: =IFERROR(INDEX(Purchases!$A$5:$A$1004,MATCH($A58,Purchases!$Q$5:$Q$1004,0)),"") -> 46304 | C58: =IFERROR(INDEX(Properties!$B$5:$B$104,MATCH(INDEX(Purchases!$B$5:$B$1004,MATCH($A58,Purchases!$Q$5:$Q$1004,0)),Properties!$A$5:$A$104,0)),"") -> First client (EXAMPLE) | D58: =IFERROR(INDEX(Purchases!$D$5:$D$1004,MATCH($A58,Purchases!$Q$5:$Q$1004,0))&" x"&INDEX(Purchases!$E$5:$E$1004,MATCH($A58,Purchases!$Q$5:$Q$1004,0))&" ("&INDEX(Purchases!$G$5:$G$1004,MATCH($A58,Purchases!$Q$5:$Q$1004,0))&")","") -> LED bulb E27 x1 (Replacement) | E58: =IFERROR(INDEX(Purchases!$N$5:$N$1004,MATCH($A58,Purchases!$Q$5:$Q$1004,0)),"") -> 1.65
A59: 2 | B59: =IFERROR(INDEX(Purchases!$A$5:$A$1004,MATCH($A59,Purchases!$Q$5:$Q$1004,0)),"") -> 46320 | C59: =IFERROR(INDEX(Properties!$B$5:$B$104,MATCH(INDEX(Purchases!$B$5:$B$1004,MATCH($A59,Purchases!$Q$5:$Q$1004,0)),Properties!$A$5:$A$104,0)),"") -> First client (EXAMPLE) | D59: =IFERROR(INDEX(Purchases!$D$5:$D$1004,MATCH($A59,Purchases!$Q$5:$Q$1004,0))&" x"&INDEX(Purchases!$E$5:$E$1004,MATCH($A59,Purchases!$Q$5:$Q$1004,0))&" ("&INDEX(Purchases!$G$5:$G$1004,MATCH($A59,Purchases!$Q$5:$Q$1004,0))&")","") -> UHT milk portions x12 (Restock) | E59: =IFERROR(INDEX(Purchases!$N$5:$N$1004,MATCH($A59,Purchases!$Q$5:$Q$1004,0)),"") -> 0.99
A60: 3 | B60: =IFERROR(INDEX(Purchases!$A$5:$A$1004,MATCH($A60,Purchases!$Q$5:$Q$1004,0)),"") -> 46320 | C60: =IFERROR(INDEX(Properties!$B$5:$B$104,MATCH(INDEX(Purchases!$B$5:$B$1004,MATCH($A60,Purchases!$Q$5:$Q$1004,0)),Properties!$A$5:$A$104,0)),"") -> First client (EXAMPLE) | D60: =IFERROR(INDEX(Purchases!$D$5:$D$1004,MATCH($A60,Purchases!$Q$5:$Q$1004,0))&" x"&INDEX(Purchases!$E$5:$E$1004,MATCH($A60,Purchases!$Q$5:$Q$1004,0))&" ("&INDEX(Purchases!$G$5:$G$1004,MATCH($A60,Purchases!$Q$5:$Q$1004,0))&")","") -> Wine glasses (guest broke 2) x2 (Guest damage) | E60: =IFERROR(INDEX(Purchases!$N$5:$N$1004,MATCH($A60,Purchases!$Q$5:$Q$1004,0)),"") -> 4.4
A61: 4 | B61: =IFERROR(INDEX(Purchases!$A$5:$A$1004,MATCH($A61,Purchases!$Q$5:$Q$1004,0)),"") | C61: =IFERROR(INDEX(Properties!$B$5:$B$104,MATCH(INDEX(Purchases!$B$5:$B$1004,MATCH($A61,Purchases!$Q$5:$Q$1004,0)),Properties!$A$5:$A$104,0)),"") | D61: =IFERROR(INDEX(Purchases!$D$5:$D$1004,MATCH($A61,Purchases!$Q$5:$Q$1004,0))&" x"&INDEX(Purchases!$E$5:$E$1004,MATCH($A61,Purchases!$Q$5:$Q$1004,0))&" ("&INDEX(Purchases!$G$5:$G$1004,MATCH($A61,Purchases!$Q$5:$Q$1004,0))&")","") | E61: =IFERROR(INDEX(Purchases!$N$5:$N$1004,MATCH($A61,Purchases!$Q$5:$Q$1004,0)),"")
A62: 5 | B62: =IFERROR(INDEX(Purchases!$A$5:$A$1004,MATCH($A62,Purchases!$Q$5:$Q$1004,0)),"") | C62: =IFERROR(INDEX(Properties!$B$5:$B$104,MATCH(INDEX(Purchases!$B$5:$B$1004,MATCH($A62,Purchases!$Q$5:$Q$1004,0)),Properties!$A$5:$A$104,0)),"") | D62: =IFERROR(INDEX(Purchases!$D$5:$D$1004,MATCH($A62,Purchases!$Q$5:$Q$1004,0))&" x"&INDEX(Purchases!$E$5:$E$1004,MATCH($A62,Purchases!$Q$5:$Q$1004,0))&" ("&INDEX(Purchases!$G$5:$G$1004,MATCH($A62,Purchases!$Q$5:$Q$1004,0))&")","") | E62: =IFERROR(INDEX(Purchases!$N$5:$N$1004,MATCH($A62,Purchases!$Q$5:$Q$1004,0)),"")
A63: 6 | B63: =IFERROR(INDEX(Purchases!$A$5:$A$1004,MATCH($A63,Purchases!$Q$5:$Q$1004,0)),"") | C63: =IFERROR(INDEX(Properties!$B$5:$B$104,MATCH(INDEX(Purchases!$B$5:$B$1004,MATCH($A63,Purchases!$Q$5:$Q$1004,0)),Properties!$A$5:$A$104,0)),"") | D63: =IFERROR(INDEX(Purchases!$D$5:$D$1004,MATCH($A63,Purchases!$Q$5:$Q$1004,0))&" x"&INDEX(Purchases!$E$5:$E$1004,MATCH($A63,Purchases!$Q$5:$Q$1004,0))&" ("&INDEX(Purchases!$G$5:$G$1004,MATCH($A63,Purchases!$Q$5:$Q$1004,0))&")","") | E63: =IFERROR(INDEX(Purchases!$N$5:$N$1004,MATCH($A63,Purchases!$Q$5:$Q$1004,0)),"")
A64: 7 | B64: =IFERROR(INDEX(Purchases!$A$5:$A$1004,MATCH($A64,Purchases!$Q$5:$Q$1004,0)),"") | C64: =IFERROR(INDEX(Properties!$B$5:$B$104,MATCH(INDEX(Purchases!$B$5:$B$1004,MATCH($A64,Purchases!$Q$5:$Q$1004,0)),Properties!$A$5:$A$104,0)),"") | D64: =IFERROR(INDEX(Purchases!$D$5:$D$1004,MATCH($A64,Purchases!$Q$5:$Q$1004,0))&" x"&INDEX(Purchases!$E$5:$E$1004,MATCH($A64,Purchases!$Q$5:$Q$1004,0))&" ("&INDEX(Purchases!$G$5:$G$1004,MATCH($A64,Purchases!$Q$5:$Q$1004,0))&")","") | E64: =IFERROR(INDEX(Purchases!$N$5:$N$1004,MATCH($A64,Purchases!$Q$5:$Q$1004,0)),"")
A65: 8 | B65: =IFERROR(INDEX(Purchases!$A$5:$A$1004,MATCH($A65,Purchases!$Q$5:$Q$1004,0)),"") | C65: =IFERROR(INDEX(Properties!$B$5:$B$104,MATCH(INDEX(Purchases!$B$5:$B$1004,MATCH($A65,Purchases!$Q$5:$Q$1004,0)),Properties!$A$5:$A$104,0)),"") | D65: =IFERROR(INDEX(Purchases!$D$5:$D$1004,MATCH($A65,Purchases!$Q$5:$Q$1004,0))&" x"&INDEX(Purchases!$E$5:$E$1004,MATCH($A65,Purchases!$Q$5:$Q$1004,0))&" ("&INDEX(Purchases!$G$5:$G$1004,MATCH($A65,Purchases!$Q$5:$Q$1004,0))&")","") | E65: =IFERROR(INDEX(Purchases!$N$5:$N$1004,MATCH($A65,Purchases!$Q$5:$Q$1004,0)),"")
A66: 9 | B66: =IFERROR(INDEX(Purchases!$A$5:$A$1004,MATCH($A66,Purchases!$Q$5:$Q$1004,0)),"") | C66: =IFERROR(INDEX(Properties!$B$5:$B$104,MATCH(INDEX(Purchases!$B$5:$B$1004,MATCH($A66,Purchases!$Q$5:$Q$1004,0)),Properties!$A$5:$A$104,0)),"") | D66: =IFERROR(INDEX(Purchases!$D$5:$D$1004,MATCH($A66,Purchases!$Q$5:$Q$1004,0))&" x"&INDEX(Purchases!$E$5:$E$1004,MATCH($A66,Purchases!$Q$5:$Q$1004,0))&" ("&INDEX(Purchases!$G$5:$G$1004,MATCH($A66,Purchases!$Q$5:$Q$1004,0))&")","") | E66: =IFERROR(INDEX(Purchases!$N$5:$N$1004,MATCH($A66,Purchases!$Q$5:$Q$1004,0)),"")
A67: 10 | B67: =IFERROR(INDEX(Purchases!$A$5:$A$1004,MATCH($A67,Purchases!$Q$5:$Q$1004,0)),"") | C67: =IFERROR(INDEX(Properties!$B$5:$B$104,MATCH(INDEX(Purchases!$B$5:$B$1004,MATCH($A67,Purchases!$Q$5:$Q$1004,0)),Properties!$A$5:$A$104,0)),"") | D67: =IFERROR(INDEX(Purchases!$D$5:$D$1004,MATCH($A67,Purchases!$Q$5:$Q$1004,0))&" x"&INDEX(Purchases!$E$5:$E$1004,MATCH($A67,Purchases!$Q$5:$Q$1004,0))&" ("&INDEX(Purchases!$G$5:$G$1004,MATCH($A67,Purchases!$Q$5:$Q$1004,0))&")","") | E67: =IFERROR(INDEX(Purchases!$N$5:$N$1004,MATCH($A67,Purchases!$Q$5:$Q$1004,0)),"")
A68: 11 | B68: =IFERROR(INDEX(Purchases!$A$5:$A$1004,MATCH($A68,Purchases!$Q$5:$Q$1004,0)),"") | C68: =IFERROR(INDEX(Properties!$B$5:$B$104,MATCH(INDEX(Purchases!$B$5:$B$1004,MATCH($A68,Purchases!$Q$5:$Q$1004,0)),Properties!$A$5:$A$104,0)),"") | D68: =IFERROR(INDEX(Purchases!$D$5:$D$1004,MATCH($A68,Purchases!$Q$5:$Q$1004,0))&" x"&INDEX(Purchases!$E$5:$E$1004,MATCH($A68,Purchases!$Q$5:$Q$1004,0))&" ("&INDEX(Purchases!$G$5:$G$1004,MATCH($A68,Purchases!$Q$5:$Q$1004,0))&")","") | E68: =IFERROR(INDEX(Purchases!$N$5:$N$1004,MATCH($A68,Purchases!$Q$5:$Q$1004,0)),"")
A69: 12 | B69: =IFERROR(INDEX(Purchases!$A$5:$A$1004,MATCH($A69,Purchases!$Q$5:$Q$1004,0)),"") | C69: =IFERROR(INDEX(Properties!$B$5:$B$104,MATCH(INDEX(Purchases!$B$5:$B$1004,MATCH($A69,Purchases!$Q$5:$Q$1004,0)),Properties!$A$5:$A$104,0)),"") | D69: =IFERROR(INDEX(Purchases!$D$5:$D$1004,MATCH($A69,Purchases!$Q$5:$Q$1004,0))&" x"&INDEX(Purchases!$E$5:$E$1004,MATCH($A69,Purchases!$Q$5:$Q$1004,0))&" ("&INDEX(Purchases!$G$5:$G$1004,MATCH($A69,Purchases!$Q$5:$Q$1004,0))&")","") | E69: =IFERROR(INDEX(Purchases!$N$5:$N$1004,MATCH($A69,Purchases!$Q$5:$Q$1004,0)),"")
... A82: 25 | B82: =IFERROR(INDEX(Purchases!$A$5:$A$1004,MATCH($A82,Purchases!$Q$5:$Q$1004,0)),"") | C82: =IFERROR(INDEX(Properties!$B$5:$B$104,MATCH(INDEX(Purchases!$B$5:$B$1004,MATCH($A82,Purchases!$Q$5:$Q$1004,0)),Properties!$A$5:$A$104,0)),"") | D82: =IFERROR(INDEX(Purchases!$D$5:$D$1004,MATCH($A82,Purchases!$Q$5:$Q$1004,0))&" x"&INDEX(Purchases!$E$5:$E$1004,MATCH($A82,Purchases!$Q$5:$Q$1004,0))&" ("&INDEX(Purchases!$G$5:$G$1004,MATCH($A82,Purchases!$Q$5:$Q$1004,0))&")","") | E82: =IFERROR(INDEX(Purchases!$N$5:$N$1004,MATCH($A82,Purchases!$Q$5:$Q$1004,0)),"")
D84: TOTAL | E84: =SUM(E11:E55)+SUM(E58:E82) -> 232.04
D85: Payment due within 7 days of the invoice date. Thank you!
B87: =IF(COUNTIF('Cleans Log'!$S$5:$S$1004,">45")+COUNTIF(Purchases!$Q$5:$Q$1004,">25")>0,"Warning: more lines than fit here. Extend the list.","")

Sheet Cleaner Pay
A1: Cleaner Pay
A2: Work weeks run Saturday to Friday. Pay on the following Friday. Add one row per cleaner per week.
A4: Work week ending (Fri) | B4: Cleaner ID | C4: Paid (date) | D4: Payment ref | E4: Notes | F4: Name | G4: Jobs | H4: Amount (£) | I4: Pay on | J4: Status
A5: 46304 | B5: C001 | C5: 46311 | E5: EXAMPLE | F5: =IF($B5="","",IFERROR(INDEX(Cleaners!$B$5:$B$34,MATCH($B5,Cleaners!$A$5:$A$34,0)),"?")) -> Cleaner 1 | G5: =IF($B5="","",COUNTIFS('Cleans Log'!$C$5:$C$1004,$B5,'Cleans Log'!$R$5:$R$1004,$A5,'Cleans Log'!$O$5:$O$1004,">0")) -> 1 | H5: =IF($B5="","",SUMIFS('Cleans Log'!$O$5:$O$1004,'Cleans Log'!$C$5:$C$1004,$B5,'Cleans Log'!$R$5:$R$1004,$A5)) -> 40 | I5: =IF($A5="","",$A5+7) -> 46311 | J5: =IF($B5="","",IF($C5<>"","Paid",IF(TODAY()>=$I5,"PAY NOW","Upcoming"))) -> Paid
A6: 46318 | B6: C002 | E6: EXAMPLE | F6: =IF($B6="","",IFERROR(INDEX(Cleaners!$B$5:$B$34,MATCH($B6,Cleaners!$A$5:$A$34,0)),"?")) -> Cleaner 2 | G6: =IF($B6="","",COUNTIFS('Cleans Log'!$C$5:$C$1004,$B6,'Cleans Log'!$R$5:$R$1004,$A6,'Cleans Log'!$O$5:$O$1004,">0")) -> 1 | H6: =IF($B6="","",SUMIFS('Cleans Log'!$O$5:$O$1004,'Cleans Log'!$C$5:$C$1004,$B6,'Cleans Log'!$R$5:$R$1004,$A6)) -> 47.5 | I6: =IF($A6="","",$A6+7) -> 46325 | J6: =IF($B6="","",IF($C6<>"","Paid",IF(TODAY()>=$I6,"PAY NOW","Upcoming"))) -> Upcoming
F7: =IF($B7="","",IFERROR(INDEX(Cleaners!$B$5:$B$34,MATCH($B7,Cleaners!$A$5:$A$34,0)),"?")) | G7: =IF($B7="","",COUNTIFS('Cleans Log'!$C$5:$C$1004,$B7,'Cleans Log'!$R$5:$R$1004,$A7,'Cleans Log'!$O$5:$O$1004,">0")) | H7: =IF($B7="","",SUMIFS('Cleans Log'!$O$5:$O$1004,'Cleans Log'!$C$5:$C$1004,$B7,'Cleans Log'!$R$5:$R$1004,$A7)) | I7: =IF($A7="","",$A7+7) | J7: =IF($B7="","",IF($C7<>"","Paid",IF(TODAY()>=$I7,"PAY NOW","Upcoming")))
F8: =IF($B8="","",IFERROR(INDEX(Cleaners!$B$5:$B$34,MATCH($B8,Cleaners!$A$5:$A$34,0)),"?")) | G8: =IF($B8="","",COUNTIFS('Cleans Log'!$C$5:$C$1004,$B8,'Cleans Log'!$R$5:$R$1004,$A8,'Cleans Log'!$O$5:$O$1004,">0")) | H8: =IF($B8="","",SUMIFS('Cleans Log'!$O$5:$O$1004,'Cleans Log'!$C$5:$C$1004,$B8,'Cleans Log'!$R$5:$R$1004,$A8)) | I8: =IF($A8="","",$A8+7) | J8: =IF($B8="","",IF($C8<>"","Paid",IF(TODAY()>=$I8,"PAY NOW","Upcoming")))
F9: =IF($B9="","",IFERROR(INDEX(Cleaners!$B$5:$B$34,MATCH($B9,Cleaners!$A$5:$A$34,0)),"?")) | G9: =IF($B9="","",COUNTIFS('Cleans Log'!$C$5:$C$1004,$B9,'Cleans Log'!$R$5:$R$1004,$A9,'Cleans Log'!$O$5:$O$1004,">0")) | H9: =IF($B9="","",SUMIFS('Cleans Log'!$O$5:$O$1004,'Cleans Log'!$C$5:$C$1004,$B9,'Cleans Log'!$R$5:$R$1004,$A9)) | I9: =IF($A9="","",$A9+7) | J9: =IF($B9="","",IF($C9<>"","Paid",IF(TODAY()>=$I9,"PAY NOW","Upcoming")))
F10: =IF($B10="","",IFERROR(INDEX(Cleaners!$B$5:$B$34,MATCH($B10,Cleaners!$A$5:$A$34,0)),"?")) | G10: =IF($B10="","",COUNTIFS('Cleans Log'!$C$5:$C$1004,$B10,'Cleans Log'!$R$5:$R$1004,$A10,'Cleans Log'!$O$5:$O$1004,">0")) | H10: =IF($B10="","",SUMIFS('Cleans Log'!$O$5:$O$1004,'Cleans Log'!$C$5:$C$1004,$B10,'Cleans Log'!$R$5:$R$1004,$A10)) | I10: =IF($A10="","",$A10+7) | J10: =IF($B10="","",IF($C10<>"","Paid",IF(TODAY()>=$I10,"PAY NOW","Upcoming")))
F11: =IF($B11="","",IFERROR(INDEX(Cleaners!$B$5:$B$34,MATCH($B11,Cleaners!$A$5:$A$34,0)),"?")) | G11: =IF($B11="","",COUNTIFS('Cleans Log'!$C$5:$C$1004,$B11,'Cleans Log'!$R$5:$R$1004,$A11,'Cleans Log'!$O$5:$O$1004,">0")) | H11: =IF($B11="","",SUMIFS('Cleans Log'!$O$5:$O$1004,'Cleans Log'!$C$5:$C$1004,$B11,'Cleans Log'!$R$5:$R$1004,$A11)) | I11: =IF($A11="","",$A11+7) | J11: =IF($B11="","",IF($C11<>"","Paid",IF(TODAY()>=$I11,"PAY NOW","Upcoming")))
F12: =IF($B12="","",IFERROR(INDEX(Cleaners!$B$5:$B$34,MATCH($B12,Cleaners!$A$5:$A$34,0)),"?")) | G12: =IF($B12="","",COUNTIFS('Cleans Log'!$C$5:$C$1004,$B12,'Cleans Log'!$R$5:$R$1004,$A12,'Cleans Log'!$O$5:$O$1004,">0")) | H12: =IF($B12="","",SUMIFS('Cleans Log'!$O$5:$O$1004,'Cleans Log'!$C$5:$C$1004,$B12,'Cleans Log'!$R$5:$R$1004,$A12)) | I12: =IF($A12="","",$A12+7) | J12: =IF($B12="","",IF($C12<>"","Paid",IF(TODAY()>=$I12,"PAY NOW","Upcoming")))
F13: =IF($B13="","",IFERROR(INDEX(Cleaners!$B$5:$B$34,MATCH($B13,Cleaners!$A$5:$A$34,0)),"?")) | G13: =IF($B13="","",COUNTIFS('Cleans Log'!$C$5:$C$1004,$B13,'Cleans Log'!$R$5:$R$1004,$A13,'Cleans Log'!$O$5:$O$1004,">0")) | H13: =IF($B13="","",SUMIFS('Cleans Log'!$O$5:$O$1004,'Cleans Log'!$C$5:$C$1004,$B13,'Cleans Log'!$R$5:$R$1004,$A13)) | I13: =IF($A13="","",$A13+7) | J13: =IF($B13="","",IF($C13<>"","Paid",IF(TODAY()>=$I13,"PAY NOW","Upcoming")))
F14: =IF($B14="","",IFERROR(INDEX(Cleaners!$B$5:$B$34,MATCH($B14,Cleaners!$A$5:$A$34,0)),"?")) | G14: =IF($B14="","",COUNTIFS('Cleans Log'!$C$5:$C$1004,$B14,'Cleans Log'!$R$5:$R$1004,$A14,'Cleans Log'!$O$5:$O$1004,">0")) | H14: =IF($B14="","",SUMIFS('Cleans Log'!$O$5:$O$1004,'Cleans Log'!$C$5:$C$1004,$B14,'Cleans Log'!$R$5:$R$1004,$A14)) | I14: =IF($A14="","",$A14+7) | J14: =IF($B14="","",IF($C14<>"","Paid",IF(TODAY()>=$I14,"PAY NOW","Upcoming")))
F15: =IF($B15="","",IFERROR(INDEX(Cleaners!$B$5:$B$34,MATCH($B15,Cleaners!$A$5:$A$34,0)),"?")) | G15: =IF($B15="","",COUNTIFS('Cleans Log'!$C$5:$C$1004,$B15,'Cleans Log'!$R$5:$R$1004,$A15,'Cleans Log'!$O$5:$O$1004,">0")) | H15: =IF($B15="","",SUMIFS('Cleans Log'!$O$5:$O$1004,'Cleans Log'!$C$5:$C$1004,$B15,'Cleans Log'!$R$5:$R$1004,$A15)) | I15: =IF($A15="","",$A15+7) | J15: =IF($B15="","",IF($C15<>"","Paid",IF(TODAY()>=$I15,"PAY NOW","Upcoming")))
F16: =IF($B16="","",IFERROR(INDEX(Cleaners!$B$5:$B$34,MATCH($B16,Cleaners!$A$5:$A$34,0)),"?")) | G16: =IF($B16="","",COUNTIFS('Cleans Log'!$C$5:$C$1004,$B16,'Cleans Log'!$R$5:$R$1004,$A16,'Cleans Log'!$O$5:$O$1004,">0")) | H16: =IF($B16="","",SUMIFS('Cleans Log'!$O$5:$O$1004,'Cleans Log'!$C$5:$C$1004,$B16,'Cleans Log'!$R$5:$R$1004,$A16)) | I16: =IF($A16="","",$A16+7) | J16: =IF($B16="","",IF($C16<>"","Paid",IF(TODAY()>=$I16,"PAY NOW","Upcoming")))
F17: =IF($B17="","",IFERROR(INDEX(Cleaners!$B$5:$B$34,MATCH($B17,Cleaners!$A$5:$A$34,0)),"?")) | G17: =IF($B17="","",COUNTIFS('Cleans Log'!$C$5:$C$1004,$B17,'Cleans Log'!$R$5:$R$1004,$A17,'Cleans Log'!$O$5:$O$1004,">0")) | H17: =IF($B17="","",SUMIFS('Cleans Log'!$O$5:$O$1004,'Cleans Log'!$C$5:$C$1004,$B17,'Cleans Log'!$R$5:$R$1004,$A17)) | I17: =IF($A17="","",$A17+7) | J17: =IF($B17="","",IF($C17<>"","Paid",IF(TODAY()>=$I17,"PAY NOW","Upcoming")))
F18: =IF($B18="","",IFERROR(INDEX(Cleaners!$B$5:$B$34,MATCH($B18,Cleaners!$A$5:$A$34,0)),"?")) | G18: =IF($B18="","",COUNTIFS('Cleans Log'!$C$5:$C$1004,$B18,'Cleans Log'!$R$5:$R$1004,$A18,'Cleans Log'!$O$5:$O$1004,">0")) | H18: =IF($B18="","",SUMIFS('Cleans Log'!$O$5:$O$1004,'Cleans Log'!$C$5:$C$1004,$B18,'Cleans Log'!$R$5:$R$1004,$A18)) | I18: =IF($A18="","",$A18+7) | J18: =IF($B18="","",IF($C18<>"","Paid",IF(TODAY()>=$I18,"PAY NOW","Upcoming")))
... F504: =IF($B504="","",IFERROR(INDEX(Cleaners!$B$5:$B$34,MATCH($B504,Cleaners!$A$5:$A$34,0)),"?")) | G504: =IF($B504="","",COUNTIFS('Cleans Log'!$C$5:$C$1004,$B504,'Cleans Log'!$R$5:$R$1004,$A504,'Cleans Log'!$O$5:$O$1004,">0")) | H504: =IF($B504="","",SUMIFS('Cleans Log'!$O$5:$O$1004,'Cleans Log'!$C$5:$C$1004,$B504,'Cleans Log'!$R$5:$R$1004,$A504)) | I504: =IF($A504="","",$A504+7) | J504: =IF($B504="","",IF($C504<>"","Paid",IF(TODAY()>=$I504,"PAY NOW","Upcoming")))

Sheet Expenses
A1: Running Costs
A2: Your own business costs (not things recharged to hosts). Keep receipts for 5 years after the tax return deadline.
A4: Date | B4: Type | C4: What | D4: Amount (£) | E4: Business miles (mileage only) | F4: Receipt (Y/N) | G4: Claimable (£) | H4: Tax year | I4: Month
A5: 46297 | B5: Insurance | C5: Public liability, monthly (EXAMPLE) | D5: 8 | F5: Y | G5: =IF($A5="","",IF($B5="Mileage",N($E5)*Settings!$B$13,N($D5))) -> 8 | H5: =IF($A5="","",IF($A5>=DATE(YEAR($A5),4,6),YEAR($A5)&"/"&RIGHT(YEAR($A5)+1,2),YEAR($A5)-1&"/"&RIGHT(YEAR($A5),2))) -> 2026/27 | I5: =IF($A5="","",DATE(YEAR($A5),MONTH($A5),1)) -> 46296
A6: 46298 | B6: Mileage | C6: Home to property and back (EXAMPLE) | E6: 12 | F6: N | G6: =IF($A6="","",IF($B6="Mileage",N($E6)*Settings!$B$13,N($D6))) -> 5.4 | H6: =IF($A6="","",IF($A6>=DATE(YEAR($A6),4,6),YEAR($A6)&"/"&RIGHT(YEAR($A6)+1,2),YEAR($A6)-1&"/"&RIGHT(YEAR($A6),2))) -> 2026/27 | I6: =IF($A6="","",DATE(YEAR($A6),MONTH($A6),1)) -> 46296
G7: =IF($A7="","",IF($B7="Mileage",N($E7)*Settings!$B$13,N($D7))) | H7: =IF($A7="","",IF($A7>=DATE(YEAR($A7),4,6),YEAR($A7)&"/"&RIGHT(YEAR($A7)+1,2),YEAR($A7)-1&"/"&RIGHT(YEAR($A7),2))) | I7: =IF($A7="","",DATE(YEAR($A7),MONTH($A7),1))
G8: =IF($A8="","",IF($B8="Mileage",N($E8)*Settings!$B$13,N($D8))) | H8: =IF($A8="","",IF($A8>=DATE(YEAR($A8),4,6),YEAR($A8)&"/"&RIGHT(YEAR($A8)+1,2),YEAR($A8)-1&"/"&RIGHT(YEAR($A8),2))) | I8: =IF($A8="","",DATE(YEAR($A8),MONTH($A8),1))
G9: =IF($A9="","",IF($B9="Mileage",N($E9)*Settings!$B$13,N($D9))) | H9: =IF($A9="","",IF($A9>=DATE(YEAR($A9),4,6),YEAR($A9)&"/"&RIGHT(YEAR($A9)+1,2),YEAR($A9)-1&"/"&RIGHT(YEAR($A9),2))) | I9: =IF($A9="","",DATE(YEAR($A9),MONTH($A9),1))
G10: =IF($A10="","",IF($B10="Mileage",N($E10)*Settings!$B$13,N($D10))) | H10: =IF($A10="","",IF($A10>=DATE(YEAR($A10),4,6),YEAR($A10)&"/"&RIGHT(YEAR($A10)+1,2),YEAR($A10)-1&"/"&RIGHT(YEAR($A10),2))) | I10: =IF($A10="","",DATE(YEAR($A10),MONTH($A10),1))
G11: =IF($A11="","",IF($B11="Mileage",N($E11)*Settings!$B$13,N($D11))) | H11: =IF($A11="","",IF($A11>=DATE(YEAR($A11),4,6),YEAR($A11)&"/"&RIGHT(YEAR($A11)+1,2),YEAR($A11)-1&"/"&RIGHT(YEAR($A11),2))) | I11: =IF($A11="","",DATE(YEAR($A11),MONTH($A11),1))
G12: =IF($A12="","",IF($B12="Mileage",N($E12)*Settings!$B$13,N($D12))) | H12: =IF($A12="","",IF($A12>=DATE(YEAR($A12),4,6),YEAR($A12)&"/"&RIGHT(YEAR($A12)+1,2),YEAR($A12)-1&"/"&RIGHT(YEAR($A12),2))) | I12: =IF($A12="","",DATE(YEAR($A12),MONTH($A12),1))
G13: =IF($A13="","",IF($B13="Mileage",N($E13)*Settings!$B$13,N($D13))) | H13: =IF($A13="","",IF($A13>=DATE(YEAR($A13),4,6),YEAR($A13)&"/"&RIGHT(YEAR($A13)+1,2),YEAR($A13)-1&"/"&RIGHT(YEAR($A13),2))) | I13: =IF($A13="","",DATE(YEAR($A13),MONTH($A13),1))
G14: =IF($A14="","",IF($B14="Mileage",N($E14)*Settings!$B$13,N($D14))) | H14: =IF($A14="","",IF($A14>=DATE(YEAR($A14),4,6),YEAR($A14)&"/"&RIGHT(YEAR($A14)+1,2),YEAR($A14)-1&"/"&RIGHT(YEAR($A14),2))) | I14: =IF($A14="","",DATE(YEAR($A14),MONTH($A14),1))
G15: =IF($A15="","",IF($B15="Mileage",N($E15)*Settings!$B$13,N($D15))) | H15: =IF($A15="","",IF($A15>=DATE(YEAR($A15),4,6),YEAR($A15)&"/"&RIGHT(YEAR($A15)+1,2),YEAR($A15)-1&"/"&RIGHT(YEAR($A15),2))) | I15: =IF($A15="","",DATE(YEAR($A15),MONTH($A15),1))
G16: =IF($A16="","",IF($B16="Mileage",N($E16)*Settings!$B$13,N($D16))) | H16: =IF($A16="","",IF($A16>=DATE(YEAR($A16),4,6),YEAR($A16)&"/"&RIGHT(YEAR($A16)+1,2),YEAR($A16)-1&"/"&RIGHT(YEAR($A16),2))) | I16: =IF($A16="","",DATE(YEAR($A16),MONTH($A16),1))
G17: =IF($A17="","",IF($B17="Mileage",N($E17)*Settings!$B$13,N($D17))) | H17: =IF($A17="","",IF($A17>=DATE(YEAR($A17),4,6),YEAR($A17)&"/"&RIGHT(YEAR($A17)+1,2),YEAR($A17)-1&"/"&RIGHT(YEAR($A17),2))) | I17: =IF($A17="","",DATE(YEAR($A17),MONTH($A17),1))
G18: =IF($A18="","",IF($B18="Mileage",N($E18)*Settings!$B$13,N($D18))) | H18: =IF($A18="","",IF($A18>=DATE(YEAR($A18),4,6),YEAR($A18)&"/"&RIGHT(YEAR($A18)+1,2),YEAR($A18)-1&"/"&RIGHT(YEAR($A18),2))) | I18: =IF($A18="","",DATE(YEAR($A18),MONTH($A18),1))
... G504: =IF($A504="","",IF($B504="Mileage",N($E504)*Settings!$B$13,N($D504))) | H504: =IF($A504="","",IF($A504>=DATE(YEAR($A504),4,6),YEAR($A504)&"/"&RIGHT(YEAR($A504)+1,2),YEAR($A504)-1&"/"&RIGHT(YEAR($A504),2))) | I504: =IF($A504="","",DATE(YEAR($A504),MONTH($A504),1))

Sheet Properties
A1: Properties
A2: Price and cleaner pay fill in from Settings. Type an agreed price to override. Never store door codes here.
A4: Prop ID | B4: Property name | C4: Postcode | D4: Host ID | E4: Bedrooms (0 = studio) | F4: Bathrooms | G4: Standard price (£) | H4: Agreed price (£, optional) | I4: Price per clean (£) | J4: Standard cleaner pay (£) | K4: Agreed cleaner pay (£, optional) | L4: Cleaner pay per clean (£) | M4: You keep per clean (£) | N4: Main cleaner | O4: Backup cleaner | P4: Linen | Q4: Supplies | R4: Washer on site (Y/N) | S4: Checkout | T4: Check-in | U4: Access (method only, no codes) | V4: Parking | W4: Active (Y/N) | X4: Start date | Y4: Notes
A5: P001 | B5: First client (EXAMPLE) | C5: BA1 | D5: H001 | E5: 2 | F5: 1 | G5: =IF($A5="","",INDEX(Settings!$C$22:$C$26,MATCH(MIN($E5,4),Settings!$A$22:$A$26,0))+MAX(0,$F5-1)*Settings!$B$6+IF($P5="FreshTurn",INDEX(Settings!$D$22:$D$26,MATCH(MIN($E5,4),Settings!$A$22:$A$26,0)),0)) -> 60 | I5: =IF($A5="","",IF($H5<>"",$H5,$G5)) -> 60 | J5: =IF($A5="","",INDEX(Settings!$F$22:$F$26,MATCH(MIN($E5,4),Settings!$A$22:$A$26,0))+MAX(0,$F5-1)*Settings!$B$6*Settings!$B$9) -> 40 | L5: =IF($A5="","",IF($K5<>"",$K5,$J5)) -> 40 | M5: =IF($A5="","",$I5-$L5) -> 20 | N5: C001 | O5: C002 | P5: Host's own | Q5: Host stock | R5: Y | S5: 0.45833333 | T5: 0.66666667 | U5: Key safe (code in password manager) | V5: Permit needed: check with host | W5: Y | X5: 46296 | Y5: EXAMPLE: replace with the real property
G6: =IF($A6="","",INDEX(Settings!$C$22:$C$26,MATCH(MIN($E6,4),Settings!$A$22:$A$26,0))+MAX(0,$F6-1)*Settings!$B$6+IF($P6="FreshTurn",INDEX(Settings!$D$22:$D$26,MATCH(MIN($E6,4),Settings!$A$22:$A$26,0)),0)) | I6: =IF($A6="","",IF($H6<>"",$H6,$G6)) | J6: =IF($A6="","",INDEX(Settings!$F$22:$F$26,MATCH(MIN($E6,4),Settings!$A$22:$A$26,0))+MAX(0,$F6-1)*Settings!$B$6*Settings!$B$9) | L6: =IF($A6="","",IF($K6<>"",$K6,$J6)) | M6: =IF($A6="","",$I6-$L6)
G7: =IF($A7="","",INDEX(Settings!$C$22:$C$26,MATCH(MIN($E7,4),Settings!$A$22:$A$26,0))+MAX(0,$F7-1)*Settings!$B$6+IF($P7="FreshTurn",INDEX(Settings!$D$22:$D$26,MATCH(MIN($E7,4),Settings!$A$22:$A$26,0)),0)) | I7: =IF($A7="","",IF($H7<>"",$H7,$G7)) | J7: =IF($A7="","",INDEX(Settings!$F$22:$F$26,MATCH(MIN($E7,4),Settings!$A$22:$A$26,0))+MAX(0,$F7-1)*Settings!$B$6*Settings!$B$9) | L7: =IF($A7="","",IF($K7<>"",$K7,$J7)) | M7: =IF($A7="","",$I7-$L7)
G8: =IF($A8="","",INDEX(Settings!$C$22:$C$26,MATCH(MIN($E8,4),Settings!$A$22:$A$26,0))+MAX(0,$F8-1)*Settings!$B$6+IF($P8="FreshTurn",INDEX(Settings!$D$22:$D$26,MATCH(MIN($E8,4),Settings!$A$22:$A$26,0)),0)) | I8: =IF($A8="","",IF($H8<>"",$H8,$G8)) | J8: =IF($A8="","",INDEX(Settings!$F$22:$F$26,MATCH(MIN($E8,4),Settings!$A$22:$A$26,0))+MAX(0,$F8-1)*Settings!$B$6*Settings!$B$9) | L8: =IF($A8="","",IF($K8<>"",$K8,$J8)) | M8: =IF($A8="","",$I8-$L8)
G9: =IF($A9="","",INDEX(Settings!$C$22:$C$26,MATCH(MIN($E9,4),Settings!$A$22:$A$26,0))+MAX(0,$F9-1)*Settings!$B$6+IF($P9="FreshTurn",INDEX(Settings!$D$22:$D$26,MATCH(MIN($E9,4),Settings!$A$22:$A$26,0)),0)) | I9: =IF($A9="","",IF($H9<>"",$H9,$G9)) | J9: =IF($A9="","",INDEX(Settings!$F$22:$F$26,MATCH(MIN($E9,4),Settings!$A$22:$A$26,0))+MAX(0,$F9-1)*Settings!$B$6*Settings!$B$9) | L9: =IF($A9="","",IF($K9<>"",$K9,$J9)) | M9: =IF($A9="","",$I9-$L9)
G10: =IF($A10="","",INDEX(Settings!$C$22:$C$26,MATCH(MIN($E10,4),Settings!$A$22:$A$26,0))+MAX(0,$F10-1)*Settings!$B$6+IF($P10="FreshTurn",INDEX(Settings!$D$22:$D$26,MATCH(MIN($E10,4),Settings!$A$22:$A$26,0)),0)) | I10: =IF($A10="","",IF($H10<>"",$H10,$G10)) | J10: =IF($A10="","",INDEX(Settings!$F$22:$F$26,MATCH(MIN($E10,4),Settings!$A$22:$A$26,0))+MAX(0,$F10-1)*Settings!$B$6*Settings!$B$9) | L10: =IF($A10="","",IF($K10<>"",$K10,$J10)) | M10: =IF($A10="","",$I10-$L10)
G11: =IF($A11="","",INDEX(Settings!$C$22:$C$26,MATCH(MIN($E11,4),Settings!$A$22:$A$26,0))+MAX(0,$F11-1)*Settings!$B$6+IF($P11="FreshTurn",INDEX(Settings!$D$22:$D$26,MATCH(MIN($E11,4),Settings!$A$22:$A$26,0)),0)) | I11: =IF($A11="","",IF($H11<>"",$H11,$G11)) | J11: =IF($A11="","",INDEX(Settings!$F$22:$F$26,MATCH(MIN($E11,4),Settings!$A$22:$A$26,0))+MAX(0,$F11-1)*Settings!$B$6*Settings!$B$9) | L11: =IF($A11="","",IF($K11<>"",$K11,$J11)) | M11: =IF($A11="","",$I11-$L11)
G12: =IF($A12="","",INDEX(Settings!$C$22:$C$26,MATCH(MIN($E12,4),Settings!$A$22:$A$26,0))+MAX(0,$F12-1)*Settings!$B$6+IF($P12="FreshTurn",INDEX(Settings!$D$22:$D$26,MATCH(MIN($E12,4),Settings!$A$22:$A$26,0)),0)) | I12: =IF($A12="","",IF($H12<>"",$H12,$G12)) | J12: =IF($A12="","",INDEX(Settings!$F$22:$F$26,MATCH(MIN($E12,4),Settings!$A$22:$A$26,0))+MAX(0,$F12-1)*Settings!$B$6*Settings!$B$9) | L12: =IF($A12="","",IF($K12<>"",$K12,$J12)) | M12: =IF($A12="","",$I12-$L12)
G13: =IF($A13="","",INDEX(Settings!$C$22:$C$26,MATCH(MIN($E13,4),Settings!$A$22:$A$26,0))+MAX(0,$F13-1)*Settings!$B$6+IF($P13="FreshTurn",INDEX(Settings!$D$22:$D$26,MATCH(MIN($E13,4),Settings!$A$22:$A$26,0)),0)) | I13: =IF($A13="","",IF($H13<>"",$H13,$G13)) | J13: =IF($A13="","",INDEX(Settings!$F$22:$F$26,MATCH(MIN($E13,4),Settings!$A$22:$A$26,0))+MAX(0,$F13-1)*Settings!$B$6*Settings!$B$9) | L13: =IF($A13="","",IF($K13<>"",$K13,$J13)) | M13: =IF($A13="","",$I13-$L13)
G14: =IF($A14="","",INDEX(Settings!$C$22:$C$26,MATCH(MIN($E14,4),Settings!$A$22:$A$26,0))+MAX(0,$F14-1)*Settings!$B$6+IF($P14="FreshTurn",INDEX(Settings!$D$22:$D$26,MATCH(MIN($E14,4),Settings!$A$22:$A$26,0)),0)) | I14: =IF($A14="","",IF($H14<>"",$H14,$G14)) | J14: =IF($A14="","",INDEX(Settings!$F$22:$F$26,MATCH(MIN($E14,4),Settings!$A$22:$A$26,0))+MAX(0,$F14-1)*Settings!$B$6*Settings!$B$9) | L14: =IF($A14="","",IF($K14<>"",$K14,$J14)) | M14: =IF($A14="","",$I14-$L14)
G15: =IF($A15="","",INDEX(Settings!$C$22:$C$26,MATCH(MIN($E15,4),Settings!$A$22:$A$26,0))+MAX(0,$F15-1)*Settings!$B$6+IF($P15="FreshTurn",INDEX(Settings!$D$22:$D$26,MATCH(MIN($E15,4),Settings!$A$22:$A$26,0)),0)) | I15: =IF($A15="","",IF($H15<>"",$H15,$G15)) | J15: =IF($A15="","",INDEX(Settings!$F$22:$F$26,MATCH(MIN($E15,4),Settings!$A$22:$A$26,0))+MAX(0,$F15-1)*Settings!$B$6*Settings!$B$9) | L15: =IF($A15="","",IF($K15<>"",$K15,$J15)) | M15: =IF($A15="","",$I15-$L15)
G16: =IF($A16="","",INDEX(Settings!$C$22:$C$26,MATCH(MIN($E16,4),Settings!$A$22:$A$26,0))+MAX(0,$F16-1)*Settings!$B$6+IF($P16="FreshTurn",INDEX(Settings!$D$22:$D$26,MATCH(MIN($E16,4),Settings!$A$22:$A$26,0)),0)) | I16: =IF($A16="","",IF($H16<>"",$H16,$G16)) | J16: =IF($A16="","",INDEX(Settings!$F$22:$F$26,MATCH(MIN($E16,4),Settings!$A$22:$A$26,0))+MAX(0,$F16-1)*Settings!$B$6*Settings!$B$9) | L16: =IF($A16="","",IF($K16<>"",$K16,$J16)) | M16: =IF($A16="","",$I16-$L16)
G17: =IF($A17="","",INDEX(Settings!$C$22:$C$26,MATCH(MIN($E17,4),Settings!$A$22:$A$26,0))+MAX(0,$F17-1)*Settings!$B$6+IF($P17="FreshTurn",INDEX(Settings!$D$22:$D$26,MATCH(MIN($E17,4),Settings!$A$22:$A$26,0)),0)) | I17: =IF($A17="","",IF($H17<>"",$H17,$G17)) | J17: =IF($A17="","",INDEX(Settings!$F$22:$F$26,MATCH(MIN($E17,4),Settings!$A$22:$A$26,0))+MAX(0,$F17-1)*Settings!$B$6*Settings!$B$9) | L17: =IF($A17="","",IF($K17<>"",$K17,$J17)) | M17: =IF($A17="","",$I17-$L17)
... G104: =IF($A104="","",INDEX(Settings!$C$22:$C$26,MATCH(MIN($E104,4),Settings!$A$22:$A$26,0))+MAX(0,$F104-1)*Settings!$B$6+IF($P104="FreshTurn",INDEX(Settings!$D$22:$D$26,MATCH(MIN($E104,4),Settings!$A$22:$A$26,0)),0)) | I104: =IF($A104="","",IF($H104<>"",$H104,$G104)) | J104: =IF($A104="","",INDEX(Settings!$F$22:$F$26,MATCH(MIN($E104,4),Settings!$A$22:$A$26,0))+MAX(0,$F104-1)*Settings!$B$6*Settings!$B$9) | L104: =IF($A104="","",IF($K104<>"",$K104,$J104)) | M104: =IF($A104="","",$I104-$L104)

Sheet Hosts
A1: Hosts
A2: One row per client. Keep this list private (UK GDPR).
A4: Host ID | B4: Name | C4: Phone | D4: Email | E4: Prefers (text / email / call) | F4: Pays by | G4: Card on file (Y/N) | H4: Agreement signed (date) | I4: Properties | J4: Notes
A5: H001 | B5: First client | E5: Text | F5: Bank transfer | G5: N | I5: =IF($A5="","",COUNTIF(Properties!$D$5:$D$104,$A5)) -> 1 | J5: EXAMPLE: replace with your first client's details
I6: =IF($A6="","",COUNTIF(Properties!$D$5:$D$104,$A6))
I7: =IF($A7="","",COUNTIF(Properties!$D$5:$D$104,$A7))
I8: =IF($A8="","",COUNTIF(Properties!$D$5:$D$104,$A8))
I9: =IF($A9="","",COUNTIF(Properties!$D$5:$D$104,$A9))
I10: =IF($A10="","",COUNTIF(Properties!$D$5:$D$104,$A10))
I11: =IF($A11="","",COUNTIF(Properties!$D$5:$D$104,$A11))
I12: =IF($A12="","",COUNTIF(Properties!$D$5:$D$104,$A12))
I13: =IF($A13="","",COUNTIF(Properties!$D$5:$D$104,$A13))
I14: =IF($A14="","",COUNTIF(Properties!$D$5:$D$104,$A14))
I15: =IF($A15="","",COUNTIF(Properties!$D$5:$D$104,$A15))
I16: =IF($A16="","",COUNTIF(Properties!$D$5:$D$104,$A16))
I17: =IF($A17="","",COUNTIF(Properties!$D$5:$D$104,$A17))
... I54: =IF($A54="","",COUNTIF(Properties!$D$5:$D$104,$A54))

Sheet Cleaners
A1: Cleaners
A2: Self-employed cleaners. Keep bank details in your banking app, not here.
A4: Cleaner ID | B4: Name | C4: Phone | D4: Registered self-employed with HMRC (Y/N) | E4: Agreement signed (date) | F4: Own insurance (Y/N) | G4: Days available | H4: Properties they know | I4: Jobs done | J4: Earned to date (£) | K4: Notes
A5: C001 | B5: Cleaner 1 | G5: Fri–Sun | H5: P001 | I5: =IF($A5="","",COUNTIFS('Cleans Log'!$C$5:$C$1004,$A5,'Cleans Log'!$O$5:$O$1004,">0")) -> 3 | J5: =IF($A5="","",SUMIFS('Cleans Log'!$O$5:$O$1004,'Cleans Log'!$C$5:$C$1004,$A5)) -> 100 | K5: EXAMPLE
A6: C002 | B6: Cleaner 2 | G6: Fri–Sun | H6: P001 | I6: =IF($A6="","",COUNTIFS('Cleans Log'!$C$5:$C$1004,$A6,'Cleans Log'!$O$5:$O$1004,">0")) -> 1 | J6: =IF($A6="","",SUMIFS('Cleans Log'!$O$5:$O$1004,'Cleans Log'!$C$5:$C$1004,$A6)) -> 47.5 | K6: EXAMPLE
I7: =IF($A7="","",COUNTIFS('Cleans Log'!$C$5:$C$1004,$A7,'Cleans Log'!$O$5:$O$1004,">0")) | J7: =IF($A7="","",SUMIFS('Cleans Log'!$O$5:$O$1004,'Cleans Log'!$C$5:$C$1004,$A7))
I8: =IF($A8="","",COUNTIFS('Cleans Log'!$C$5:$C$1004,$A8,'Cleans Log'!$O$5:$O$1004,">0")) | J8: =IF($A8="","",SUMIFS('Cleans Log'!$O$5:$O$1004,'Cleans Log'!$C$5:$C$1004,$A8))
I9: =IF($A9="","",COUNTIFS('Cleans Log'!$C$5:$C$1004,$A9,'Cleans Log'!$O$5:$O$1004,">0")) | J9: =IF($A9="","",SUMIFS('Cleans Log'!$O$5:$O$1004,'Cleans Log'!$C$5:$C$1004,$A9))
I10: =IF($A10="","",COUNTIFS('Cleans Log'!$C$5:$C$1004,$A10,'Cleans Log'!$O$5:$O$1004,">0")) | J10: =IF($A10="","",SUMIFS('Cleans Log'!$O$5:$O$1004,'Cleans Log'!$C$5:$C$1004,$A10))
I11: =IF($A11="","",COUNTIFS('Cleans Log'!$C$5:$C$1004,$A11,'Cleans Log'!$O$5:$O$1004,">0")) | J11: =IF($A11="","",SUMIFS('Cleans Log'!$O$5:$O$1004,'Cleans Log'!$C$5:$C$1004,$A11))
I12: =IF($A12="","",COUNTIFS('Cleans Log'!$C$5:$C$1004,$A12,'Cleans Log'!$O$5:$O$1004,">0")) | J12: =IF($A12="","",SUMIFS('Cleans Log'!$O$5:$O$1004,'Cleans Log'!$C$5:$C$1004,$A12))
I13: =IF($A13="","",COUNTIFS('Cleans Log'!$C$5:$C$1004,$A13,'Cleans Log'!$O$5:$O$1004,">0")) | J13: =IF($A13="","",SUMIFS('Cleans Log'!$O$5:$O$1004,'Cleans Log'!$C$5:$C$1004,$A13))
I14: =IF($A14="","",COUNTIFS('Cleans Log'!$C$5:$C$1004,$A14,'Cleans Log'!$O$5:$O$1004,">0")) | J14: =IF($A14="","",SUMIFS('Cleans Log'!$O$5:$O$1004,'Cleans Log'!$C$5:$C$1004,$A14))
I15: =IF($A15="","",COUNTIFS('Cleans Log'!$C$5:$C$1004,$A15,'Cleans Log'!$O$5:$O$1004,">0")) | J15: =IF($A15="","",SUMIFS('Cleans Log'!$O$5:$O$1004,'Cleans Log'!$C$5:$C$1004,$A15))
I16: =IF($A16="","",COUNTIFS('Cleans Log'!$C$5:$C$1004,$A16,'Cleans Log'!$O$5:$O$1004,">0")) | J16: =IF($A16="","",SUMIFS('Cleans Log'!$O$5:$O$1004,'Cleans Log'!$C$5:$C$1004,$A16))
I17: =IF($A17="","",COUNTIFS('Cleans Log'!$C$5:$C$1004,$A17,'Cleans Log'!$O$5:$O$1004,">0")) | J17: =IF($A17="","",SUMIFS('Cleans Log'!$O$5:$O$1004,'Cleans Log'!$C$5:$C$1004,$A17))
I18: =IF($A18="","",COUNTIFS('Cleans Log'!$C$5:$C$1004,$A18,'Cleans Log'!$O$5:$O$1004,">0")) | J18: =IF($A18="","",SUMIFS('Cleans Log'!$O$5:$O$1004,'Cleans Log'!$C$5:$C$1004,$A18))
... I34: =IF($A34="","",COUNTIFS('Cleans Log'!$C$5:$C$1004,$A34,'Cleans Log'!$O$5:$O$1004,">0")) | J34: =IF($A34="","",SUMIFS('Cleans Log'!$O$5:$O$1004,'Cleans Log'!$C$5:$C$1004,$A34))

Sheet Supplies
A1: Supplies Catalogue
A2: What things cost. Prices are October 2026 estimates unless a source is given: update them from your receipts.
A4: Item ID | B4: Item | C4: Category | D4: Pack size (units) | E4: Pack price (£) | F4: Cost per unit (£) | G4: Recharge to host? | H4: Where to buy | I4: Price source
A5: S01 | B5: Toilet roll | C5: Bathroom | D5: 36 | E5: 18.9 | F5: =IF(OR($A5="",N($D5)=0),"",$E5/$D5) -> 0.525 | G5: Y | H5: Diamond DCS (trade), Costco, Booker | I5: Diamond DCS listing, Oct 2026 (£18.90 inc VAT for 36)
A6: S02 | B6: Kitchen roll | C6: Kitchen | D6: 12 | E6: 12 | F6: =IF(OR($A6="",N($D6)=0),"",$E6/$D6) -> 1 | G6: Y | H6: Costco, Booker, supermarket multipack | I6: Estimate
A7: S03 | B7: Hand soap (500ml pump) | C7: Bathroom | D7: 6 | E7: 9 | F7: =IF(OR($A7="",N($D7)=0),"",$E7/$D7) -> 1.5 | G7: Y | H7: Amazon, Costco | I7: Estimate
A8: S04 | B8: Mini shampoo | C8: Bathroom | D8: 50 | E8: 12 | F8: =IF(OR($A8="",N($D8)=0),"",$E8/$D8) -> 0.24 | G8: Y | H8: Hotel supply sites, Amazon | I8: Estimate
A9: S05 | B9: Mini conditioner | C9: Bathroom | D9: 50 | E9: 12 | F9: =IF(OR($A9="",N($D9)=0),"",$E9/$D9) -> 0.24 | G9: Y | H9: Hotel supply sites, Amazon | I9: Estimate
A10: S06 | B10: Mini shower gel | C10: Bathroom | D10: 50 | E10: 12 | F10: =IF(OR($A10="",N($D10)=0),"",$E10/$D10) -> 0.24 | G10: Y | H10: Hotel supply sites, Amazon | I10: Estimate
A11: S07 | B11: Dishwasher tablets | C11: Kitchen | D11: 100 | E11: 15 | F11: =IF(OR($A11="",N($D11)=0),"",$E11/$D11) -> 0.15 | G11: Y | H11: Costco, Aldi, Lidl | I11: Estimate
A12: S08 | B12: Washing-up liquid | C12: Kitchen | D12: 6 | E12: 6 | F12: =IF(OR($A12="",N($D12)=0),"",$E12/$D12) -> 1 | G12: Y | H12: Supermarket, Booker | I12: Estimate
A13: S09 | B13: Sponge scourers | C13: Kitchen | D13: 10 | E13: 3 | F13: =IF(OR($A13="",N($D13)=0),"",$E13/$D13) -> 0.3 | G13: Y | H13: Supermarket | I13: Estimate
A14: S10 | B14: Bin bags (kitchen) | C14: Kitchen | D14: 100 | E14: 8 | F14: =IF(OR($A14="",N($D14)=0),"",$E14/$D14) -> 0.08 | G14: Y | H14: Supermarket, Booker | I14: Estimate
A15: S11 | B15: Tea bags | C15: Welcome | D15: 240 | E15: 6 | F15: =IF(OR($A15="",N($D15)=0),"",$E15/$D15) -> 0.025 | G15: Y | H15: Supermarket, Costco | I15: Estimate
A16: S12 | B16: Coffee sachets / pods | C16: Welcome | D16: 100 | E16: 15 | F16: =IF(OR($A16="",N($D16)=0),"",$E16/$D16) -> 0.15 | G16: Y | H16: Costco, Amazon | I16: Estimate
... A33: S29 | B33: Double duvet cover set (white) | C33: Replacement | D33: 1 | E33: 20 | F33: =IF(OR($A33="",N($D33)=0),"",$E33/$D33) -> 20 | G33: Y | H33: Dunelm, Vision Linens | I33: Estimate
F34: =IF(OR($A34="",N($D34)=0),"",$E34/$D34)
F35: =IF(OR($A35="",N($D35)=0),"",$E35/$D35)
F36: =IF(OR($A36="",N($D36)=0),"",$E36/$D36)
F37: =IF(OR($A37="",N($D37)=0),"",$E37/$D37)
F38: =IF(OR($A38="",N($D38)=0),"",$E38/$D38)
F39: =IF(OR($A39="",N($D39)=0),"",$E39/$D39)
F40: =IF(OR($A40="",N($D40)=0),"",$E40/$D40)
F41: =IF(OR($A41="",N($D41)=0),"",$E41/$D41)
F42: =IF(OR($A42="",N($D42)=0),"",$E42/$D42)
F43: =IF(OR($A43="",N($D43)=0),"",$E43/$D43)
F44: =IF(OR($A44="",N($D44)=0),"",$E44/$D44)
F45: =IF(OR($A45="",N($D45)=0),"",$E45/$D45)
... F104: =IF(OR($A104="",N($D104)=0),"",$E104/$D104)

Sheet Price Calculator
A1: Price Calculator
A2: Price a new property from how long it takes. Time the first 4 cleans and come back to check.
B4: Bedrooms (0 = studio) | C4: 2
B5: Bathrooms | C5: 1
B6: Hours one cleaner needs | C6: 2.5
B7: Parking cost per visit (£) | C7: 0
B8: FreshTurn supplies linen? (Y/N) | C8: N
B10: Suggested price (rounded up to £5) | C10: =CEILING($C$6*Settings!$B$17+$C$7,5)+IF($C$8="Y",INDEX(Settings!$D$22:$D$26,MATCH(MIN($C$4,4),Settings!$A$22:$A$26,0)),0) -> 60 | D10: Hours × target hourly charge + parking, plus linen if you supply it.
B11: Price from your standard price list | C11: =INDEX(Settings!$C$22:$C$26,MATCH(MIN($C$4,4),Settings!$A$22:$A$26,0))+MAX(0,$C$5-1)*Settings!$B$6+IF($C$8="Y",INDEX(Settings!$D$22:$D$26,MATCH(MIN($C$4,4),Settings!$A$22:$A$26,0)),0) -> 60 | D11: What the website says for this size.
B12: Cleaner pay (hours × cleaner rate, rounded) | C12: =ROUND($C$6*Settings!$B$18,0) -> 40 | D12: Compare with the standard pay in Settings.
B13: You keep per clean (at suggested price) | C13: =$C$10-$C$12-$C$7-IF($C$8="Y",INDEX(Settings!$D$22:$D$26,MATCH(MIN($C$4,4),Settings!$A$22:$A$26,0))*0.5,0) -> 20 | D13: Assumes linen laundering costs about half the linen fee.
B14: You keep as % of price | C14: =IFERROR($C$13/$C$10,0) -> 0.33333333 | D14: Aim for 25% or more.
B15: Cleaner's effective hourly rate | C15: =IFERROR($C$12/$C$6,0) -> 16 | D15: Should be at or above what they earn elsewhere.

Sheet Settings
A1: Settings
A2: Change a number here and every tab updates. Values researched for Bath, October 2026: check them against real quotes.
A3: Markup on purchases recharged to hosts | B3: 0.1 | C3: From the client agreement (cost + 10%).
A4: Replace without asking, up to (£ per item) | B4: 20 | C4: Client agreement 4.2. Above this, get the host's OK first.
A5: Host pays up front above (£) | B5: 50 | C5: Client agreement 4.5.
A6: Extra bathroom (£ per clean) | B6: 10 | C6: Website price list.
A7: Hot tub check (£) | B7: 15 | C7: Website price list.
A8: Rush surcharge (under 4 hrs notice) | B8: 0.25 | C8: Website price list.
A9: Cleaner share of extras / surcharges | B9: 0.5 | C9: Cleaner agreement 3.1.
A10: Late cancellation charge to host | B10: 0.5 | C10: Client agreement 5.3 (under 24 hrs notice).
A11: Cleaner pay on late cancellation | B11: 0.5 | C11: Your choice: half pay if they'd already set off.
A12: Invoice payment terms (days) | B12: 7 | C12: Client agreement 5.1.
A13: Mileage rate (£ per mile) | B13: 0.45 | C13: HMRC approved rate for cars, first 10,000 business miles a year.
A14: Tax set-aside (% of profit) | B14: 0.25 | C14: Rough guide for Income Tax + National Insurance. Ask an accountant for your real rate.
... A19: Cleaner share of deep cleans | B19: 0.6 | C19: Cleaner agreement 3.1.
A21: Bedrooms | B21: Label | C21: Clean price (£) | D21: Linen add-on (£) | E21: Deep clean (£) | F21: Cleaner pay (£) | H21: Clean status | I21: Y/N | J21: Purchase type | K21: Claim status | L21: Expense type | M21: Linen | N21: Supplies | O21: Platform
A22: 0 | B22: Studio | C22: 45 | D22: 12 | E22: 140 | F22: 30 | H22: Completed | I22: Y | J22: Restock | K22: Not started | L22: Insurance | M22: Host's own | N22: Host stock | O22: Airbnb
A23: 1 | B23: 1 bed | C23: 50 | D23: 14 | E23: 170 | F23: 33 | H23: Deep clean | I23: N | J23: Replacement | K23: Claimed | L23: Software | M23: FreshTurn | N23: FreshTurn buys | O23: Booking.com
A24: 2 | B24: 2 bed | C24: 60 | D24: 26 | E24: 210 | F24: 40 | H24: Late cancel | J24: Guest damage | K24: Paid | L24: Phone | O24: Vrbo
A25: 3 | B25: 3 bed | C25: 80 | D25: 38 | E25: 260 | F25: 52 | H25: Cancelled | J25: Our supplies | K25: Refused | L25: Marketing | O25: Direct
A26: 4 | B26: 4+ bed | C26: 100 | D26: 50 | E26: 320 | F26: 65 | H26: Re-clean | J26: Equipment | K26: Not claiming | L26: Mileage | O26: Other
L27: Parking
A28: Prices: UK hosts typically pay £40–£70 for a 2-bed changeover; average Airbnb cleaning fee about £55 (TaskRabbit UK, Airtasker, GuestReady 2026). Cleaner pay ≈ £16/hr. | L28: Equipment
L29: Accountant
L30: Bank fees
L31: Training
L32: Other
